Workbook

Sheet 本金与余额
B2: 序号 | C2: 姓名 | D2: R/H | E2: R/H余额
B3: 1 | C3: 徐伟伟 | D3: 1000000
B4: 2 | C4: 何凤 | D4: 1000000
B5: 3 | C5: 钟荣辉 | D5: 1000000
B6: 4 | C6: 宋倩 | D6: 1000000
B7: 5 | C7: 张咏博 | D7: 1000000
B8: 6 | C8: 钱虹语 | D8: 1000000
B9: 7 | C9: 邹俊峰 | D9: 1000000
B10: 8 | C10: 骆怡锋 | D10: 1000000
B11: 9 | C11: 王金花 | D11: 1000000
B12: 10 | C12: 顺道 | D12: 1000000
B13: 11 | C13: 候闯振 | D13: 1000000
B14: 12 | C14: 周金英 | D14: 1000000
... B38: 36 | C38: 李生 | D38: 1000000

Sheet 伟伟
A1: back | D1: 操盘：徐伟伟
D2: 时间 | E2: 市场 | F2: 企业 | G2: 股票代码 | H2: 操作 | I2: 数量 | J2: 平均买价 | K2: 成本 | L2: 买卖价格 | M2: 市值
C3: 1 | D3: 45136 | E3: HK | F3: 腾讯集团 | G3: 00700 | H3: 买入 | I3: 200 | L3: 350.4 | M3: =L3*I3 -> 70080
C4: 2 | D4: 45171 | E4: HK | F4: 腾讯集团 | G4: 00700 | H4: 卖出 | I4: -200 | L4: 325 | M4: =L4*I4 -> -65000
C5: 3 | D5: 45136 | E5: HK | F5: 东方甄选 | G5: 1797 | H5: 买入 | I5: 1000 | L5: 38.9 | M5: =L5*I5 -> 38900
C6: 4 | D6: 45290 | E6: HK | F6: 东方甄选 | G6: 1797 | H6: 卖出 | I6: -1000 | L6: 27.8 | M6: =L6*I6 -> -27800
C7: 5 | D7: 45171 | E7: HK | F7: 东方甄选 | G7: 1797 | H7: 买入 | I7: 500 | L7: 39.75 | M7: =L7*I7 -> 19875
C8: 6 | D8: 45241 | E8: HK | F8: 东方甄选 | G8: 1797 | H8: 卖出 | I8: -500 | L8: 29.6 | M8: =L8*I8 -> -14800
C9: 7 | D9: 45150 | E9: HK | F9: 京东集团 | G9: 9618 | H9: 买入 | I9: 1000 | L9: 146.1 | M9: =L9*I9 -> 146100
C10: 8 | D10: 45241 | E10: HK | F10: 京东集团 | G10: 9618 | H10: 卖出 | I10: -400 | L10: 99 | M10: =L10*I10 -> -39600
C11: 9 | D11: 45346 | E11: HK | F11: 京东集团 | G11: 9618 | H11: 卖出 | I11: -600 | L11: 93.75 | M11: =L11*I11 -> -56250
C12: 10 | D12: 45136 | E12: HK | F12: 比亚迪 | G12: 1211 | H12: 买入 | I12: 200 | L12: 271.2 | M12: =L12*I12 -> 54240
C13: 11 | D13: 45346 | E13: HK | F13: 比亚迪 | G13: 1211 | H13: 卖出 | I13: -200 | L13: 185.2 | M13: =L13*I13 -> -37040
C14: 12 | D14: 45150 | E14: HK | F14: 舜宇光学科技 | G14: 2382 | H14: 买入 | I14: 2382 | L14: 68.95 | M14: =L14*I14 -> 164238.9
C15: 13 | D15: 45171 | E15: HK | F15: 舜宇光学科技 | G15: 2382 | H15: 买入 | I15: 500 | L15: 64.1 | M15: =L15*I15 -> 32050
C16: 14 | D16: 45353 | E16: HK | F16: 舜宇光学科技 | G16: 2382 | H16: 卖出 | I16: -2882 | L16: 50.9 | M16: =L16*I16 -> -146693.8
C17: 15 | D17: 45213 | E17: US | F17: 小鹏汽车 | G17: XPEV | H17: 买入 | I17: 500 | L17: 125.892 | M17: =L17*I17 -> 62946
C18: 16 | D18: 45360 | E18: US | F18: 小鹏汽车 | G18: XPEV | H18: 卖出 | I18: -500 | L18: 74.256 | M18: =L18*I18 -> -37128
C19: 20 | D19: 45241 | E19: CN | F19: 爱美客 | G19: 300896 | H19: 买入 | I19: 500 | L19: 326.85 | M19: =L19*I19 -> 163425
D20: 45416 | E20: CN | F20: 爱美客 | G20: 300896 | H20: 送 | I20: 200 | L20: 0 | M20: =L20*I20 -> 0
D21: 45423 | E21: CN | F21: 爱美客 | G21: 300896 | H21: 卖出 | I21: -700 | L21: 215.54 | M21: =L21*I21 -> -150878
D22: 45423 | E22: US | F22: 极氪 | G22: ZK | H22: 买入 | I22: 80 | L22: 220.428 | M22: =L22*I22 -> 17634.24
D23: 45430 | E23: US | F23: 极氪 | G23: ZK | H23: 卖出 | I23: -80 | L23: 202.8 | M23: =L23*I23 -> -16224
D24: 45430 | E24: HK | F24: 中国中免 | G24: 1880 | H24: 买入 | I24: 200 | L24: 74.6 | M24: =L24*I24 -> 14920
D25: 45451 | E25: HK | F25: 中国中免 | G25: 1880 | H25: 卖出 | I25: -200 | L25: 63.1 | M25: =L25*I25 -> -12620
D26: 45430 | E26: US | F26: 亚马逊 | G26: AMZN | H26: 买入 | I26: 20 | L26: 1440.66 | M26: =L26*I26 -> 28813.2
D27: 45458 | E27: US | F27: 亚马逊 | G27: AMZN | H27: 卖出 | I27: -10 | L27: 1432.548 | M27: =L27*I27 -> -14325.48
D28: 45472 | E28: US | F28: 亚马逊 | G28: AMZN | H28: 卖出 | I28: -10 | L28: 1507.35 | M28: =L28*I28 -> -15073.5
D29: 45430 | E29: US | F29: 谷歌 | G29: GOOGL | H29: 买入 | I29: 30 | L29: 1373.268 | M29: =L29*I29 -> 41198.04
D30: 45451 | E30: US | F30: 微软 | G30: MSFT | H30: 买入 | I30: 12 | L30: 3306.03 | M30: =L30*I30 -> 39672.36
D31: 45486 | E31: US | F31: 微软 | G31: MSFT | H31: 买入 | I31: 2 | L31: 3537.69 | M31: =L31*I31 -> 7075.38
D32: 45493 | E32: US | F32: 微软 | G32: MSFT | H32: 卖出 | I32: -14 | L32: 3409.458 | M32: =L32*I32 -> -47732.412
D33: 45556 | E33: US | F33: 微软 | G33: MSFT | H33: 买入 | I33: 13 | L33: 3395.106 | M33: =L33*I33 -> 44136.378
D34: 45577 | E34: US | F34: 微软 | G34: MSFT | H34: 卖出 | I34: -5 | L34: 3247.296 | M34: =L34*I34 -> -16236.48
D35: 45633 | E35: US | F35: 微软 | G35: MSFT | H35: 卖出 | I35: -8 | L35: 3459.846 | M35: =L35*I35 -> -27678.768
D36: 45633 | E36: US | F36: 谷歌 | G36: GOOGL | H36: 卖出 | I36: -30 | L36: 1362.738 | M36: =L36*I36 -> -40882.14
C37: 17 | D37: 45136 | E37: US | F37: 拼多多 | G37: PDD | H37: 买入 | I37: 50 | L37: 696.93 | M37: =L37*I37 -> 34846.5
C38: 18 | D38: 45241 | E38: US | F38: 诺和诺德 | G38: NVO | H38: 买入 | I38: 150 | L38: 789.282 | M38: =L38*I38 -> 118392.3
C39: 19 | D39: 45241 | E39: CN | F39: 宁德时代 | G39: 300750 | H39: 买入 | I39: 800 | L39: 189.03 | M39: =L39*I39 -> 151224
C40: 21 | D40: 45290 | E40: US | F40: 拼多多 | G40: PDD | H40: 买入 | I40: 30 | L40: 1141.218 | M40: =L40*I40 -> 34236.54
C41: 22 | D41: 45346 | E41: US | F41: 拼多多 | G41: PDD | H41: 买入 | I41: 120 | L41: 995.982 | M41: =L41*I41 -> 119517.84
C42: 23 | D42: 45353 | E42: CN | F42: 宁德时代 | G42: 300750 | H42: 卖出 | I42: -400 | L42: 164.55 | M42: =L42*I42 -> -65820
C43: 27 | D43: 45409 | E43: CN | F43: 宁德时代 | G43: 300750 | H43: 卖出 | I43: -400 | L43: 198.48 | M43: =L43*I43 -> -79392
D44: 45493 | E44: US | F44: 诺和诺德 | G44: NVO | H44: 卖出 | I44: -100 | L44: 1026.012 | M44: =L44*I44 -> -102601.2
D45: 45556 | E45: US | F45: 诺和诺德 | G45: NVO | H45: 卖出 | I45: -20 | L45: 994.578 | M45: =L45*I45 -> -19891.56
D46: 45563 | E46: US | F46: 诺和诺德 | G46: NVO | H46: 卖出 | I46: -30 | L46: 941.928 | M46: =L46*I46 -> -28257.84
D47: 45556 | E47: US | F47: 拼多多 | G47: PDD | H47: 卖出 | I47: -50 | L47: 779.22 | M47: =L47*I47 -> -38961
D48: 45430 | E48: US | F48: 拼多多 | G48: PDD | H48: 卖出 | I48: -100 | L48: 1140.282 | M48: =L48*I48 -> -114028.2
D49: 45423 | E49: US | F49: 拼多多 | G49: PDD | H49: 卖出 | I49: -50 | L49: 1062.906 | M49: =L49*I49 -> -53145.3
C50: 24 | D50: 45353 | E50: US | F50: 英伟达 | G50: NVDA | H50: 买入 | I50: 15 | L50: 6417.762 | M50: =L50*I50 -> 96266.43
C51: 25 | D51: 45353 | E51: US | F51: 脸书 | G51: Meta | H51: 买入 | I51: 15 | L51: 3917.94 | M51: =L51*I51 -> 58769.1
C52: 26 | D52: 45360 | E52: US | F52: 英伟达 | G52: NVDA | H52: 买入 | I52: 15 | L52: 6827.184 | M52: =L52*I52 -> 102407.76
C53: 28 | D53: 45409 | E53: US | F53: 特斯拉 | G53: TSLA | H53: 买入 | I53: 69 | L53: 1312.662 | M53: =L53*I53 -> 90573.678
D54: 45423 | E54: US | F54: 脸书 | G54: Meta | H54: 买入 | I54: 15 | L54: 3714.36 | M54: =L54*I54 -> 55715.4
D55: 45423 | E55: US | F55: 特斯拉 | G55: TSLA | H55: 买入 | I55: 11 | L55: 1314.066 | M55: =L55*I55 -> 14454.726
D56: 45423 | E56: US | F56: 超微电脑 | G56: SMCI | H56: 买入 | I56: 8 | L56: 6228.3 | M56: =L56*I56 -> 49826.4
D57: 45423 | E57: US | F57: 台积电 | G57: TSM | H57: 买入 | I57: 30 | L57: 1164.228 | M57: =L57*I57 -> 34926.84
D58: 45430 | E58: US | F58: 特斯拉 | G58: TSLA | H58: 买入 | I58: 28 | L58: 1384.188 | M58: =L58*I58 -> 38757.264
D59: 45430 | E59: US | F59: 超微电脑 | G59: SMCI | H59: 买入 | I59: 5 | L59: 6925.542 | M59: =L59*I59 -> 34627.71
D60: 45451 | E60: US | F60: 超微电脑 | G60: SMCI | H60: 卖出 | I60: -2 | L60: 5999.058 | M60: =L60*I60 -> -11998.116
D61: 45451 | E61: US | F61: 台积电 | G61: TSM | H61: 买入 | I61: 10 | L61: 1282.242 | M61: =L61*I61 -> 12822.42
D62: 45451 | E62: US | F62: 特斯拉 | G62: TSLA | H62: 卖出 | I62: -18 | L62: 1384.344 | M62: =L62*I62 -> -24918.192
D63: 45458 | E63: US | F63: 英伟达 | G63: NVDA | H63: 拆分 | I63: 270 | L63: 0 | M63: =L63*I63 -> 0
D64: 45458 | E64: US | F64: 超微电脑 | G64: SMCI | H64: 卖出 | I64: -3 | L64: 6587.412 | M64: =L64*I64 -> -19762.236
D65: 45458 | E65: US | F65: 脸书 | G65: Meta | H65: 卖出 | I65: -10 | L65: 3932.448 | M65: =L65*I65 -> -39324.48
... D75: 45500 | E75: US | F75: 超微电脑 | G75: SMCI | H75: 买入 | I75: 5 | L75: 5555.082 | M75: =L75*I75 -> 27775.41
D76: 45500 | E76: US | F76: 台积电 | G76: TSM | H76: 买入 | I76: 13 | L76: =VLOOKUP(G76,股价!C:D,2,FALSE) -> 2253.81 | M76: =L76*I76 -> 29299.53
D77: 45556 | E77: US | F77: 英伟达 | G77: NVDA | H77: 卖出 | I77: -60 | L77: 904.8 | M77: =L77*I77 -> -54288
D78: 45556 | E78: US | F78: 特斯拉 | G78: TSLA | H78: 卖出 | I78: -18 | L78: 1858.35 | M78: =L78*I78 -> -33450.3
D79: 45556 | E79: US | F79: Crowdstrike Holdings | G79: CRWD | H79: 买入 | I79: 38 | L79: 2338.83 | M79: =L79*I79 -> 88875.54
D80: 45563 | E80: US | F80: 英伟达 | G80: NVDA | H80: 卖出 | I80: -40 | L80: 946.92 | M80: =L80*I80 -> -37876.8
D81: 45566 | E81: US | F81: 超微电脑 | G81: SMCI | H81: 拆股 | I81: 342 | M81: =L81*I81 -> 0
D82: 45577 | E82: US | F82: 特斯拉 | G82: TSLA | H82: 卖出 | I82: -15 | L82: 1698.84 | M82: =L82*I82 -> -25482.6
D83: 45577 | E83: US | F83: 英伟达 | G83: NVDA | H83: 卖出 | I83: -72 | L83: 1051.44 | M83: =L83*I83 -> -75703.68
D84: 45577 | E84: US | F84: 台积电 | G84: TSM | H84: 卖出 | I84: -20 | L84: 1488.318 | M84: =L84*I84 -> -29766.36
D85: 45577 | E85: US | F85: 礼来 | G85: LLY | H85: 卖出 | I85: -10 | L85: 7270.068 | M85: =L85*I85 -> -72700.68
D86: 45584 | E86: US | F86: 阿斯麦 | G86: ASML | H86: 买入 | I86: 48 | L86: 5641.428 | M86: =L86*I86 -> 270788.54
D87: 45584 | E87: US | F87: 台积电 | G87: TSM | H87: 买入 | I87: 25 | L87: 1566.084 | M87: =L87*I87 -> 39152.1
D88: 45689 | E88: US | F88: 超微电脑 | G88: SMCI | H88: 卖出 | I88: -80 | L88: 222.456 | M88: =L88*I88 -> -17796.48
D89: 45689 | E89: US | F89: 英伟达 | G89: NVDA | H89: 买入 | I89: 20 | L89: 936.546 | M89: =L89*I89 -> 18730.92
D90: 45689 | E90: US | F90: 特斯拉 | G90: TSLA | H90: 买入 | I90: 20 | L90: 3155.88 | M90: =L90*I90 -> 63117.6
D91: 45738 | E91: US | F91: Crowdstrike Holdings | G91: CRWD | H91: 卖出 | I91: -38 | L91: 2825.472 | M91: =L91*I91 -> -107367.94
D92: 45738 | E92: US | F92: 礼来 | G92: LLY | H92: 卖出 | I92: -8 | L92: 6533.046 | M92: =L92*I92 -> -52264.368
D93: 45738 | E93: US | F93: Robinhood Market | G93: HOOD | H93: 买入 | I93: 100 | L93: 346.008 | M93: =L93*I93 -> 34600.8
... D121: 45983 | E121: US | F121: Circle Internet Group.Inc. | G121: CRCL | H121: 买入 | I121: 80 | L121: 556.374 | M121: =L121*I121 -> 44509.92
M122: =L122*I122 -> 0
D123: 累计净买入 | M123: =SUM(M3:M122) -> 791434.35
D124: 时间 | E124: 市场 | F124: 企业 | G124: 股票代码 | H124: 状态 | I124: 数量 | J124: 平均买价 | K124: 成本 | L124: 当前价格 | M124: 市值
D125: =全班!$R$1 -> 46011 | E125: US | F125: 英伟达 | G125: NVDA | H125: 持有 | I125: =SUMIFS($I$50:$I$123,$G$50:$G$123,G125) -> 58 | J125: =K125/I125 -> -1131.8136 | K125: =SUMIFS($M$50:$M$123,$G$50:$G$123,G125) -> -65645.19 | L125: =VLOOKUP(G125,股价!C:D,2,FALSE) -> 1411.722 | M125: =IFERROR(I125*L125,0) -> 81879.876
D126: =全班!$R$1 -> 46011 | E126: US | F126: 脸书 | G126: Meta | H126: 持有 | I126: =SUMIFS($I$50:$I$123,$G$50:$G$123,G126) -> 23 | J126: =K126/I126 -> 3218.5852 | K126: =SUMIFS($M$50:$M$123,$G$50:$G$123,G126) -> 74027.46 | L126: =VLOOKUP(G126,股价!C:D,2,FALSE) -> 5138.406 | M126: =IFERROR(I126*L126,0) -> 118183.34
D127: =全班!$R$1 -> 46011 | E127: US | F127: 特斯拉 | G127: TSLA | H127: 持有 | I127: =SUMIFS($I$50:$I$123,$G$50:$G$123,G127) -> 98 | J127: =K127/I127 -> 2022.9021 | K127: =SUMIFS($M$50:$M$123,$G$50:$G$123,G127) -> 198244.41 | L127: =VLOOKUP(G127,股价!C:D,2,FALSE) -> 3753.36 | M127: =IFERROR(I127*L127,0) -> 367829.28
D128: =全班!$R$1 -> 46011 | E128: US | F128: 超微电脑 | G128: SMCI | H128: 持有 | I128: =SUMIFS($I$50:$I$123,$G$50:$G$123,G128) -> 15 | J128: =K128/I128 -> 7534.8572 | K128: =SUMIFS($M$50:$M$123,$G$50:$G$123,G128) -> 113022.86 | L128: =VLOOKUP(G128,股价!C:D,2,FALSE) -> 242.658 | M128: =IFERROR(I128*L128,0) -> 3639.87
D129: =全班!$R$1 -> 46011 | E129: US | F129: 台积电 | G129: TSM | H129: 持有 | I129: =SUMIFS($I$50:$I$123,$G$50:$G$123,G129) -> 28 | J129: =K129/I129 -> 873.39107 | K129: =SUMIFS($M$50:$M$123,$G$50:$G$123,G129) -> 24454.95 | L129: =VLOOKUP(G129,股价!C:D,2,FALSE) -> 2253.81 | M129: =IFERROR(I129*L129,0) -> 63106.68
D130: =全班!$R$1 -> 46011 | E130: US | F130: 阿斯麦 | G130: ASML | H130: 持有 | I130: =SUMIFS($I$50:$I$123,$G$50:$G$123,G130) -> 28 | J130: =K130/I130 -> 5236.4409 | K130: =SUMIFS($M$50:$M$123,$G$50:$G$123,G130) -> 146620.34 | L130: =VLOOKUP(G130,股价!C:D,2,FALSE) -> 8236.956 | M130: =IFERROR(I130*L130,0) -> 230634.77
D131: =全班!$R$1 -> 46011 | E131: US | F131: Robinhood Market | G131: HOOD | H131: 持有 | I131: =SUMIFS($I$50:$I$123,$G$50:$G$123,G131) -> 50 | J131: =K131/I131 -> 44.382 | K131: =SUMIFS($M$50:$M$123,$G$50:$G$123,G131) -> 2219.1 | L131: =VLOOKUP(G131,股价!C:D,2,FALSE) -> 946.53 | M131: =IFERROR(I131*L131,0) -> 47326.5
D132: =全班!$R$1 -> 46011 | E132: US | F132: 博通 | G132: AVGO | H132: 持有 | I132: =SUMIFS($I$50:$I$123,$G$50:$G$123,G132) -> 8 | J132: =K132/I132 -> -266.98425 | K132: =SUMIFS($M$50:$M$123,$G$50:$G$123,G132) -> -2135.874 | L132: =VLOOKUP(G132,股价!C:D,2,FALSE) -> 2654.808 | M132: =IFERROR(I132*L132,0) -> 21238.464
D133: =全班!$R$1 -> 46011 | E133: US | F133: applovin corporation | G133: APP | H133: 持有 | I133: =SUMIFS($I$50:$I$123,$G$50:$G$123,G133) -> 18 | J133: =K133/I133 -> -133.536 | K133: =SUMIFS($M$50:$M$123,$G$50:$G$123,G133) -> -2403.648 | L133: =VLOOKUP(G133,股价!C:D,2,FALSE) -> 5626.686 | M133: =IFERROR(I133*L133,0) -> 101280.35
D134: =全班!$R$1 -> 46011 | E134: US | F134: 谷歌 | G134: GOOGL | H134: 持有 | I134: =SUMIFS($I$50:$I$123,$G$50:$G$123,G134) -> 30 | J134: =K134/I134 -> 2410.408 | K134: =SUMIFS($M$50:$M$123,$G$50:$G$123,G134) -> 72312.24 | L134: =VLOOKUP(G134,股价!C:D,2,FALSE) -> 2395.848 | M134: =IFERROR(I134*L134,0) -> 71875.44
D135: =全班!$R$1 -> 46011 | E135: US | F135: Coinbase Global | G135: COIN | H135: 持有 | I135: =SUMIFS($I$50:$I$123,$G$50:$G$123,G135) -> 30 | J135: =K135/I135 -> 1875.198 | K135: =SUMIFS($M$50:$M$123,$G$50:$G$123,G135) -> 56255.94 | L135: =VLOOKUP(G135,股价!C:D,2,FALSE) -> 1911.936 | M135: =IFERROR(I135*L135,0) -> 57358.08
D136: =全班!$R$1 -> 46011 | E136: US | F136: Circle Internet Group.Inc. | G136: CRCL | H136: 持有 | I136: =SUMIFS($I$50:$I$123,$G$50:$G$123,G136) -> 80 | J136: =K136/I136 -> 556.374 | K136: =SUMIFS($M$50:$M$123,$G$50:$G$123,G136) -> 44509.92 | L136: =VLOOKUP(G136,股价!C:D,2,FALSE) -> 671.814 | M136: =IFERROR(I136*L136,0) -> 53745.12
...

Sheet 何凤
A1: back | D1: 操盘：何凤
D2: 时间 | E2: 市场 | F2: 企业 | G2: 股票代码 | H2: 操作 | I2: 数量 | J2: 平均买价 | K2: 成本 | L2: 买卖价格 | M2: 市值
D3: 45479 | E3: CN | F3: 百纳千成 | G3: 300291 | H3: 卖出 | I3: -1000 | L3: 4.2 | M3: =L3*I3 -> -4200
C4: 3 | D4: 45241 | E4: CN | F4: 百纳千成 | G4: 300291 | H4: 买入 | I4: 5000 | L4: 7.81 | M4: =L4*I4 -> 39050
C5: 6 | D5: 45402 | E5: CN | F5: 百纳千成 | G5: 300291 | H5: 卖出 | I5: -4000 | L5: 4.56 | M5: =L5*I5 -> -18240
C6: 8 | D6: 45402 | E6: HK | F6: 理想汽车 | G6: 2015 | H6: 卖出 | I6: -500 | L6: 106.3 | M6: =L6*I6 -> -53150
C7: 4 | D7: 45304 | E7: HK | F7: 理想汽车 | G7: 2015 | H7: 买入 | I7: 1000 | L7: 126.1 | M7: =L7*I7 -> 126100
D8: 45479 | E8: HK | F8: 理想汽车 | G8: 2015 | H8: 卖出 | I8: -500 | L8: 79.25 | M8: =L8*I8 -> -39625
D9: 45479 | E9: CN | F9: 贝肯能源 | G9: 002828 | H9: 卖出 | I9: -500 | L9: 8.37 | M9: =L9*I9 -> -4185
D10: 45402 | E10: CN | F10: 贝肯能源 | G10: 002828 | H10: 买入 | I10: 500 | L10: 11.69 | M10: =L10*I10 -> 5845
D11: 45402 | E11: CN | F11: 中信海直 | G11: 000099 | H11: 买入 | I11: 500 | L11: 22.26 | M11: =L11*I11 -> 11130
D12: 45479 | E12: CN | F12: 中信海直 | G12: 000099 | H12: 卖出 | I12: -500 | L12: 15.46 | M12: =L12*I12 -> -7730
C13: 1 | D13: 45150 | E13: CN | F13: 比亚迪 | G13: 002594 | H13: 买入 | I13: 2000 | L13: 259.25 | M13: =L13*I13 -> 518500
C14: 2 | D14: 45192 | E14: CN | F14: 比亚迪 | G14: 002594 | H14: 买入 | I14: 500 | L14: 245.05 | M14: =L14*I14 -> 122525
C15: 5 | D15: 45402 | E15: CN | F15: 比亚迪 | G15: 002594 | H15: 卖出 | I15: -1000 | L15: 210.13 | M15: =L15*I15 -> -210130
D16: 45402 | E16: US | F16: 特斯拉 | G16: TSLA | H16: 买入 | I16: 100 | L16: 1146.99 | M16: =L16*I16 -> 114699
C17: 9 | D17: 45402 | E17: CN | F17: 赛力斯 | G17: 601127 | H17: 买入 | I17: 2000 | L17: 95.48 | M17: =L17*I17 -> 190960
D18: 45430 | E18: US | F18: 强生 | G18: JNJ | H18: 买入 | I18: 100 | L18: 1206.192 | M18: =L18*I18 -> 120619.2
D19: 45514 | E19: US | F19: 特斯拉 | G19: TSLA | H19: 买入 | I19: 50 | L19: 1560 | M19: =L19*I19 -> 78000
D20: 45535 | E20: CN | F20: 比亚迪 | G20: 002594 | H20: 卖出 | I20: -1500 | L20: 249.42 | M20: =L20*I20 -> -374130
D21: 45535 | E21: US | F21: 特斯拉 | G21: TSLA | H21: 卖出 | I21: -150 | L21: 1670.058 | M21: =L21*I21 -> -250508.7
D22: 45535 | E22: CN | F22: 赛力斯 | G22: 601127 | H22: 卖出 | I22: -2000 | L22: 76.52 | M22: =L22*I22 -> -153040
D23: 45535 | E23: US | F23: 强生 | G23: JNJ | H23: 卖出 | I23: -100 | L23: 1293.708 | M23: =L23*I23 -> -129370.8
D24: 45535 | E24: CN | F24: 日久光电 | G24: 003015 | H24: 买入 | I24: 33000 | L24: 13.22 | M24: =L24*I24 -> 436260
D25: 45535 | E25: CN | F25: 奋达科技 | G25: 002681 | H25: 买入 | I25: 72700 | L25: 4.81 | M25: =L25*I25 -> 349687
D26: 45535 | E26: CN | F26: 科森科技 | G26: 603626 | H26: 买入 | I26: 15948 | L26: 8.21 | M26: =L26*I26 -> 130933.08
D27: 45542 | E27: CN | F27: 日久光电 | G27: 003015 | H27: 卖出 | I27: -33000 | L27: 11.87 | M27: =L27*I27 -> -391710
D28: 45542 | E28: CN | F28: 奋达科技 | G28: 002681 | H28: 卖出 | I28: -72700 | L28: 4 | M28: =L28*I28 -> -290800
D29: 45542 | E29: CN | F29: 大众交通 | G29: 600611 | H29: 买入 | I29: 43995 | L29: 11.44 | M29: =L29*I29 -> 503302.8
... D107: 46011 | E107: CN | F107: 航天发展 | G107: 000547 | H107: 买入 | I107: 9000 | L107: 22.3 | M107: =L107*I107 -> 200700
M108: =L108*I108 -> 0
M109: =L109*I109 -> 0
M110: =L110*I110 -> 0
M111: =L111*I111 -> 0
D112: 累计净买入 | M112: =SUM(M3:M111) -> 999652.18
D113: 时间 | E113: 市场 | F113: 企业 | G113: 股票代码 | H113: 状态 | I113: 数量 | J113: 平均买价 | K113: 成本 | L113: 当前价格 | M113: 市值
D114: =全班!$R$1 -> 46011 | E114: US | F114: 英伟达 | G114: NVDA | H114: 持有 | I114: =SUMIFS($I$99:$I$112,$G$99:$G$112,G114) -> 200 | J114: =K114/I114 -> 1380.6 | K114: =SUMIFS($M$99:$M$111,$G$99:$G$111,G114) -> 276120 | L114: =VLOOKUP(G114,股价!C:D,2,FALSE) -> 1411.722 | M114: =IFERROR(I114*L114,0) -> 282344.4
D115: =全班!$R$1 -> 46011 | E115: US | F115: 小鹏汽车 | G115: XPEV | H115: 持有 | I115: =SUMIFS($I$99:$I$112,$G$99:$G$112,G115) -> 1000 | J115: =K115/I115 -> 148.122 | K115: =SUMIFS($M$99:$M$111,$G$99:$G$111,G115) -> 148122 | L115: =VLOOKUP(G115,股价!C:D,2,FALSE) -> 154.908 | M115: =IFERROR(I115*L115,0) -> 154908
D116: =全班!$R$1 -> 46011 | E116: CN | F116: 航天电机 | G116: 600151 | H116: 持有 | I116: =SUMIFS($I$99:$I$112,$G$99:$G$112,G116) -> 5000 | J116: =K116/I116 -> 15.4 | K116: =SUMIFS($M$99:$M$111,$G$99:$G$111,G116) -> 77000 | L116: =VLOOKUP(G116,股价!C:D,2,FALSE) -> 18.88 | M116: =IFERROR(I116*L116,0) -> 94400
D117: =全班!$R$1 -> 46011 | E117: CN | F117: 海南瑞泽 | G117: 002596 | H117: 持有 | I117: =SUMIFS($I$99:$I$112,$G$99:$G$112,G117) -> 40500 | J117: =K117/I117 -> 5.35 | K117: =SUMIFS($M$99:$M$111,$G$99:$G$111,G117) -> 216675 | L117: =VLOOKUP(G117,股价!C:D,2,FALSE) -> 5.35 | M117: =IFERROR(I117*L117,0) -> 216675
D118: =全班!$R$1 -> 46011 | E118: CN | F118: 航天发展 | G118: 000547 | H118: 持有 | I118: =SUMIFS($I$99:$I$112,$G$99:$G$112,G118) -> 9000 | J118: =K118/I118 -> 22.3 | K118: =SUMIFS($M$99:$M$111,$G$99:$G$111,G118) -> 200700 | L118: =VLOOKUP(G118,股价!C:D,2,FALSE) -> 22.3 | M118: =IFERROR(I118*L118,0) -> 200700
D119: =全班!$R$1 -> 46011 | H119: 持有 | I119: =SUMIFS($I$99:$I$112,$G$99:$G$112,G119) -> 0 | J119: =K119/I119 -> #DIV/0! | K119: =SUMIFS($M$99:$M$111,$G$99:$G$111,G119) -> 0 | L119: =VLOOKUP(G119,股价!C:D,2,FALSE) -> #N/A | M119: =IFERROR(I119*L119,0) -> 0
M120: =IFERROR(I120*L120,0) -> 0
D121: 市值结余 | M121: =SUM(M114:M120) -> 949027.4
D122: 累计分红 | M122: =L137 -> 0
D123: 现金结余 | M123: =M128-M112+M122 -> 347.82
D124: 结余总额 | M124: =M121+M123 -> 949375.22
D125: 累计盈利 | M125: =M124-M128 -> -50624.78
D126: 盈利率 | M126: =M125/M128 -> -0.05062478
D128: 本金 | M128: =本金与余额!D4 -> 1000000
D129: 登记日 | E129: 市场 | F129: 企业 | G129: 股票代码 | H129: 状态 | I129: 数量 | J129: 分红方案 | K129: 实施 | L129: 红利金额 | M129: 除权日
D137: 累计分红 | L137: =SUM(L130:L136) -> 0

Sheet 荣辉 
A1: back | D1: 操盘：钟荣辉
D2: 时间 | E2: 市场 | F2: 企业 | G2: 股票代码 | H2: 操作 | I2: 数量 | J2: 平均买价 | K2: 成本 | L2: 买卖价格 | M2: 市值
C3: 2 | D3: 45164 | E3: HK | F3: 东方甄选 | G3: 1797 | H3: 买入 | I3: 1000 | L3: 43.15 | M3: =L3*I3 -> 43150
C4: 6 | D4: 45227 | E4: HK | F4: 东方甄选 | G4: 1797 | H4: 卖出 | I4: -500 | L4: 32.4 | M4: =L4*I4 -> -16200
C5: 9 | D5: 45227 | E5: HK | F5: 李宁 | G5: 2331 | H5: 买入 | I5: 500 | L5: 24.9 | M5: =L5*I5 -> 12450
C6: 10 | D6: 45234 | E6: HK | F6: 小米集团 | G6: 1810 | H6: 买入 | I6: 10000 | L6: 15.24 | M6: =L6*I6 -> 152400
C7: 12 | D7: 45276 | E7: HK | F7: 东方甄选 | G7: 1797 | H7: 买入 | I7: 500 | L7: 26.25 | M7: =L7*I7 -> 13125
D8: 45367 | E8: HK | F8: 东方甄选 | G8: 1797 | H8: 卖出 | I8: -1000 | L8: 23.9 | M8: =L8*I8 -> -23900
D9: 45367 | E9: HK | F9: 李宁 | G9: 2331 | H9: 卖出 | I9: -500 | L9: 20.7 | M9: =L9*I9 -> -10350
D10: 45367 | E10: HK | F10: 小米集团 | G10: 1810 | H10: 卖出 | I10: -10000 | L10: 14.54 | M10: =L10*I10 -> -145400
C11: 8 | D11: 45227 | E11: CN | F11: 赛力斯 | G11: 601127 | H11: 买入 | I11: 500 | L11: 79.81 | M11: =L11*I11 -> 39905
C12: 11 | D12: 45234 | E12: HK | F12: 中兴通讯 | G12: 763 | H12: 买入 | I12: 2000 | L12: 18.04 | M12: =L12*I12 -> 36080
D13: 45367 | E13: CN | F13: 赛力斯 | G13: 601127 | H13: 卖出 | I13: -500 | L13: 98.45 | M13: =L13*I13 -> -49225
D14: 45367 | E14: HK | F14: 中兴通讯 | G14: 763 | H14: 卖出 | I14: -2000 | L14: 17.12 | M14: =L14*I14 -> -34240
C15: 5 | D15: 45192 | E15: US | F15: 可口可乐 | G15: KO | H15: 买入 | I15: 500 | L15: 449.28 | M15: =L15*I15 -> 224640
D16: 45374 | E16: US | F16: 可口可乐 | G16: KO | H16: 卖出 | I16: -300 | L16: 471.822 | M16: =L16*I16 -> -141546.6
D17: 45409 | E17: US | F17: 可口可乐 | G17: KO | H17: 卖出 | I17: -100 | L17: 481.572 | M17: =L17*I17 -> -48157.2
D18: 45437 | E18: US | F18: 可口可乐 | G18: KO | H18: 卖出 | I18: -100 | L18: 483.6 | M18: =L18*I18 -> -48360
C19: 1 | D19: 45164 | E19: CN | F19: 比亚迪 | G19: 002594 | H19: 买入 | I19: 1000 | L19: 232.6 | M19: =L19*I19 -> 232600
D20: 45374 | E20: CN | F20: 比亚迪 | G20: 002594 | H20: 卖出 | I20: -1000 | L20: 216.95 | M20: =L20*I20 -> -216950
C21: 3 | D21: 45178 | E21: US | F21: 京东 | G21: JD | H21: 买入 | I21: 500 | L21: 252.72 | M21: =L21*I21 -> 126360
C22: 4 | D22: 45185 | E22: US | F22: 京东 | G22: JD | H22: 买入 | I22: 500 | L22: 246.246 | M22: =L22*I22 -> 123123
C23: 7 | D23: 45227 | E23: US | F23: 京东 | G23: JD | H23: 卖出 | I23: -500 | L23: 200.07 | M23: =L23*I23 -> -100035
D24: 45374 | E24: US | F24: 京东 | G24: JD | H24: 卖出 | I24: -500 | L24: 206.7 | M24: =L24*I24 -> -103350
D25: 45367 | E25: US | F25: 特斯拉 | G25: TSLA | H25: 买入 | I25: 50 | L25: 1275.846 | M25: =L25*I25 -> 63792.3
D26: 45367 | E26: US | F26: 拼多多 | G26: PDD | H26: 买入 | I26: 50 | L26: 965.172 | M26: =L26*I26 -> 48258.6
D27: 45367 | E27: US | F27: 英伟达 | G27: NVDA | H27: 买入 | I27: 20 | L27: 6851.286 | M27: =L27*I27 -> 137025.72
D28: 45367 | E28: US | F28: 谷歌-A | G28: GOOGL | H28: 买入 | I28: 50 | L28: 1101.204 | M28: =L28*I28 -> 55060.2
D29: 45367 | E29: US | F29: 脸书 | G29: Meta | H29: 买入 | I29: 10 | L29: 3775.98 | M29: =L29*I29 -> 37759.8
D30: 45374 | E30: US | F30: 英伟达 | G30: NVDA | H30: 买入 | I30: 10 | L30: 7354.542 | M30: =L30*I30 -> 73545.42
D31: 45374 | E31: US | F31: 脸书 | G31: Meta | H31: 买入 | I31: 20 | L31: 3974.724 | M31: =L31*I31 -> 79494.48
D32: 45374 | E32: US | F32: 阿斯麦 | G32: ASML | H32: 买入 | I32: 10 | L32: 7643.688 | M32: =L32*I32 -> 76436.88
D33: 45374 | E33: US | F33: 诺和诺德 | G33: NVO | H33: 买入 | I33: 50 | L33: 1004.328 | M33: =L33*I33 -> 50216.4
D34: 45374 | E34: US | F34: 高通 | G34: QCOM | H34: 买入 | I34: 30 | L34: 1326.78 | M34: =L34*I34 -> 39803.4
D35: 45374 | E35: US | F35: 台积电 | G35: TSM | H35: 买入 | I35: 30 | L35: 1096.212 | M35: =L35*I35 -> 32886.36
... D77: 45528 | E77: US | F77: 诺和诺德 | G77: NVO | H77: 卖出 | I77: -20 | L77: 1068.366 | M77: =L77*I77 -> -21367.32
D78: =全班!$R$1 -> 46011 | E78: US | F78: 高通 | G78: QCOM | H78: 买入 | I78: 20 | L78: 1404.39 | M78: =L78*I78 -> 28087.8
D79: 45528 | E79: US | F79: 高通 | G79: QCOM | H79: 卖出 | I79: -20 | L79: 1353.3 | M79: =L79*I79 -> -27066
D80: 45500 | E80: US | F80: 微软 | G80: MSFT | H80: 买入 | I80: 15 | L80: 3317.106 | M80: =L80*I80 -> 49756.59
D81: 45528 | E81: US | F81: 微软 | G81: MSFT | H81: 卖出 | I81: -15 | L81: 3250.962 | M81: =L81*I81 -> -48764.43
D82: 45500 | E82: US | F82: 亚马逊 | G82: AMZN | H82: 买入 | I82: 20 | L82: 1423.5 | M82: =L82*I82 -> 28470
D83: =全班!$R$1 -> 46011 | E83: US | F83: 亚马逊 | G83: AMZN | H83: 卖出 | I83: -20 | L83: 1380.912 | M83: =L83*I83 -> -27618.24
D84: 45500 | E84: US | F84: 超微电脑 | G84: SMCI | H84: 买入 | I84: 40 | L84: 5555.082 | M84: =L84*I84 -> 222203.28
D85: 45521 | E85: US | F85: 超微电脑 | G85: SMCI | H85: 买入 | I85: 9 | L85: 4904.64 | M85: =L85*I85 -> 44141.76
D86: 45566 | E86: US | F86: 超微电脑 | G86: SMCI | H86: 拆股 | I86: =490-49 -> 441 | M86: =L86*I86 -> 0
D87: 45619 | E87: US | F87: 超微电脑 | G87: SMCI | H87: 买入 | I87: 1156 | L87: 258.57 | M87: =L87*I87 -> 298906.92
D88: 45710 | E88: US | F88: 超微电脑 | G88: SMCI | H88: 卖出 | I88: -400 | L88: 437.346 | M88: =L88*I88 -> -174938.4
D89: 45717 | E89: US | F89: 超微电脑 | G89: SMCI | H89: 卖出 | I89: -200 | L89: 323.388 | M89: =L89*I89 -> -64677.6
D90: 45829 | E90: US | F90: 超微电脑 | G90: SMCI | H90: 卖出 | I90: -500 | L90: 353.496 | M90: =L90*I90 -> -176748
D91: 45857 | E91: US | F91: 超微电脑 | G91: SMCI | H91: 卖出 | I91: -546 | L91: 384.072 | M91: =L91*I91 -> -209703.31
D92: 45500 | E92: US | F92: 拼多多 | G92: PDD | H92: 买入 | I92: 20 | L92: 1020.24 | M92: =L92*I92 -> 20404.8
D93: 45710 | E93: US | F93: 拼多多 | G93: PDD | H93: 买入 | I93: 80 | L93: 1024.452 | M93: =L93*I93 -> 81956.16
D94: 45829 | E94: US | F94: 拼多多 | G94: PDD | H94: 买入 | I94: 50 | L94: 789.438 | M94: =L94*I94 -> 39471.9
D95: 45878 | E95: US | F95: 拼多多 | G95: PDD | H95: 卖出 | I95: -150 | L95: 891.228 | M95: =L95*I95 -> -133684.2
D96: 45717 | E96: US | F96: 爱芬奇 | G96: ANF | H96: 买入 | I96: 80 | L96: 803.322 | M96: =L96*I96 -> 64265.76
D97: 45878 | E97: US | F97: 爱芬奇 | G97: ANF | H97: 卖出 | I97: -80 | L97: 804.258 | M97: =L97*I97 -> -64340.64
D98: 45500 | E98: US | F98: 英伟达 | G98: NVDA | H98: 买入 | I98: 160 | L98: 881.868 | M98: =L98*I98 -> 141098.88
... D165: 46011 | E165: US | F165: 谷歌 | G165: GOOGL | H165: 买入 | I165: 10 | L165: 2395.848 | M165: =L165*I165 -> 23958.48
M166: =L166*I166 -> 0
M167: =L167*I167 -> 0
M168: =L168*I168 -> 0
D169: 累计净买入 | M169: =SUM(M3:M168) -> 213902.76
D170: 时间 | E170: 市场 | F170: 企业 | G170: 股票代码 | H170: 状态 | I170: 数量 | J170: 平均买价 | K170: 成本 | L170: 当前价格 | M170: 市值
D171: =全班!$R$1 -> 46011 | E171: US | F171: 脸书 | G171: Meta | H171: 持有 | I171: =SUMIFS($I$142:$I$168,$G$142:$G$168,G171) -> 30 | J171: =K171/I171 -> 4942.522 | K171: =SUMIFS($M$142:$M$168,$G$142:$G$168,G171) -> 148275.66 | L171: =VLOOKUP(G171,股价!C:D,2,FALSE) -> 5138.406 | M171: =IFERROR(I171*L171,0) -> 154152.18
D172: =全班!$R$1 -> 46011 | E172: US | F172: 台积电 | G172: TSM | H172: 持有 | I172: =SUMIFS($I$142:$I$168,$G$142:$G$168,G172) -> 30 | J172: =K172/I172 -> 2224.352 | K172: =SUMIFS($M$142:$M$168,$G$142:$G$168,G172) -> 66730.56 | L172: =VLOOKUP(G172,股价!C:D,2,FALSE) -> 2253.81 | M172: =IFERROR(I172*L172,0) -> 67614.3
D173: =全班!$R$1 -> 46011 | E173: US | F173: 英伟达 | G173: NVDA | H173: 持有 | I173: =SUMIFS($I$142:$I$168,$G$142:$G$168,G173) -> 30 | J173: =K173/I173 -> 1395.862 | K173: =SUMIFS($M$142:$M$168,$G$142:$G$168,G173) -> 41875.86 | L173: =VLOOKUP(G173,股价!C:D,2,FALSE) -> 1411.722 | M173: =IFERROR(I173*L173,0) -> 42351.66
D174: =全班!$R$1 -> 46011 | E174: US | F174: 特斯拉 | G174: TSLA | H174: 持有 | I174: =SUMIFS($I$142:$I$168,$G$142:$G$168,G174) -> 30 | J174: =K174/I174 -> 3386.396 | K174: =SUMIFS($M$142:$M$168,$G$142:$G$168,G174) -> 101591.88 | L174: =VLOOKUP(G174,股价!C:D,2,FALSE) -> 3753.36 | M174: =IFERROR(I174*L174,0) -> 112600.8
D175: =全班!$R$1 -> 46011 | E175: US | F175: 亚马逊 | G175: AMZN | H175: 持有 | I175: =SUMIFS($I$142:$I$168,$G$142:$G$168,G175) -> 30 | J175: =K175/I175 -> 1771.276 | K175: =SUMIFS($M$142:$M$168,$G$142:$G$168,G175) -> 53138.28 | L175: =VLOOKUP(G175,股价!C:D,2,FALSE) -> 1773.33 | M175: =IFERROR(I175*L175,0) -> 53199.9
D176: =全班!$R$1 -> 46011 | E176: US | F176: 微软 | G176: MSFT | H176: 持有 | I176: =SUMIFS($I$142:$I$168,$G$142:$G$168,G176) -> 30 | J176: =K176/I176 -> 3770.13 | K176: =SUMIFS($M$142:$M$168,$G$142:$G$168,G176) -> 113103.9 | L176: =VLOOKUP(G176,股价!C:D,2,FALSE) -> 3790.176 | M176: =IFERROR(I176*L176,0) -> 113705.28
D177: =全班!$R$1 -> 46011 | E177: US | F177: 苹果 | G177: AAPL | H177: 持有 | I177: =SUMIFS($I$142:$I$168,$G$142:$G$168,G177) -> 30 | J177: =K177/I177 -> 2142.426 | K177: =SUMIFS($M$142:$M$168,$G$142:$G$168,G177) -> 64272.78 | L177: =VLOOKUP(G177,股价!C:D,2,FALSE) -> 2134.626 | M177: =IFERROR(I177*L177,0) -> 64038.78
D178: =全班!$R$1 -> 46011 | E178: US | F178: 谷歌 | G178: GOOGL | H178: 持有 | I178: =SUMIFS($I$142:$I$168,$G$142:$G$168,G178) -> 30 | J178: =K178/I178 -> 2410.2 | K178: =SUMIFS($M$142:$M$168,$G$142:$G$168,G178) -> 72306 | L178: =VLOOKUP(G178,股价!C:D,2,FALSE) -> 2395.848 | M178: =IFERROR(I178*L178,0) -> 71875.44
D182: 市值结余 | M182: =SUM(M171:M181) -> 679538.34
D183: 累计分红 | M183: =L199 -> 735.6336
D184: 现金结余 | M184: =M189-M169+M183 -> 786832.88
D185: 结余总额 | M185: =M182+M184 -> 1466371.2
D186: 累计盈利 | M186: =M185-M189 -> 466371.22
D187: 盈利率 | M187: =M186/M189 -> 0.46637122
D189: 本金 | M189: =本金与余额!D5 -> 1000000
D190: 登记日 | E190: 市场 | F190: 企业 | G190: 股票代码 | H190: 状态 | I190: 数量 | J190: 分红方案 | K190: 实施 | L190: 红利金额 | M190: 除权日
D191: 45458 | E191: US | F191: 英伟达 | G191: NVDA | H191: 拆分 | I191: 30 | J191: 1拆10 | K191: 300
D192: 45453 | E192: US | F192: 谷歌-A | G192: GOOGL | H192: 分红 | I192: 50 | J192: 1派1.56 | K192: 1派1.56 | L192: =I192*1.56 -> 78 | M192: 45453
D193: 45566 | E193: US | F193: 超微电脑 | G193: SMCI | H193: 拆股 | I193: 49 | J193: 1拆10 | K193: =I193*10 -> 490 | M193: 45566
D194: 45594 | E194: US | F194: 阿斯麦 | G194: ASML | H194: 分红 | I194: 10 | J194: 1派1.395USD | K194: 1派1.395USD | L194: =I194*1.395*7.8 -> 108.81 | M194: 45594
D195: 45819 | E195: US | F195: 英伟达 | G195: NVDA | H195: 分红 | I195: 324 | J195: 1派0.01USD | K195: 1派0.01USD | L195: =I195*0.01*7.8 -> 25.272 | M195: 45819
D196: 45820 | E196: US | F196: 台积电 | G196: TSM | H196: 分红 | I196: 113 | J196: 1派0.594USD | K196: 1派0.594USD | L196: =I196*0.594*7.8 -> 523.5516 | M196: 45820
D199: 累计分红 | L199: =SUM(L191:L198) -> 735.6336

Sheet 宋倩
A1: back | D1: 操盘：宋倩
D2: 时间 | E2: 市场 | F2: 企业 | G2: 股票代码 | H2: 操作 | I2: 数量 | J2: 平均买价 | K2: 成本 | L2: 买卖价格 | M2: 市值
C3: 3 | D3: 45213 | E3: HK | F3: 比亚迪股份 | G3: 1211 | H3: 买入 | I3: 1000 | L3: 243.4 | M3: =L3*I3 -> 243400
C4: 6 | D4: 45269 | E4: HK | F4: 比亚迪股份 | G4: 1211 | H4: 买入 | I4: 1000 | L4: 210.8 | M4: =L4*I4 -> 210800
D5: 45409 | E5: HK | F5: 比亚迪股份 | G5: 1211 | H5: 卖出 | I5: -1000 | L5: 212.8 | M5: =L5*I5 -> -212800
D6: 45416 | E6: HK | F6: 比亚迪股份 | G6: 1211 | H6: 卖出 | I6: -1000 | L6: 226.4 | M6: =L6*I6 -> -226400
D7: 45409 | E7: US | F7: 苹果 | G7: AAPL | H7: 买入 | I7: 20 | L7: 1320.54 | M7: =L7*I7 -> 26410.8
D8: 45416 | E8: US | F8: 苹果 | G8: AAPL | H8: 卖出 | I8: -20 | L8: 1430.364 | M8: =L8*I8 -> -28607.28
C9: 2 | D9: 45213 | E9: HK | F9: 东方甄选 | G9: 1797 | H9: 买入 | I9: 1000 | L9: 35.05 | M9: =L9*I9 -> 35050
C10: 5 | D10: 45220 | E10: HK | F10: 东方甄选 | G10: 1797 | H10: 卖出 | I10: -300 | L10: 30.25 | M10: =L10*I10 -> -9075
C11: 8 | D11: 45276 | E11: HK | F11: 东方甄选 | G11: 1797 | H11: 买入 | I11: 2000 | L11: 26.25 | M11: =L11*I11 -> 52500
D12: 45416 | E12: HK | F12: 东方甄选 | G12: 1797 | H12: 卖出 | I12: -2500 | L12: 17.96 | M12: =L12*I12 -> -44900
D13: 45479 | E13: HK | F13: 东方甄选 | G13: 1797 | H13: 卖出 | I13: -200 | L13: 12.56 | M13: =L13*I13 -> -2512
D14: 45430 | E14: US | F14: 长江基建集团 | G14: CKISY | H14: 买入 | I14: 50 | L14: 229.554 | M14: =L14*I14 -> 11477.7
D15: 45479 | E15: US | F15: 长江基建集团 | G15: CKISY | H15: 卖出 | I15: -50 | L15: 216.06 | M15: =L15*I15 -> -10803
D16: 45409 | E16: US | F16: 安森美半导体 | G16: ON | H16: 买入 | I16: 50 | L16: 530.868 | M16: =L16*I16 -> 26543.4
D17: 45409 | E17: US | F17: 台积电 | G17: TSM | H17: 买入 | I17: 30 | L17: 1078.74 | M17: =L17*I17 -> 32362.2
D18: 45416 | E18: US | F18: 安森美半导体 | G18: ON | H18: 买入 | I18: 150 | L18: 548.886 | M18: =L18*I18 -> 82332.9
D19: 45416 | E19: US | F19: 台积电 | G19: TSM | H19: 买入 | I19: 70 | L19: 1104.168 | M19: =L19*I19 -> 77291.76
D20: 45416 | E20: US | F20: 英伟达 | G20: NVDA | H20: 买入 | I20: 5 | L20: 6925.542 | M20: =L20*I20 -> 34627.71
D21: 45416 | E21: US | F21: 微软 | G21: MSFT | H21: 买入 | I21: 10 | L21: 3171.948 | M21: =L21*I21 -> 31719.48
D22: 45416 | E22: US | F22: 脸书 | G22: Meta | H22: 买入 | I22: 20 | L22: 3525.288 | M22: =L22*I22 -> 70505.76
D23: 45430 | E23: HK | F23: 中银香港 | G23: 02388 | H23: 买入 | I23: 100 | L23: 25.85 | M23: =L23*I23 -> 2585
D24: 45430 | E24: US | F24: 台积电 | G24: TSM | H24: 买入 | I24: 50 | L24: 1183.104 | M24: =L24*I24 -> 59155.2
D25: 45430 | E25: US | F25: 微软 | G25: MSFT | H25: 买入 | I25: 5 | L25: 3277.638 | M25: =L25*I25 -> 16388.19
... D56: 45913 | E56: US | F56: 亚马逊 | G56: AMZN | H56: 卖出 | I56: -10 | L56: 1779.57 | M56: =L56*I56 -> -17795.7
C57: 1 | D57: 45213 | E57: US | F57: 特斯拉 | G57: TSLA | H57: 买入 | I57: 100 | L57: 1958.736 | M57: =L57*I57 -> 195873.6
C58: 4 | D58: 45220 | E58: US | F58: 特斯拉 | G58: TSLA | H58: 买入 | I58: 30 | L58: 1653.522 | M58: =L58*I58 -> 49605.66
C59: 7 | D59: 45276 | E59: US | F59: 特斯拉 | G59: TSLA | H59: 卖出 | I59: -50 | L59: 1977.3 | M59: =L59*I59 -> -98865
C60: 9 | D60: 45311 | E60: US | F60: 特斯拉 | G60: TSLA | H60: 买入 | I60: 50 | L60: 1655.082 | M60: =L60*I60 -> 82754.1
D61: 45318 | E61: US | F61: 特斯拉 | G61: TSLA | H61: 买入 | I61: 100 | L61: 1429.35 | M61: =L61*I61 -> 142935
D62: 45409 | E62: US | F62: 特斯拉 | G62: TSLA | H62: 买入 | I62: 80 | L62: 1312.662 | M62: =L62*I62 -> 105012.96
D63: 45416 | E63: US | F63: 特斯拉 | G63: TSLA | H63: 买入 | I63: -60 | L63: 1413.282 | M63: =L63*I63 -> -84796.92
D64: 45430 | E64: US | F64: 特斯拉 | G64: TSLA | H64: 卖出 | I64: -50 | L64: 1384.188 | M64: =L64*I64 -> -69209.4
D65: 45437 | E65: US | F65: 特斯拉 | G65: TSLA | H65: 卖出 | I65: -30 | L65: 1398.072 | M65: =L65*I65 -> -41942.16
D66: 45472 | E66: US | F66: 特斯拉 | G66: TSLA | H66: 卖出 | I66: -120 | L66: 1543.464 | M66: =L66*I66 -> -185215.68
D67: 45479 | E67: US | F67: 特斯拉 | G67: TSLA | H67: 卖出 | I67: -20 | L67: 1961.856 | M67: =L67*I67 -> -39237.12
D68: 45913 | E68: US | F68: 特斯拉 | G68: TSLA | H68: 卖出 | I68: -15 | L68: 3088.332 | M68: =L68*I68 -> -46324.98
D69: 45920 | E69: US | F69: 亚马逊 | G69: AMZN | H69: 买入 | I69: 20 | L69: 1805.544 | M69: =L69*I69 -> 36110.88
D70: 45920 | E70: US | F70: 脸书 | G70: Meta | H70: 买入 | I70: 15 | L70: 6071.364 | M70: =L70*I70 -> 91070.46
D71: 45920 | E71: US | F71: 谷歌 | G71: GOOGL | H71: 买入 | I71: 30 | L71: 1986.816 | M71: =L71*I71 -> 59604.48
D72: 45920 | E72: US | F72: Ionq,Inc. | G72: IONQ | H72: 买入 | I72: 5 | L72: 549.198 | M72: =L72*I72 -> 2745.99
... D77: 45941 | E77: US | F77: Ionq,Inc. | G77: IONQ | H77: 卖出 | I77: -5 | L77: 551.07 | M77: =L77*I77 -> -2755.35
M78: =L78*I78 -> 0
M79: =L79*I79 -> 0
M80: =L80*I80 -> 0
C81: 10 | M81: =L81*I81 -> 0
D82: 累计净买入 | M82: =SUM(M3:M81) -> -274538.97
D83: 时间 | E83: 市场 | F83: 企业 | G83: 股票代码 | H83: 状态 | I83: 数量 | J83: 平均买价 | K83: 成本 | L83: 当前价格 | M83: 市值
D84: =全班!$R$1 -> 46011 | H84: 持有 | I84: =SUMIFS($I$78:$I$82,$G$78:$G$82,G84) -> 0 | J84: =K84/I84 -> #DIV/0! | K84: =SUMIFS($M$78:$M$82,$G$78:$G$82,G84) -> 0 | L84: =VLOOKUP(G84,股价!C:D,2,FALSE) -> #N/A | M84: =IFERROR(I84*L84,0) -> 0
D85: =全班!$R$1 -> 46011 | H85: 持有 | I85: =SUMIFS($I$78:$I$82,$G$78:$G$82,G85) -> 0 | J85: =K85/I85 -> #DIV/0! | K85: =SUMIFS($M$78:$M$82,$G$78:$G$82,G85) -> 0 | L85: =VLOOKUP(G85,股价!C:D,2,FALSE) -> #N/A | M85: =IFERROR(I85*L85,0) -> 0
D86: =全班!$R$1 -> 46011 | H86: 持有 | I86: =SUMIFS($I$78:$I$82,$G$78:$G$82,G86) -> 0 | J86: =K86/I86 -> #DIV/0! | K86: =SUMIFS($M$78:$M$82,$G$78:$G$82,G86) -> 0 | L86: =VLOOKUP(G86,股价!C:D,2,FALSE) -> #N/A | M86: =IFERROR(I86*L86,0) -> 0
D87: =全班!$R$1 -> 46011 | H87: 持有 | I87: =SUMIFS($I$78:$I$82,$G$78:$G$82,G87) -> 0 | J87: =K87/I87 -> #DIV/0! | K87: =SUMIFS($M$78:$M$82,$G$78:$G$82,G87) -> 0 | L87: =VLOOKUP(G87,股价!C:D,2,FALSE) -> #N/A | M87: =IFERROR(I87*L87,0) -> 0
D88: =全班!$R$1 -> 46011 | H88: 持有 | I88: =SUMIFS($I$78:$I$82,$G$78:$G$82,G88) -> 0 | J88: =K88/I88 -> #DIV/0! | K88: =SUMIFS($M$78:$M$82,$G$78:$G$82,G88) -> 0 | L88: =VLOOKUP(G88,股价!C:D,2,FALSE) -> #N/A | M88: =IFERROR(I88*L88,0) -> 0
D90: 市值结余 | M90: =SUM(M84:M89) -> 0
D91: 累计分红 | M91: =L114 -> 2131.779
D92: 现金结余 | M92: =M97-M82+M91 -> 1276670.8
D93: 结余总额 | M93: =M90+M92 -> 1276670.8
D94: 累计盈利 | M94: =M93-M97 -> 276670.75
D95: 盈利率 | M95: =M94/M97 -> 0.27667075
D97: 本金 | M97: =本金与余额!D6 -> 1000000
D98: 登记日 | E98: 市场 | F98: 企业 | G98: 股票代码 | H98: 状态 | I98: 数量 | J98: 分红方案 | K98: 实施 | L98: 红利金额 | M98: 除权日
D99: 45458 | E99: US | F99: 英伟达 | G99: NVDA | H99: 拆分 | I99: 3 | J99: 1拆10 | K99: 30
D100: 45453 | E100: US | F100: 谷歌 | G100: GOOGL | H100: 分红 | I100: 40 | J100: 1派1.56 | K100: 1派1.56 | L100: =I100*1.56 -> 62.4 | M100: 45453
D101: 45819 | E101: US | F101: 英伟达 | G101: NVDA | H101: 分红 | I101: 70 | J101: 1派0.01USD | K101: 1派0.01USD | L101: =I101*0.01*7.8 -> 5.46 | M101: 45819
D102: 45817 | E102: US | F102: 谷歌-A | G102: GOOGL | H102: 分红 | I102: 60 | J102: 1派0.21USD | K102: 1派0.21USD | L102: =I102*0.21*7.8 -> 98.28 | M102: 45817
D103: 45806 | E103: US | F103: 脸书 | G103: Meta | H103: 分红 | I103: 25 | J103: 1派0.525USD | K103: 1派0.525USD | L103: =I103*0.525*7.8 -> 102.375 | M103: 45824
D104: 45820 | E104: US | F104: 台积电 | G104: TSM | H104: 分红 | I104: 170 | J104: 1派0.594USD | K104: 1派0.594USD | L104: =I104*0.594*7.8 -> 787.644 | M104: 45820
D105: 45789 | E105: US | F105: 苹果 | G105: AAPL | H105: 分红 | I105: 50 | J105: 1派0.26USD | K105: 1派0.26USD | L105: =I105*0.26*7.8 -> 101.4 | M105: 45789
D106: 45804 | E106: US | F106: 强生 | G106: JNJ | H106: 分红 | I106: 10 | J106: 1派1.3USD | K106: 1派1.3USD | L106: =I106*1.3*7.8 -> 101.4 | M106: 45804
D107: 45820 | E107: US | F107: 阿里巴巴 | G107: BABA | H107: 分红 | I107: 50 | J107: 1派1.98USD | K107: 1派1.98USD | L107: =I107*1.98*7.8 -> 772.2 | M107: 45820
D108: 45786 | E108: US | F108: 辉瑞 | G108: PFE | H108: 分红 | I108: 30 | J108: 1派0.43USD | K108: 1派0.43USD | L108: =I108*0.43*7.8 -> 100.62 | M108: 45786
D114: 累计分红 | L114: =SUM(L99:L113) -> 2131.779

Sheet 咏博
A1: back | D1: 操盘：张咏博
D2: 时间 | E2: 市场 | F2: 企业 | G2: 股票代码 | H2: 操作 | I2: 数量 | J2: 平均买价 | K2: 成本 | L2: 买卖价格 | M2: 市值
C3: 5 | D3: 45171 | E3: CN | F3: 五粮液 | G3: 000858 | H3: 买入 | I3: 100 | L3: 159.74 | M3: =L3*I3 -> 15974
D4: 45290 | E4: CN | F4: 五粮液 | G4: 000858 | H4: 卖出 | I4: -100 | L4: 140.31 | M4: =L4*I4 -> -14031
C5: 2 | D5: 45157 | E5: US | F5: 小鹏汽车 | G5: XPEV | H5: 买入 | I5: 1000 | L5: 116.844 | M5: =L5*I5 -> 116844
C6: 3 | D6: 45157 | E6: HK | F6: 携程集团 | G6: 9961 | H6: 买入 | I6: 100 | L6: 299.6 | M6: =L6*I6 -> 29960
D7: 45318 | E7: US | F7: 小鹏汽车 | G7: XPEV | H7: 卖出 | I7: -1000 | L7: 69.966 | M7: =L7*I7 -> -69966
D8: 45318 | E8: HK | F8: 携程集团 | G8: 9961 | H8: 卖出 | I8: -100 | L8: 290.2 | M8: =L8*I8 -> -29020
D9: 45318 | E9: HK | F9: 东方甄选 | G9: 1797 | H9: 卖出 | I9: -1000 | L9: 22.2 | M9: =L9*I9 -> -22200
C10: 6 | D10: 45171 | E10: HK | F10: 东方甄选 | G10: 1797 | H10: 买入 | I10: 1000 | L10: 39.75 | M10: =L10*I10 -> 39750
C11: 7 | D11: 45220 | E11: HK | F11: 东方甄选 | G11: 1797 | H11: 卖出 | I11: -500 | L11: 30.25 | M11: =L11*I11 -> -15125
C12: 9 | D12: 45247 | E12: HK | F12: 东方甄选 | G12: 1797 | H12: 买入 | I12: 500 | L12: 28.65 | M12: =L12*I12 -> 14325
D13: 45423 | E13: US | F13: 极氪 | G13: ZK | H13: 买入 | I13: 50 | L13: 220.428 | M13: =L13*I13 -> 11021.4
D14: 45437 | E14: US | F14: 极氪 | G14: ZK | H14: 卖出 | I14: -50 | L14: 182.364 | M14: =L14*I14 -> -9118.2
D15: 45374 | E15: HK | F15: 小米集团 | G15: 1810 | H15: 买入 | I15: 10000 | L15: 14.8 | M15: =L15*I15 -> 148000
D16: 45402 | E16: HK | F16: 小米集团 | G16: 1810 | H16: 卖出 | I16: -5000 | L16: 15.8 | M16: =L16*I16 -> -79000
D17: 45409 | E17: HK | F17: 小米集团 | G17: 1810 | H17: 卖出 | I17: -1000 | L17: 17.36 | M17: =L17*I17 -> -17360
D18: 45416 | E18: HK | F18: 小米集团 | G18: 1810 | H18: 卖出 | I18: -2000 | L18: 18.18 | M18: =L18*I18 -> -36360
D19: 45437 | E19: HK | F19: 小米集团 | G19: 1810 | H19: 卖出 | I19: -2000 | L19: 18.3 | M19: =L19*I19 -> -36600
D20: 45423 | E20: US | F20: 超微电脑 | G20: SMCI | H20: 买入 | I20: 7 | L20: 6228.3 | M20: =L20*I20 -> 43598.1
D21: 45444 | E21: US | F21: 超微电脑 | G21: SMCI | H21: 买入 | I21: 3 | L21: 6119.178 | M21: =L21*I21 -> 18357.534
D22: 45472 | E22: US | F22: 超微电脑 | G22: SMCI | H22: 买入 | I22: 5 | L22: 6390.93 | M22: =L22*I22 -> 31954.65
D23: 45479 | E23: US | F23: 超微电脑 | G23: SMCI | H23: 买入 | I23: 5 | L23: 6603.324 | M23: =L23*I23 -> 33016.62
D24: 45486 | E24: US | F24: 超微电脑 | G24: SMCI | H24: 卖出 | I24: -10 | L24: 7097.688 | M24: =L24*I24 -> -70976.88
D25: 45493 | E25: US | F25: 超微电脑 | G25: SMCI | H25: 买入 | I25: 5 | L25: 6214.884 | M25: =L25*I25 -> 31074.42
D26: 45566 | E26: US | F26: 超微电脑 | G26: SMCI | H26: 拆股 | I26: =250-25 -> 225 | M26: =L26*I26 -> 0
D27: 45591 | E27: US | F27: 超微电脑 | G27: SMCI | H27: 买入 | I27: 100 | L27: 368.706 | M27: =L27*I27 -> 36870.6
D28: 45598 | E28: US | F28: 超微电脑 | G28: SMCI | H28: 卖出 | I28: -350 | L28: 203.19 | M28: =L28*I28 -> -71116.5
D29: 45514 | E29: US | F29: 超微电脑 | G29: SMCI | H29: 买入 | I29: 10 | L29: 3968.328 | M29: =L29*I29 -> 39683.28
D30: 45416 | E30: US | F30: 微软 | G30: MSFT | H30: 买入 | I30: 10 | L30: 3171.948 | M30: =L30*I30 -> 31719.48
D31: 45444 | E31: US | F31: 微软 | G31: MSFT | H31: 买入 | I31: 5 | L31: 3238.014 | M31: =L31*I31 -> 16190.07
D32: 45465 | E32: US | F32: 微软 | G32: MSFT | H32: 卖出 | I32: -5 | L32: 3508.284 | M32: =L32*I32 -> -17541.42
D33: 45486 | E33: US | F33: 微软 | G33: MSFT | H33: 买入 | I33: 5 | L33: 3537.69 | M33: =L33*I33 -> 17688.45
D34: 45591 | E34: US | F34: 微软 | G34: MSFT | H34: 卖出 | I34: -15 | L34: 3339.57 | M34: =L34*I34 -> -50093.55
D35: 45381 | E35: US | F35: 安森美半导体 | G35: ON | H35: 买入 | I35: 50 | L35: 573.69 | M35: =L35*I35 -> 28684.5
D36: 45416 | E36: US | F36: 安森美半导体 | G36: ON | H36: 买入 | I36: 30 | L36: 548.886 | M36: =L36*I36 -> 16466.58
D37: 45409 | E37: US | F37: 安森美半导体 | G37: ON | H37: 买入 | I37: 10 | L37: 530.868 | M37: =L37*I37 -> 5308.68
D38: 45423 | E38: US | F38: 安森美半导体 | G38: ON | H38: 卖出 | I38: -90 | L38: 549.588 | M38: =L38*I38 -> -49462.92
... D57: 45710 | E57: US | F57: 谷歌 | G57: GOOGL | H57: 卖出 | I57: -42 | L57: 1401.348 | M57: =L57*I57 -> -58856.616
C58: 4 | D58: 45157 | E58: CN | F58: 比亚迪 | G58: 002594 | H58: 买入 | I58: 100 | L58: 240.29 | M58: =L58*I58 -> 24029
D59: 45261 | E59: CN | F59: 比亚迪 | G59: 002594 | H59: 买入 | I59: 200 | L59: 197.05 | M59: =L59*I59 -> 39410
D60: 45290 | E60: CN | F60: 比亚迪 | G60: 002594 | H60: 买入 | I60: 200 | L60: 198 | M60: =L60*I60 -> 39600
D61: 45409 | E61: CN | F61: 比亚迪 | G61: 002594 | H61: 卖出 | I61: -200 | L61: 219.37 | M61: =L61*I61 -> -43874
D62: 45416 | E62: CN | F62: 比亚迪 | G62: 002594 | H62: 卖出 | I62: -300 | L62: 218.5 | M62: =L62*I62 -> -65550
C63: 1 | D63: 45157 | E63: US | F63: 拼多多 | G63: PDD | H63: 买入 | I63: 200 | L63: 600.444 | M63: =L63*I63 -> 120088.8
D64: 45374 | E64: US | F64: 苹果 | G64: AAPL | H64: 买入 | I64: 30 | L64: 1332.474 | M64: =L64*I64 -> 39974.22
D65: 45374 | E65: US | F65: 亚马逊 | G65: AMZN | H65: 买入 | I65: 50 | L65: 1343.784 | M65: =L65*I65 -> 67189.2
D66: 45374 | E66: US | F66: 脸书 | G66: Meta | H66: 买入 | I66: 30 | L66: 3974.724 | M66: =L66*I66 -> 119241.72
D67: 45381 | E67: US | F67: 台积电 | G67: TSM | H67: 买入 | I67: 50 | L67: 1061.19 | M67: =L67*I67 -> 53059.5
D68: 45402 | E68: US | F68: 脸书 | G68: Meta | H68: 买入 | I68: 10 | L68: 3752.346 | M68: =L68*I68 -> 37523.46
D69: 45402 | E69: US | F69: 苹果 | G69: AAPL | H69: 买入 | I69: 10 | L69: 1287 | M69: =L69*I69 -> 12870
D70: 45409 | E70: US | F70: 苹果 | G70: AAPL | H70: 买入 | I70: 10 | L70: 1320.54 | M70: =L70*I70 -> 13205.4
D71: 45416 | E71: US | F71: 脸书 | G71: Meta | H71: 买入 | I71: 20 | L71: 3525.288 | M71: =L71*I71 -> 70505.76
D72: 45416 | E72: US | F72: 台积电 | G72: TSM | H72: 买入 | I72: 30 | L72: 1104.168 | M72: =L72*I72 -> 33125.04
D73: 45409 | E73: US | F73: 拼多多 | G73: PDD | H73: 买入 | I73: 10 | L73: 1008.618 | M73: =L73*I73 -> 10086.18
D74: 45423 | E74: US | F74: 拼多多 | G74: PDD | H74: 买入 | I74: 10 | L74: 1062.906 | M74: =L74*I74 -> 10629.06
D75: 45444 | E75: US | F75: 拼多多 | G75: PDD | H75: 买入 | I75: 10 | L75: 1168.284 | M75: =L75*I75 -> 11682.84
... D105: 45955 | E105: US | F105: 超微电脑 | G105: SMCI | H105: 卖出 | I105: -50 | L105: 376.662 | M105: =L105*I105 -> -18833.1
C106: 8 | D106: 45220 | E106: US | F106: 特斯拉 | G106: TSLA | H106: 买入 | I106: 30 | L106: 1653.522 | M106: =L106*I106 -> 49605.66
D107: 45318 | E107: US | F107: 特斯拉 | G107: TSLA | H107: 买入 | I107: 10 | L107: 1429.35 | M107: =L107*I107 -> 14293.5
D108: 45374 | E108: US | F108: 特斯拉 | G108: TSLA | H108: 买入 | I108: 10 | L108: 1332.474 | M108: =L108*I108 -> 13324.74
D109: 45402 | E109: US | F109: 特斯拉 | G109: TSLA | H109: 买入 | I109: 20 | L109: 1146.99 | M109: =L109*I109 -> 22939.8
D110: 45409 | E110: US | F110: 特斯拉 | G110: TSLA | H110: 买入 | I110: 10 | L110: 1312.662 | M110: =L110*I110 -> 13126.62
D111: 45416 | E111: US | F111: 特斯拉 | G111: TSLA | H111: 买入 | I111: 20 | L111: 1413.282 | M111: =L111*I111 -> 28265.64
D112: 45416 | E112: US | F112: 英伟达 | G112: NVDA | H112: 买入 | I112: 5 | L112: 6925.542 | M112: =L112*I112 -> 34627.71
D113: 45423 | E113: US | F113: 特斯拉 | G113: TSLA | H113: 买入 | I113: 10 | L113: 1314.066 | M113: =L113*I113 -> 13140.66
D114: 45444 | E114: US | F114: 英伟达 | G114: NVDA | H114: 买入 | I114: 5 | L114: 8551.374 | M114: =L114*I114 -> 42756.87
D115: 45444 | E115: US | F115: 特斯拉 | G115: TSLA | H115: 卖出 | I115: -10 | L115: 1384.344 | M115: =L115*I115 -> -13843.44
D116: 45458 | E116: US | F116: 英伟达 | G116: NVDA | H116: 拆分 | I116: 90 | L116: 0 | M116: =L116*I116 -> 0
D117: 45465 | E117: US | F117: 特斯拉 | G117: TSLA | H117: 买入 | I117: 10 | L117: 1427.478 | M117: =L117*I117 -> 14274.78
D118: 45465 | E118: US | F118: 英伟达 | G118: NVDA | H118: 买入 | I118: 30 | L118: 987.246 | M118: =L118*I118 -> 29617.38
... D151: 46004 | E151: US | F151: 拼多多 | G151: PDD | H151: 买入 | I151: 10 | L151: 873.288 | M151: =L151*I151 -> 8732.88
M152: =L152*I152 -> 0
M153: =L153*I153 -> 0
M154: =L154*I154 -> 0
M155: =L155*I155 -> 0
C156: 10 | M156: =L156*I156 -> 0
D157: 累计净买入 | M157: =SUM(M3:M156) -> 129709.11
D158: 时间 | E158: 市场 | F158: 企业 | G158: 股票代码 | H158: 状态 | I158: 数量 | J158: 平均买价 | K158: 成本 | L158: 当前价格 | M158: 市值
D159: =全班!$R$1 -> 46011 | E159: US | F159: 英伟达 | G159: NVDA | H159: 持有 | I159: =SUMIFS($I$106:$I$157,$G$106:$G$157,G159) -> 188 | J159: =K159/I159 -> 833.05577 | K159: =SUMIFS($M$106:$M$157,$G$106:$G$157,G159) -> 156614.48 | L159: =VLOOKUP(G159,股价!C:D,2,FALSE) -> 1411.722 | M159: =IFERROR(I159*L159,0) -> 265403.74
D160: =全班!$R$1 -> 46011 | E160: US | F160: 特斯拉 | G160: TSLA | H160: 持有 | I160: =SUMIFS($I$106:$I$157,$G$106:$G$157,G160) -> 68 | J160: =K160/I160 -> 859.0335 | K160: =SUMIFS($M$106:$M$157,$G$106:$G$157,G160) -> 58414.278 | L160: =VLOOKUP(G160,股价!C:D,2,FALSE) -> 3753.36 | M160: =IFERROR(I160*L160,0) -> 255228.48
D161: =全班!$R$1 -> 46011 | E161: US | F161: 台积电 | G161: TSM | H161: 持有 | I161: =SUMIFS($I$106:$I$157,$G$106:$G$157,G161) -> 50 | J161: =K161/I161 -> 2243.514 | K161: =SUMIFS($M$106:$M$157,$G$106:$G$157,G161) -> 112175.7 | L161: =VLOOKUP(G161,股价!C:D,2,FALSE) -> 2253.81 | M161: =IFERROR(I161*L161,0) -> 112690.5
D162: =全班!$R$1 -> 46011 | E162: US | F162: 拼多多 | G162: PDD | H162: 持有 | I162: =SUMIFS($I$106:$I$157,$G$106:$G$157,G162) -> 40 | J162: =K162/I162 -> 894.86387 | K162: =SUMIFS($M$106:$M$157,$G$106:$G$157,G162) -> 35794.555 | L162: =VLOOKUP(G162,股价!C:D,2,FALSE) -> 854.178 | M162: =IFERROR(I162*L162,0) -> 34167.12
D164: 市值结余 | M164: =SUM(M159:M163) -> 667489.84
D165: 累计分红 | M165: =L184 -> 2149.056
D166: 现金结余 | M166: =M171-M157+M165 -> 872439.95
D167: 结余总额 | M167: =M164+M166 -> 1539929.8
D168: 累计盈利 | M168: =M167-M171 -> 539929.78
D169: 盈利率 | M169: =M168/M171 -> 0.53992978
D171: 本金 | M171: =本金与余额!D7 -> 1000000
D172: 登记日 | E172: 市场 | F172: 企业 | G172: 股票代码 | H172: 状态 | I172: 数量 | J172: 分红方案 | K172: 实施 | L172: 红利金额 | M172: 除权日
D173: 45458 | E173: US | F173: 英伟达 | G173: NVDA | H173: 拆分 | I173: 10 | J173: 1拆10 | K173: 100
D174: 45453 | E174: US | F174: 谷歌 | G174: GOOGL | H174: 分红 | I174: 40 | J174: 1派1.56 | K174: 1派1.56 | L174: =I174*1.56 -> 62.4 | M174: 45453
D175: 45566 | E175: US | F175: 超微电脑 | G175: SMCI | H175: 拆股 | I175: 25 | J175: 1拆10 | K175: =I175*10 -> 250 | M175: 45566
D176: 45819 | E176: US | F176: 英伟达 | G176: NVDA | H176: 分红 | I176: 195 | J176: 1派0.01USD | K176: 1派0.01USD | L176: =I176*0.01*7.8 -> 15.21 | M176: 45819
D177: 45820 | E177: US | F177: 台积电 | G177: TSM | H177: 分红 | I177: 105 | J177: 1派0.594USD | K177: 1派0.594USD | L177: =I177*0.594*7.8 -> 486.486 | M177: 45820
D178: 45789 | E178: US | F178: 苹果 | G178: AAPL | H178: 分红 | I178: 20 | J178: 1派0.26USD | K178: 1派0.26USD | L178: =I178*0.26*7.8 -> 40.56 | M178: 45789
D179: 45820 | E179: US | F179: 阿里巴巴 | G179: BABA | H179: 分红 | I179: 100 | J179: 1派1.98USD | K179: 1派1.98USD | L179: =I179*1.98*7.8 -> 1544.4 | M179: 45820
D184: 累计分红 | L184: =SUM(L173:L183) -> 2149.056

Sheet 彩银
A1: back | D1: 操盘：周彩银
D2: 时间 | E2: 市场 | F2: 企业 | G2: 股票代码 | H2: 操作 | I2: 数量 | J2: 平均买价 | K2: 成本 | L2: 买卖价格 | M2: 市值
C3: 1 | D3: 45969 | E3: CN | F3: 中芯国际 | G3: 688981 | H3: 买入 | I3: 1000 | L3: 122.11 | M3: =L3*I3 -> 122110
C4: 2 | D4: 45969 | E4: US | F4: 特斯拉 | G4: TSLA | H4: 买入 | I4: 100 | L4: 3350.256 | M4: =L4*I4 -> 335025.6
C5: 3 | D5: 45976 | E5: CN | F5: 比亚迪 | G5: 002594 | H5: 买入 | I5: 1000 | L5: 98.37 | M5: =L5*I5 -> 98370
C6: 4 | D6: 45976 | E6: CN | F6: 海天味业 | G6: 603288 | H6: 买入 | I6: 1000 | L6: 38.42 | M6: =L6*I6 -> 38420
C7: 5 | M7: =L7*I7 -> 0
C8: 6 | M8: =L8*I8 -> 0
C9: 7 | M9: =L9*I9 -> 0
C10: 8 | M10: =L10*I10 -> 0
C11: 9 | M11: =L11*I11 -> 0
C12: 10 | M12: =L12*I12 -> 0
D13: 累计净买入 | M13: =SUM(M3:M12) -> 593925.6
D14: 时间 | E14: 市场 | F14: 企业 | G14: 股票代码 | H14: 状态 | I14: 数量 | J14: 平均买价 | K14: 成本 | L14: 当前股价 | M14: 市值
D15: =全班!$R$1 -> 46011 | E15: CN | F15: 中芯国际 | G15: 688981 | H15: 持有 | I15: =SUMIFS($I$3:$I$13,$G$3:$G$13,G15) -> 1000 | J15: =K15/I15 -> 122.11 | K15: =SUMIFS($M$3:$M$13,$G$3:$G$13,G15) -> 122110 | L15: =VLOOKUP(G15,股价!C:D,2,FALSE) -> 113.63 | M15: =IFERROR(I15*L15,0) -> 113630
D16: =全班!$R$1 -> 46011 | E16: US | F16: 特斯拉 | G16: TSLA | H16: 持有 | I16: =SUMIFS($I$3:$I$13,$G$3:$G$13,G16) -> 100 | J16: =K16/I16 -> 3350.256 | K16: =SUMIFS($M$3:$M$13,$G$3:$G$13,G16) -> 335025.6 | L16: =VLOOKUP(G16,股价!C:D,2,FALSE) -> 3753.36 | M16: =IFERROR(I16*L16,0) -> 375336
D17: =全班!$R$1 -> 46011 | E17: CN | F17: 比亚迪 | G17: 002594 | H17: 持有 | I17: =SUMIFS($I$3:$I$13,$G$3:$G$13,G17) -> 1000 | J17: =K17/I17 -> 98.37 | K17: =SUMIFS($M$3:$M$13,$G$3:$G$13,G17) -> 98370 | L17: =VLOOKUP(G17,股价!C:D,2,FALSE) -> 94.23 | M17: =IFERROR(I17*L17,0) -> 94230
D18: =全班!$R$1 -> 46011 | E18: CN | F18: 海天味业 | G18: 603288 | H18: 持有 | I18: =SUMIFS($I$3:$I$13,$G$3:$G$13,G18) -> 1000 | J18: =K18/I18 -> 38.42 | K18: =SUMIFS($M$3:$M$13,$G$3:$G$13,G18) -> 38420 | L18: =VLOOKUP(G18,股价!C:D,2,FALSE) -> 37.78 | M18: =IFERROR(I18*L18,0) -> 37780
D19: =全班!$R$1 -> 46011 | H19: 持有 | I19: =SUMIFS($I$3:$I$13,$G$3:$G$13,G19) -> 0 | J19: =K19/I19 -> #DIV/0! | K19: =SUMIFS($M$3:$M$13,$G$3:$G$13,G19) -> 0 | L19: =VLOOKUP(G19,股价!C:D,2,FALSE) -> #N/A | M19: =IFERROR(I19*L19,0) -> 0
D21: 市值结余 | M21: =SUM(M15:M20) -> 620976
D22: 累计分红 | M22: =L35 -> 0
D23: 现金结余 | M23: =M28-M13+M22 -> 406074.4
D24: 结余总额 | M24: =M21+M23 -> 1027050.4
D25: 累计盈利 | M25: =M24-M28 -> 27050.4
D26: 盈利率 | M26: =M25/M28 -> 0.0270504
D28: 本金 | M28: =本金与余额!D25 -> 1000000
D29: 登记日 | E29: 市场 | F29: 企业 | G29: 股票代码 | H29: 状态 | I29: 数量 | J29: 分红方案 | K29: 实施 | L29: 红利金额 | M29: 除权日
D35: 累计分红 | L35: =SUM(L30:L34) -> 0

Sheet 俊峰
A1: back | D1: 操盘：邹俊峰
D2: 时间 | E2: 市场 | F2: 企业 | G2: 股票代码 | H2: 操作 | I2: 数量 | J2: 平均买价 | K2: 成本 | L2: 买卖价格 | M2: 市值
C3: 1 | D3: 45143 | E3: CN | F3: 科大讯飞 | G3: 002230 | H3: 卖出 | I3: -2000 | L3: 63.32 | M3: =L3*I3 -> -126640
C4: 2 | D4: 45136 | E4: CN | F4: 科大讯飞 | G4: 002230 | H4: 买入 | I4: 2000 | L4: 62.43 | M4: =L4*I4 -> 124860
C5: 3 | D5: 45143 | E5: CN | F5: 英杰电气 | G5: 300820 | H5: 卖出 | I5: -1000 | L5: =股价!D78 -> 38.34 | M5: =L5*I5 -> -38340
C6: 4 | D6: 45136 | E6: CN | F6: 英杰电气 | G6: 300820 | H6: 买入 | I6: 1000 | L6: 68.65 | M6: =L6*I6 -> 68650
C7: 5 | D7: 45143 | E7: CN | F7: 特一药业 | G7: 002728 | H7: 买入 | I7: 8000 | L7: 15.51 | M7: =L7*I7 -> 124080
C8: 6 | D8: 45150 | E8: CN | F8: 特一药业 | G8: 002728 | H8: 卖出 | I8: -8000 | L8: 16.74 | M8: =L8*I8 -> -133920
C9: 7 | D9: 45143 | E9: CN | F9: 东田微 | G9: 301183 | H9: 买入 | I9: 1000 | L9: 52.04 | M9: =L9*I9 -> 52040
C10: 8 | D10: 45150 | E10: CN | F10: 东田微 | G10: 301183 | H10: 买入 | I10: 3000 | L10: 48.89 | M10: =L10*I10 -> 146670
C11: 9 | D11: 45185 | E11: CN | F11: 东田微 | G11: 301183 | H11: 卖出 | I11: -4000 | L11: 50.7 | M11: =L11*I11 -> -202800
C12: 10 | D12: 45185 | E12: CN | F12: 姚记科技 | G12: 002605 | H12: 卖出 | I12: -3000 | L12: 26.34 | M12: =L12*I12 -> -79020
C13: 11 | D13: 45150 | E13: CN | F13: 姚记科技 | G13: 002605 | H13: 买入 | I13: 3000 | L13: 33.43 | M13: =L13*I13 -> 100290
C14: 12 | D14: 45136 | E14: CN | F14: 中船科技 | G14: 600072 | H14: 买入 | I14: 3000 | L14: 24.62 | M14: =L14*I14 -> 73860
C15: 13 | D15: 45143 | E15: CN | F15: 中船科技 | G15: 600072 | H15: 买入 | I15: 3000 | L15: 23.13 | M15: =L15*I15 -> 69390
C16: 14 | D16: 45150 | E16: CN | F16: 中船科技 | G16: 600072 | H16: 买入 | I16: 8000 | L16: 22.02 | M16: =L16*I16 -> 176160
C17: 15 | D17: 45192 | E17: CN | F17: 中船科技 | G17: 600072 | H17: 卖出 | I17: -14000 | L17: 19.84 | M17: =L17*I17 -> -277760
C18: 16 | D18: 45136 | E18: CN | F18: 西安饮食 | G18: 000721 | H18: 买入 | I18: 8000 | L18: 13.91 | M18: =L18*I18 -> 111280
C19: 17 | D19: 45150 | E19: CN | F19: 西安饮食 | G19: 000721 | H19: 买入 | I19: 2000 | L19: 14.04 | M19: =L19*I19 -> 28080
C20: 18 | D20: 45213 | E20: CN | F20: 西安饮食 | G20: 000721 | H20: 卖出 | I20: -10000 | L20: 11.45 | M20: =L20*I20 -> -114500
C21: 19 | D21: 45164 | E21: CN | F21: 首创证券 | G21: 601136 | H21: 买入 | I21: 4000 | L21: 25.27 | M21: =L21*I21 -> 101080
C22: 20 | D22: 45185 | E22: CN | F22: 首创证券 | G22: 601136 | H22: 买入 | I22: 2000 | L22: 22.25 | M22: =L22*I22 -> 44500
C23: 21 | D23: 45213 | E23: CN | F23: 首创证券 | G23: 601136 | H23: 卖出 | I23: -6000 | L23: 20.42 | M23: =L23*I23 -> -122520
C24: 22 | D24: 45276 | E24: CN | F24: 宝明科技 | G24: 002992 | H24: 买入 | I24: 905 | L24: 75.06 | M24: =L24*I24 -> 67929.3
C25: 23 | D25: 45290 | E25: CN | F25: 翠微股份 | G25: 603123 | H25: 买入 | I25: 5000 | L25: 10.65 | M25: =L25*I25 -> 53250
C26: 24 | D26: 45290 | E26: CN | F26: 科大讯飞 | G26: 002230 | H26: 买入 | I26: 1811 | L26: 46.38 | M26: =L26*I26 -> 83994.18
C27: 25 | D27: 45353 | E27: CN | F27: 宝明科技 | G27: 002992 | H27: 卖出 | I27: -905 | L27: 49.97 | M27: =L27*I27 -> -45222.85
C28: 26 | D28: 45353 | E28: CN | F28: 富春股份 | G28: 300299 | H28: 卖出 | I28: -10000 | L28: 4.94 | M28: =L28*I28 -> -49400
C29: 27 | D29: 45353 | E29: CN | F29: 翠微股份 | G29: 603123 | H29: 卖出 | I29: -11020 | L29: 8.59 | M29: =L29*I29 -> -94661.8
C30: 28 | D30: 45353 | E30: CN | F30: 科大讯飞 | G30: 002230 | H30: 卖出 | I30: -1811 | L30: 52.57 | M30: =L30*I30 -> -95204.27
C31: 29 | D31: 45283 | E31: CN | F31: 富春股份 | G31: 300299 | H31: 买入 | I31: 10000 | L31: 5.89 | M31: =L31*I31 -> 58900
C32: 30 | D32: 45283 | E32: CN | F32: 翠微股份 | G32: 603123 | H32: 买入 | I32: 6020 | L32: 10.4 | M32: =L32*I32 -> 62608
C33: 31 | D33: 45136 | E33: CN | F33: 中科曙光 | G33: 603019 | H33: 买入 | I33: 3000 | L33: 45.15 | M33: =L33*I33 -> 135450
C34: 32 | D34: 45192 | E34: CN | F34: 中科曙光 | G34: 603019 | H34: 买入 | I34: 1000 | L34: 39.13 | M34: =L34*I34 -> 39130
C35: 33 | D35: 45255 | E35: CN | F35: 中科曙光 | G35: 603019 | H35: 卖出 | I35: -4000 | L35: 38 | M35: =L35*I35 -> -152000
C36: 34 | D36: 45192 | E36: CN | F36: 剑桥科技 | G36: 603083 | H36: 买入 | I36: 3000 | L36: 48.1 | M36: =L36*I36 -> 144300
C37: 35 | D37: 45227 | E37: CN | F37: 剑桥科技 | G37: 603083 | H37: 买入 | I37: 764 | L37: 36.96 | M37: =L37*I37 -> 28237.44
C38: 36 | D38: 45247 | E38: CN | F38: 剑桥科技 | G38: 603083 | H38: 卖出 | I38: -2000 | L38: 43.48 | M38: =L38*I38 -> -86960
C39: 37 | D39: 45276 | E39: CN | F39: 剑桥科技 | G39: 603083 | H39: 卖出 | I39: -1764 | L39: 40.85 | M39: =L39*I39 -> -72059.4
C40: 38 | D40: 45255 | E40: US | F40: 蔚来 | G40: NIO | H40: 买入 | I40: 3758 | L40: 57.72 | M40: =L40*I40 -> 216911.76
C41: 39 | D41: 45283 | E41: US | F41: 蔚来 | G41: NIO | H41: 卖出 | I41: -1879 | L41: 65.676 | M41: =L41*I41 -> -123405.2
C42: 40 | D42: 45290 | E42: US | F42: 蔚来 | G42: NIO | H42: 卖出 | I42: -1879 | L42: 70.746 | M42: =L42*I42 -> -132931.73
C43: 41 | D43: 45213 | E43: CN | F43: 申万宏源 | G43: 000166 | H43: 买入 | I43: 20000 | L43: 4.38 | M43: =L43*I43 -> 87600
C44: 42 | D44: 45255 | E44: CN | F44: 申万宏源 | G44: 000166 | H44: 卖出 | I44: -20000 | L44: 4.56 | M44: =L44*I44 -> -91200
C45: 43 | D45: 45213 | E45: CN | F45: 沪州老窖 | G45: 000568 | H45: 买入 | I45: 1000 | L45: 205.15 | M45: =L45*I45 -> 205150
C46: 44 | D46: 45247 | E46: CN | F46: 沪州老窖 | G46: 000568 | H46: 卖出 | I46: -1000 | L46: 208.3 | M46: =L46*I46 -> -208300
C47: 45 | D47: 45247 | E47: CN | F47: 中通客车 | G47: 000957 | H47: 买入 | I47: 8000 | L47: 10.63 | M47: =L47*I47 -> 85040
C48: 46 | D48: 45255 | E48: CN | F48: 中通客车 | G48: 000957 | H48: 卖出 | I48: -8000 | L48: 10.25 | M48: =L48*I48 -> -82000
C49: 47 | D49: 45185 | E49: CN | F49: 比亚迪 | G49: 002594 | H49: 买入 | I49: 1012 | L49: 244.05 | M49: =L49*I49 -> 246978.6
C50: 48 | D50: 45247 | E50: CN | F50: 比亚迪 | G50: 002594 | H50: 买入 | I50: 500 | L50: 236.76 | M50: =L50*I50 -> 118380
C51: 52 | D51: 45423 | E51: CN | F51: 比亚迪 | G51: 002594 | H51: 卖出 | I51: -2012 | L51: 227.8 | M51: =L51*I51 -> -458333.6
C52: 49 | D52: 45247 | E52: CN | F52: 药明康德 | G52: 603259 | H52: 买入 | I52: 1172 | L52: 85.36 | M52: =L52*I52 -> 100041.92
D53: 45423 | E53: CN | F53: 药明康德 | G53: 603259 | H53: 卖出 | I53: -1172 | L53: 44.85 | M53: =L53*I53 -> -52564.2
D54: 45577 | E54: CN | F54: 赛力斯 | G54: 601127 | H54: 买入 | I54: 2000 | L54: 92.2 | M54: =L54*I54 -> 184400
D55: 45577 | E55: CN | F55: 沪电股份 | G55: 002463 | H55: 买入 | I55: 2000 | L55: 41.84 | M55: =L55*I55 -> 83680
D56: 45598 | E56: CN | F56: 赛力斯 | G56: 601127 | H56: 卖出 | I56: -2000 | L56: 113.93 | M56: =L56*I56 -> -227860
D57: 45598 | E57: CN | F57: 沪电股份 | G57: 002463 | H57: 卖出 | I57: -2000 | L57: 39.42 | M57: =L57*I57 -> -78840
C58: 50 | D58: 45255 | E58: CN | F58: 比亚迪 | G58: 002594 | H58: 买入 | I58: 500 | L58: 216.85 | M58: =L58*I58 -> 108425
C59: 51 | D59: 45360 | E59: CN | F59: 中国科传 | G59: 601858 | H59: 买入 | I59: 10000 | L59: 27.46 | M59: =L59*I59 -> 274600
C60: 53 | D60: 45423 | E60: US | F60: 特斯拉 | G60: TSLA | H60: 买入 | I60: 153 | L60: 1314.066 | M60: =L60*I60 -> 201052.1
D61: 45423 | E61: CN | F61: 斯达半导 | G61: 603290 | H61: 买入 | I61: 1000 | L61: 130.98 | M61: =L61*I61 -> 130980
D62: 45423 | E62: CN | F62: 中铁装配 | G62: 300374 | H62: 买入 | I62: 7423 | L62: 16.81 | M62: =L62*I62 -> 124780.63
D63: 45423 | E63: CN | F63: 传音控股 | G63: 688036 | H63: 买入 | I63: 360 | L63: 145.86 | M63: =L63*I63 -> 52509.6
D64: 45479 | E64: US | F64: 特斯拉 | G64: TSLA | H64: 卖出 | I64: -153 | L64: 1961.856 | M64: =L64*I64 -> -300163.97
D65: 45479 | E65: CN | F65: 传音控股 | G65: 688036 | H65: 卖出 | I65: -360 | L65: 74.63 | M65: =L65*I65 -> -26866.8
D66: 45479 | E66: CN | F66: 中国科传 | G66: 601858 | H66: 卖出 | I66: -10000 | L66: 18.95 | M66: =L66*I66 -> -189500
D67: 45479 | E67: CN | F67: 上海电影 | G67: 601595 | H67: 买入 | I67: 9905 | L67: 19.13 | M67: =L67*I67 -> 189482.65
D68: 45479 | E68: CN | F68: 韦尔股份 | G68: 603501 | H68: 买入 | I68: 1363 | L68: 97.68 | M68: =L68*I68 -> 133137.84
D69: 45479 | E69: CN | F69: 长安汽车 | G69: 000625 | H69: 买入 | I69: 5000 | L69: 13.69 | M69: =L69*I69 -> 68450
D70: 45570 | E70: CN | F70: 斯达半导 | G70: 603290 | H70: 卖出 | I70: -1000 | L70: 91.25 | M70: =L70*I70 -> -91250
D71: 45570 | E71: CN | F71: 中铁装配 | G71: 300374 | H71: 卖出 | I71: -7423 | L71: 16.94 | M71: =L71*I71 -> -125745.62
D72: 45570 | E72: CN | F72: 上海电影 | G72: 601595 | H72: 卖出 | I72: -9905 | L72: 25.3 | M72: =L72*I72 -> -250596.5
... D77: 45591 | E77: CN | F77: 东方财富 | G77: 300059 | H77: 买入 | I77: 10060 | L77: 22.7 | M77: =L77*I77 -> 228362
M78: =L78*I78 -> 0
C79: 54 | M79: =L79*I79 -> 0
D80: 累计净买入 | M80: =SUM(M3:M79) -> 705501.47
D81: 时间 | E81: 市场 | F81: 企业 | G81: 股票代码 | H81: 状态 | I81: 数量 | J81: 平均买价 | K81: 成本 | L81: 当前价格 | M81: 市值
D82: =全班!$R$1 -> 46011 | E82: CN | F82: 消费50ETF | G82: 515650 | H82: 持有 | I82: =SUMIFS($I$75:$I$80,$G$75:$G$80,G82) -> 110000 | J82: =K82/I82 -> 1.048 | K82: =SUMIFS($M$75:$M$80,$G$75:$G$80,G82) -> 115280 | L82: =VLOOKUP(G82,股价!C:D,2,FALSE) -> 1.204 | M82: =IFERROR(I82*L82,0) -> 132440
D83: =全班!$R$1 -> 46011 | E83: CN | F83: 证券ETF | G83: 159841 | H83: 持有 | I83: =SUMIFS($I$75:$I$80,$G$75:$G$80,G83) -> 200000 | J83: =K83/I83 -> 1.033 | K83: =SUMIFS($M$75:$M$80,$G$75:$G$80,G83) -> 206600 | L83: =VLOOKUP(G83,股价!C:D,2,FALSE) -> 1.097 | M83: =IFERROR(I83*L83,0) -> 219400
D84: =全班!$R$1 -> 46011 | E84: CN | F84: 东方财富 | G84: 300059 | H84: 持有 | I84: =SUMIFS($I$75:$I$80,$G$75:$G$80,G84) -> 10060 | J84: =K84/I84 -> 22.7 | K84: =SUMIFS($M$75:$M$80,$G$75:$G$80,G84) -> 228362 | L84: =VLOOKUP(G84,股价!C:D,2,FALSE) -> 23 | M84: =IFERROR(I84*L84,0) -> 231380
M88: =IFERROR(I88*L88,0) -> 0
D89: 市值结余 | M89: =SUM(M82:M88) -> 583220
D90: 累计分红 | M90: =L105 -> 0
D91: 现金结余 | M91: =M96-M80+M90 -> 294498.53
D92: 结余总额 | M92: =M89+M91 -> 877718.53
D93: 累计盈利 | M93: =M92-M96 -> -122281.47
D94: 盈利率 | M94: =M93/M96 -> -0.12228147
D96: 本金 | M96: =本金与余额!D9 -> 1000000
D97: 登记日 | E97: 市场 | F97: 企业 | G97: 股票代码 | H97: 状态 | I97: 数量 | J97: 分红方案 | K97: 实施 | L97: 红利金额 | M97: 除权日
D105: 累计分红 | L105: =SUM(L98:L104) -> 0
D110: =全班!$R$1 -> 46011 | E110: CN | F110: 东田微 | G110: 301183 | H110: 持有 | I110: =SUMIFS($I$18:$I$80,$G$18:$G$80,G110) -> 0 | J110: =K110/I110 -> #DIV/0! | K110: =SUMIFS($M$18:$M$80,$G$18:$G$80,G110) -> 0 | L110: =VLOOKUP(G110,股价!C:D,2,FALSE) -> #N/A | M110: =IFERROR(I110*L110,0) -> 0
D111: =全班!$R$1 -> 46011 | E111: CN | F111: 姚记科技 | G111: 00265 | H111: 持有 | I111: =SUMIFS($I$18:$I$80,$G$18:$G$80,G111) -> 0 | J111: =K111/I111 -> #DIV/0! | K111: =SUMIFS($M$18:$M$80,$G$18:$G$80,G111) -> 0 | L111: =VLOOKUP(G111,股价!C:D,2,FALSE) -> #N/A | M111: =IFERROR(I111*L111,0) -> 0

Sheet 怡锋
A1: back | D1: 操盘：骆怡锋
D2: 时间 | E2: 市场 | F2: 企业 | G2: 股票代码 | H2: 操作 | I2: 数量 | J2: 平均买价 | K2: 成本 | L2: 买卖价格 | M2: 市值
C3: 2 | D3: 45150 | E3: HK | F3: 中芯国际 | G3: 981 | H3: 买入 | I3: 10000 | L3: 18.1 | M3: =L3*I3 -> 181000
C4: 8 | D4: 45241 | E4: HK | F4: 中芯国际 | G4: 981 | H4: 卖出 | I4: -10000 | L4: 21.8 | M4: =L4*I4 -> -218000
C5: 5 | D5: 45185 | E5: CN | F5: 浪潮信息 | G5: 000977 | H5: 买入 | I5: 8000 | L5: 35.82 | M5: =L5*I5 -> 286560
C6: 6 | D6: 45220 | E6: CN | F6: 浪潮信息 | G6: 000977 | H6: 买入 | I6: 1600 | L6: 29.65 | M6: =L6*I6 -> 47440
C7: 9 | D7: 45241 | E7: CN | F7: 钧达股份 | G7: 002865 | H7: 买入 | I7: 2000 | L7: 95.26 | M7: =L7*I7 -> 190520
C8: 10 | D8: 45241 | E8: CN | F8: 润和软件 | G8: 300339 | H8: 买入 | I8: 12879 | L8: 27.15 | M8: =L8*I8 -> 349664.85
C9: 9 | D9: 45367 | E9: CN | F9: 浪潮信息 | G9: 000977 | H9: 卖出 | I9: -5000 | L9: 39.98 | M9: =L9*I9 -> -199900
D10: 45367 | E10: CN | F10: 博创科技 | G10: 300548 | H10: 买入 | I10: 6704 | L10: 29.82 | M10: =L10*I10 -> 199913.28
D11: 45500 | E11: CN | F11: 浪潮信息 | G11: 000977 | H11: 卖出 | I11: -4600 | L11: 37.1 | M11: =L11*I11 -> -170660
D12: 45500 | E12: CN | F12: 钧达股份 | G12: 002865 | H12: 卖出 | I12: -2000 | L12: 36.81 | M12: =L12*I12 -> -73620
D13: 45500 | E13: CN | F13: 润和软件 | G13: 300339 | H13: 卖出 | I13: -12879 | L13: 20.04 | M13: =L13*I13 -> -258095.16
D14: 45500 | E14: CN | F14: 博创科技 | G14: 300548 | H14: 卖出 | I14: -6704 | L14: 17.79 | M14: =L14*I14 -> -119264.16
C15: 1 | D15: 45136 | E15: HK | F15: 小米集团 | G15: 01810 | H15: 买入 | I15: 20000 | L15: 12.18 | M15: =L15*I15 -> 243600
C16: 3 | D16: 45164 | E16: HK | F16: 小米集团 | G16: 01810 | H16: 买入 | I16: 10000 | L16: 12.1 | M16: =L16*I16 -> 121000
C17: 4 | D17: 45178 | E17: HK | F17: 小米集团 | G17: 01810 | H17: 买入 | I17: 10000 | L17: 11.9 | M17: =L17*I17 -> 119000
D18: 45500 | E18: US | F18: 超微电脑 | G18: SMCI | H18: 买入 | I18: 111 | L18: 5555.082 | M18: =L18*I18 -> 616614.1
D19: 45566 | E19: US | F19: 超微电脑 | G19: SMCI | H19: 拆股 | I19: 999 | M19: =L19*I19 -> 0
D20: 45241 | E20: HK | F20: 小米集团 | G20: 01810 | H20: 卖出 | I20: -20000 | L20: 16.04 | M20: =L20*I20 -> -320800
D21: 45661 | E21: HK | F21: 小米集团 | G21: 01810 | H21: 卖出 | I21: -5000 | L21: 36.25 | M21: =L21*I21 -> -181250
D22: 45661 | E22: US | F22: 超微电脑 | G22: SMCI | H22: 买入 | I22: 716 | L22: 259.974 | M22: =L22*I22 -> 186141.38
D23: 45710 | E23: HK | F23: 小米集团 | G23: 01810 | H23: 卖出 | I23: -8000 | L23: 51.7 | M23: =L23*I23 -> -413600
D24: 45710 | E24: US | F24: 超微电脑 | G24: SMCI | H24: 卖出 | I24: -800 | L24: 437.346 | M24: =L24*I24 -> -349876.8
D25: 45710 | E25: CN | F25: 贵州茅台 | G25: 600519 | H25: 买入 | I25: 200 | L25: 1488.21 | M25: =L25*I25 -> 297642
D26: 45717 | E26: US | F26: 超微电脑 | G26: SMCI | H26: 买入 | I26: 300 | L26: 323.388 | M26: =L26*I26 -> 97016.4
D27: 45724 | E27: US | F27: 超微电脑 | G27: SMCI | H27: 买入 | I27: 400 | L27: 298.272 | M27: =L27*I27 -> 119308.8
D28: 45724 | E28: CN | F28: 包钢股份 | G28: 600010 | H28: 买入 | I28: 60000 | L28: 1.86 | M28: =L28*I28 -> 111600
D29: 45724 | E29: CN | F29: 易华录 | G29: 300212 | H29: 买入 | I29: 4000 | L29: 28.08 | M29: =L29*I29 -> 112320
D30: 45731 | E30: CN | F30: 包钢股份 | G30: 600010 | H30: 卖出 | I30: -30000 | L30: 1.9 | M30: =L30*I30 -> -57000
D31: 45731 | E31: CN | F31: 酒鬼酒 | G31: 000799 | H31: 买入 | I31: 1594 | L31: 51.88 | M31: =L31*I31 -> 82696.72
... D41: 45913 | E41: US | F41: 消费ETF龙头 | G41: 560680 | H41: 买入 | I41: 50000 | L41: 0.963 | M41: =L41*I41 -> 48150
M42: =L42*I42 -> 0
C43: 10 | M43: =L43*I43 -> 0
D44: 累计净买入 | M44: =SUM(M3:M43) -> 890920.97
C45: 骆怡锋 | D45: 时间 | E45: 市场 | F45: 企业 | G45: 股票代码 | H45: 状态 | I45: 数量 | J45: 平均买价 | K45: 成本 | L45: 当前价格 | M45: 市值
D46: =全班!$R$1 -> 46011 | E46: HK | F46: 小米集团 | G46: 01810 | H46: 持有 | I46: =SUMIFS($I$15:$I$44,$G$15:$G$44,G46) -> 7000 | J46: =K46/I46 -> -61.721429 | K46: =SUMIFS($M$15:$M$44,$G$15:$G$44,G46) -> -432050 | L46: =VLOOKUP(G46,股价!C:D,2,FALSE) -> 40.54 | M46: =IFERROR(I46*L46,0) -> 283780
D47: =全班!$R$1 -> 46011 | E47: US | F47: 超微电脑 | G47: SMCI | H47: 持有 | I47: =SUMIFS($I$15:$I$44,$G$15:$G$44,G47) -> 919 | J47: =K47/I47 -> 336.34678 | K47: =SUMIFS($M$15:$M$44,$G$15:$G$44,G47) -> 309102.69 | L47: =VLOOKUP(G47,股价!C:D,2,FALSE) -> 242.658 | M47: =IFERROR(I47*L47,0) -> 223002.7
D48: =全班!$R$1 -> 46011 | E48: CN | F48: 贵州茅台 | G48: 600519 | H48: 持有 | I48: =SUMIFS($I$15:$I$44,$G$15:$G$44,G48) -> 100 | J48: =K48/I48 -> 1391.21 | K48: =SUMIFS($M$15:$M$44,$G$15:$G$44,G48) -> 139121 | L48: =VLOOKUP(G48,股价!C:D,2,FALSE) -> 1410 | M48: =IFERROR(I48*L48,0) -> 141000
D49: =全班!$R$1 -> 46011 | E49: CN | F49: 包钢股份 | G49: 600010 | H49: 持有 | I49: =SUMIFS($I$15:$I$44,$G$15:$G$44,G49) -> 30000 | J49: =K49/I49 -> 1.82 | K49: =SUMIFS($M$15:$M$44,$G$15:$G$44,G49) -> 54600 | L49: =VLOOKUP(G49,股价!C:D,2,FALSE) -> 2.37 | M49: =IFERROR(I49*L49,0) -> 71100
D50: =全班!$R$1 -> 46011 | E50: CN | F50: 易华录 | G50: 300212 | H50: 持有 | I50: =SUMIFS($I$15:$I$44,$G$15:$G$44,G50) -> 7000 | J50: =K50/I50 -> 25.217143 | K50: =SUMIFS($M$15:$M$44,$G$15:$G$44,G50) -> 176520 | L50: =VLOOKUP(G50,股价!C:D,2,FALSE) -> 16.23 | M50: =IFERROR(I50*L50,0) -> 113610
D51: =全班!$R$1 -> 46011 | E51: CN | F51: 酒鬼酒 | G51: 000799 | H51: 持有 | I51: =SUMIFS($I$15:$I$44,$G$15:$G$44,G51) -> 1594 | J51: =K51/I51 -> 51.88 | K51: =SUMIFS($M$15:$M$44,$G$15:$G$44,G51) -> 82696.72 | L51: =VLOOKUP(G51,股价!C:D,2,FALSE) -> 55.54 | M51: =IFERROR(I51*L51,0) -> 88530.76
D52: =全班!$R$1 -> 46011 | E52: US | F52: 特斯拉 | G52: TSLA | H52: 持有 | I52: =SUMIFS($I$15:$I$44,$G$15:$G$44,G52) -> 80 | J52: =K52/I52 -> 2465.268 | K52: =SUMIFS($M$15:$M$44,$G$15:$G$44,G52) -> 197221.44 | L52: =VLOOKUP(G52,股价!C:D,2,FALSE) -> 3753.36 | M52: =IFERROR(I52*L52,0) -> 300268.8
D53: =全班!$R$1 -> 46011 | E53: US | F53: 酒LOF | G53: 160632 | H53: 持有 | I53: =SUMIFS($I$15:$I$44,$G$15:$G$44,G53) -> 262468 | J53: =K53/I53 -> 0.381 | K53: =SUMIFS($M$15:$M$44,$G$15:$G$44,G53) -> 100000.31 | L53: =VLOOKUP(G53,股价!C:D,2,FALSE) -> #N/A | M53: =IFERROR(I53*L53,0) -> 0
D54: =全班!$R$1 -> 46011 | E54: US | F54: 消费ETF龙头 | G54: 560680 | H54: 持有 | I54: =SUMIFS($I$15:$I$44,$G$15:$G$44,G54) -> 50000 | J54: =K54/I54 -> 0.963 | K54: =SUMIFS($M$15:$M$44,$G$15:$G$44,G54) -> 48150 | L54: =VLOOKUP(G54,股价!C:D,2,FALSE) -> 0.885 | M54: =IFERROR(I54*L54,0) -> 44250
D57: 市值结余 | M57: =SUM(M46:M56) -> 1265542.3
D58: 累计分红 | M58: =L71 -> 0
D59: 现金结余 | M59: =M64-M44+M58 -> 109079.03
D60: 结余总额 | M60: =M57+M59 -> 1374621.3
D61: 累计盈利 | M61: =M60-M64 -> 374621.29
D62: 盈利率 | M62: =M61/M64 -> 0.37462129
D64: 本金 | M64: =本金与余额!D10 -> 1000000
D65: 登记日 | E65: 市场 | F65: 企业 | G65: 股票代码 | H65: 状态 | I65: 数量 | J65: 分红方案 | K65: 实施 | L65: 红利金额 | M65: 除权日
D66: 45566 | E66: US | F66: 超微电脑 | G66: SMCI | H66: 拆股 | I66: 111 | J66: 1拆10 | K66: =I66*10 -> 1110 | M66: 45566
D71: 累计分红 | L71: =SUM(L66:L70) -> 0

Sheet 闯振
A1: back | D1: 操盘：候闯振
D2: 时间 | E2: 市场 | F2: 企业 | G2: 股票代码 | H2: 操作 | I2: 数量 | J2: 平均买价 | K2: 成本 | L2: 买卖价格 | M2: 市值
C3: 1 | D3: 45136 | E3: US | F3: 亚马逊 | G3: AMZN | H3: 买入 | I3: 225 | L3: 1031.238 | M3: =L3*I3 -> 232028.55
C4: 2 | D4: 45220 | E4: US | F4: 亚马逊 | G4: AMZN | H4: 卖出 | I4: -145 | L4: 976.326 | M4: =L4*I4 -> -141567.27
C5: 3 | D5: 45247 | E5: US | F5: 亚马逊 | G5: AMZN | H5: 卖出 | I5: -80 | L5: 1132.404 | M5: =L5*I5 -> -90592.32
C6: 4 | D6: 45220 | E6: US | F6: 英伟达 | G6: NVDA | H6: 买入 | I6: 25 | L6: 3228.186 | M6: =L6*I6 -> 80704.65
C7: 5 | D7: 45247 | E7: US | F7: 英伟达 | G7: NVDA | H7: 卖出 | I7: -25 | L7: 3845.244 | M7: =L7*I7 -> -96131.1
C8: 8 | D8: 45136 | E8: HK | F8: 腾讯集团 | G8: 00700 | H8: 买入 | I8: 800 | L8: 350.4 | M8: =L8*I8 -> 280320
C9: 9 | D9: 45220 | E9: HK | F9: 腾讯集团 | G9: 00700 | H9: 卖出 | I9: -800 | L9: 289 | M9: =L9*I9 -> -231200
C10: 6 | D10: 45136 | E10: US | F10: 阿里巴巴 | G10: BABA | H10: 买入 | I10: 400 | L10: 784.29 | M10: =L10*I10 -> 313716
C11: 7 | D11: 45136 | E11: HK | F11: 碧桂园 | G11: 02007 | H11: 买入 | I11: 100169 | L11: 1.69 | M11: =L11*I11 -> 169285.61
C12: 10 | D12: 45220 | E12: HK | F12: 碧桂园 | G12: 02007 | H12: 卖出 | I12: -100169 | L12: 0.75 | M12: =L12*I12 -> -75126.75
D13: 45276 | E13: US | F13: 阿里巴巴 | G13: BABA | H13: 卖出 | I13: -300 | L13: 581.178 | M13: =L13*I13 -> -174353.4
D14: 45276 | E14: HK | F14: 东方甄选 | G14: 1797 | H14: 买入 | I14: 6700 | L14: 26.25 | M14: =L14*I14 -> 175875
D15: 45283 | E15: HK | F15: 东方甄选 | G15: 1797 | H15: 卖出 | I15: -6700 | L15: 28.85 | M15: =L15*I15 -> -193295
D16: 45283 | E16: HK | F16: 腾讯集团 | G16: 00700 | H16: 买入 | I16: 705 | L16: 274 | M16: =L16*I16 -> 193170
D17: 45479 | E17: US | F17: 阿里巴巴 | G17: BABA | H17: 卖出 | I17: -100 | L17: 581.256 | M17: =L17*I17 -> -58125.6
D18: 45479 | E18: HK | F18: 腾讯集团 | G18: 00700 | H18: 卖出 | I18: -705 | L18: 379.8 | M18: =L18*I18 -> -267759
D19: 45479 | E19: US | F19: 耐克 | G19: NKE | H19: 买入 | I19: 454 | L19: 588.354 | M19: =L19*I19 -> 267112.72
D20: 45507 | E20: US | F20: 耐克 | G20: NKE | H20: 卖出 | I20: -454 | L20: 577.278 | M20: =L20*I20 -> -262084.21
C21: 11 | D21: 45220 | E21: US | F21: 特斯拉 | G21: TSLA | H21: 买入 | I21: 223 | L21: 1653.522 | M21: =L21*I21 -> 368735.41
C22: 12 | D22: 45247 | E22: US | F22: 特斯拉 | G22: TSLA | H22: 买入 | I22: 103 | L22: 1827.54 | M22: =L22*I22 -> 188236.62
D23: 45479 | E23: US | F23: 英伟达 | G23: NVDA | H23: 买入 | I23: 60 | L23: 981.474 | M23: =L23*I23 -> 58888.44
D24: 45507 | E24: US | F24: 亚马逊 | G24: AMZN | H24: 买入 | I24: 200 | L24: 1309.62 | M24: =L24*I24 -> 261924
D25: 45528 | E25: US | F25: 英伟达 | G25: NVDA | H25: 卖出 | I25: -60 | L25: 1009.086 | M25: =L25*I25 -> -60545.16
D26: 45528 | E26: US | F26: 特斯拉 | G26: TSLA | H26: 卖出 | I26: -326 | L26: 1718.496 | M26: =L26*I26 -> -560229.7
D27: 45528 | E27: US | F27: 亚马逊 | G27: AMZN | H27: 卖出 | I27: -200 | L27: 1380.912 | M27: =L27*I27 -> -276182.4
D28: 45542 | E28: US | F28: 特斯拉 | G28: TSLA | H28: 买入 | I28: 272 | L28: 1643.694 | M28: =L28*I28 -> 447084.77
D29: 45542 | E29: US | F29: 英伟达 | G29: NVDA | H29: 买入 | I29: 561 | L29: 802.074 | M29: =L29*I29 -> 449963.51
D30: 45556 | E30: US | F30: 特斯拉 | G30: TSLA | H30: 卖出 | I30: -272 | L30: 1858.35 | M30: =L30*I30 -> -505471.2
D31: 45556 | E31: US | F31: 英伟达 | G31: NVDA | H31: 卖出 | I31: -561 | L31: 904.8 | M31: =L31*I31 -> -507592.8
D32: 45556 | E32: CN | F32: 药明康德 | G32: 603259 | H32: 买入 | I32: 24968 | L32: 40.58 | M32: =L32*I32 -> 1013201.4
D33: 45577 | E33: CN | F33: 药明康德 | G33: 603259 | H33: 卖出 | I33: -24968 | L33: 51.45 | M33: =L33*I33 -> -1284603.6
D34: 45710 | E34: US | F34: 英伟达 | G34: NVDA | H34: 买入 | I34: 1186 | L34: 1083.03 | M34: =L34*I34 -> 1284473.6
... D38: 45976 | E38: US | F38: 特斯拉 | G38: TSLA | H38: 买入 | I38: 591 | L38: 3153.93 | M38: =L38*I38 -> 1863972.6
M39: =L39*I39 -> 0
M40: =L40*I40 -> 0
M41: =L41*I41 -> 0
M42: =L42*I42 -> 0
M43: =L43*I43 -> 0
D44: 累计净买入 | M44: =SUM(M3:M43) -> 999394.89
D45: 时间 | E45: 市场 | F45: 企业 | G45: 股票代码 | H45: 状态 | I45: 数量 | J45: 平均买价 | K45: 成本 | L45: 当前价格 | M45: 市值
D46: =全班!$R$1 -> 46011 | E46: US | F46: 特斯拉 | G46: TSLA | H46: 持有 | I46: =SUMIFS($I$38:$I$44,$G$38:$G$44,G46) -> 591 | J46: =K46/I46 -> 3153.93 | K46: =SUMIFS($M$38:$M$44,$G$38:$G$44,G46) -> 1863972.6 | L46: =VLOOKUP(G46,股价!C:D,2,FALSE) -> 3753.36 | M46: =IFERROR(I46*L46,0) -> 2218235.8
D50: 市值结余 | M50: =SUM(M46:M49) -> 2218235.8
D51: 累计分红 | M51: =L63 -> 0
D52: 现金结余 | M52: =M57-M44+M51 -> 605.108
D53: 结余总额 | M53: =M50+M52 -> 2218840.9
D54: 累计盈利 | M54: =M53-M57 -> 1218840.9
D55: 盈利率 | M55: =M54/M57 -> 1.2188409
D57: 本金 | M57: =本金与余额!D13 -> 1000000
D58: 登记日 | E58: 市场 | F58: 企业 | G58: 股票代码 | H58: 状态 | I58: 数量 | J58: 分红方案 | K58: 实施 | L58: 红利金额 | M58: 除权日
D63: 累计分红 | L63: =SUM(L59:L62) -> 0
D65: 历史购买名单 | F65: 交易次数
C66: 1 | D66: 华安证券 | F66: 4
C67: 2 | D67: 中天科技

Sheet 天明
A1: back | D1: 操盘：杨天明 | O1: 操盘：杨天明
D2: 时间 | E2: 市场 | F2: 企业 | G2: 股票代码 | H2: 操作 | I2: 数量 | J2: 平均买价 | K2: 成本 | L2: 买卖价格 | M2: 市值 | O2: 时间 | P2: 市场 | Q2: 企业 | R2: 股票代码 | S2: 操作 | T2: 数量 | U2: 平均买价 | V2: 成本 | W2: 买卖价格 | X2: 市值
C3: 1 | M3: =L3*I3 -> 0 | X3: =W3*T3 -> 0
C4: 2 | M4: =L4*I4 -> 0 | X4: =W4*T4 -> 0
C5: 3 | M5: =L5*I5 -> 0 | X5: =W5*T5 -> 0
C6: 4 | M6: =L6*I6 -> 0 | X6: =W6*T6 -> 0
C7: 5 | M7: =L7*I7 -> 0 | X7: =W7*T7 -> 0
C8: 6 | M8: =L8*I8 -> 0 | X8: =W8*T8 -> 0
C9: 7 | M9: =L9*I9 -> 0 | X9: =W9*T9 -> 0
C10: 8 | M10: =L10*I10 -> 0 | X10: =W10*T10 -> 0
C11: 9 | M11: =L11*I11 -> 0 | X11: =W11*T11 -> 0
C12: 10 | M12: =L12*I12 -> 0 | X12: =W12*T12 -> 0
D13: 累计净买入 | M13: =SUM(M3:M12) -> 0 | O13: 累计净买入 | X13: =SUM(X3:X12) -> 0
D14: 时间 | E14: 市场 | F14: 企业 | G14: 股票代码 | H14: 状态 | I14: 数量 | J14: 平均买价 | K14: 成本 | L14: 当前股价 | M14: 市值 | O14: 时间 | P14: 市场 | Q14: 企业 | R14: 股票代码 | S14: 状态 | T14: 数量 | U14: 平均买价 | V14: 成本 | W14: 当前股价 | X14: 市值
D15: =全班!$R$1 -> 46011 | H15: 持有 | I15: =SUMIFS($I$3:$I$13,$G$3:$G$13,G15) -> 0 | J15: =K15/I15 -> #DIV/0! | K15: =SUMIFS($M$3:$M$13,$G$3:$G$13,G15) -> 0 | L15: =VLOOKUP(G15,股价!C:D,2,FALSE) -> #N/A | M15: =IFERROR(I15*L15,0) -> 0 | O15: =全班!$R$1 -> 46011 | S15: 持有 | T15: =SUMIFS($I$3:$I$13,$G$3:$G$13,R15) -> 0 | U15: =V15/T15 -> #DIV/0! | V15: =SUMIFS($X$3:$X$13,$R$3:$R$13,R15) -> 0 | W15: =VLOOKUP(R15,股价!C:D,2,FALSE) -> #N/A | X15: =T15*W15 -> #N/A
D19: 市值结余 | M19: =SUM(M15:M18) -> 0 | O19: 市值结余 | X19: =SUM(X15:X18) -> #N/A
D20: 累计分红 | M20: =L33 -> 0 | O20: 累计分红 | X20: =W33 -> 0
D21: 现金结余 | M21: =M26-M13+M20 -> 1000000 | O21: 现金结余 | X21: =X26-X13+X20 -> #REF!
D22: 结余总额 | M22: =M19+M21 -> 1000000 | O22: 结余总额 | X22: =X19+X21 -> #N/A
D23: 累计盈利 | M23: =M22-M26 -> 0 | O23: 累计盈利 | X23: =X22-X26 -> #N/A
D24: 盈利率 | M24: =M23/M26 -> 0 | O24: 盈利率 | X24: =X23/X26 -> #N/A
D26: 本金 | M26: =本金与余额!D15 -> 1000000 | O26: 本金 | X26: =本金与余额!#REF! -> #REF!
D27: 登记日 | E27: 市场 | F27: 企业 | G27: 股票代码 | H27: 状态 | I27: 数量 | J27: 分红方案 | K27: 实施 | L27: 红利金额 | M27: 除权日 | O27: 登记日 | P27: 市场 | Q27: 企业 | R27: 股票代码 | S27: 状态 | T27: 数量 | U27: 分红方案 | V27: 实施 | W27: 红利金额 | X27: 除权日
D33: 累计分红 | L33: =SUM(L28:L32) -> 0 | O33: 累计分红 | W33: =SUM(W28:W32) -> 0

Sheet 小林
A1: back | D1: 操盘：纪小林
D2: 时间 | E2: 市场 | F2: 企业 | G2: 股票代码 | H2: 操作 | I2: 数量 | J2: 平均买价 | K2: 成本 | L2: 买卖价格 | M2: 市值
C3: 1 | D3: 45906 | E3: US | F3: 拼多多 | G3: PDD | H3: 买入 | I3: 1026 | L3: 972.504 | M3: =L3*I3 -> 997789.1
C4: 2 | D4: 45997 | E4: US | F4: 拼多多 | G4: PDD | H4: 卖出 | I4: -526 | L4: 917.47149 | M4: =L4*I4 -> -482590
C5: 3 | D5: 45997 | E5: US | F5: 拼多多-期权 | G5: PDD-C130-2026-4-17 | H5: 买入 | I5: 13400 | L5: 35.88 | M5: =L5*I5 -> 480792
C6: 4 | M6: =L6*I6 -> 0
C7: 5 | M7: =L7*I7 -> 0
C8: 6 | M8: =L8*I8 -> 0
C9: 7 | M9: =L9*I9 -> 0
C10: 8 | M10: =L10*I10 -> 0
C11: 9
C12: 10
D13: 累计净买入 | M13: =SUM(M3:M12) -> 995991.1
D14: 时间 | E14: 市场 | F14: 企业 | G14: 股票代码 | H14: 状态 | I14: 数量 | J14: 平均买价 | K14: 成本 | L14: 当前价格 | M14: 市值
D15: =全班!$R$1 -> 46011 | E15: US | F15: 拼多多 | G15: PDD | I15: =SUMIFS($I$3:$I$13,$G$3:$G$13,G15) -> 500 | J15: =K15/I15 -> 1030.3982 | K15: =SUMIFS($M$3:$M$13,$G$3:$G$13,G15) -> 515199.1 | L15: =VLOOKUP(G15,股价!C:D,2,FALSE) -> 854.178 | M15: =IFERROR(I15*L15,0) -> 427089
D16: =全班!$R$1 -> 46011 | E16: US | F16: 拼多多-期权 | G16: PDD-C130-2026-4-17 | I16: =SUMIFS($I$3:$I$13,$G$3:$G$13,G16) -> 13400 | J16: =K16/I16 -> 35.88 | K16: =SUMIFS($M$3:$M$13,$G$3:$G$13,G16) -> 480792 | L16: =VLOOKUP(G16,股价!C:D,2,FALSE) -> 20.982 | M16: =IFERROR(I16*L16,0) -> 281158.8
D19: 市值结余 | M19: =SUM(M15:M18) -> 708247.8
D20: 累计分红 | M20: =L33 -> 0
D21: 现金结余 | M21: =M26-M13+M20 -> 4008.8997
D22: 结余总额 | M22: =M19+M21 -> 712256.7
D23: 累计盈利 | M23: =M22-M26 -> -287743.3
D24: 盈利率 | M24: =M23/M26 -> -0.2877433
D26: 本金 | M26: =本金与余额!D16 -> 1000000
D27: 登记日 | E27: 市场 | F27: 企业 | G27: 股票代码 | H27: 状态 | I27: 数量 | J27: 分红方案 | K27: 实施 | L27: 红利金额 | M27: 除权日
D33: 累计分红 | L33: =SUM(L28:L32) -> 0

Sheet 秀容
A1: back | D1: 操盘：高秀容 | O1: 操盘：高秀容
D2: 时间 | E2: 市场 | F2: 企业 | G2: 股票代码 | H2: 操作 | I2: 数量 | J2: 平均买价 | K2: 成本 | L2: 买卖价格 | M2: 市值 | O2: 时间 | P2: 市场 | Q2: 企业 | R2: 股票代码 | S2: 操作 | T2: 数量 | U2: 平均买价 | V2: 成本 | W2: 买卖价格 | X2: 市值
C3: 1 | M3: =L3*I3 -> 0 | X3: =W3*T3 -> 0
C4: 2 | M4: =L4*I4 -> 0 | X4: =W4*T4 -> 0
C5: 3
C6: 4
C7: 5
C8: 6 | M8: =L8*I8 -> 0 | X8: =W8*T8 -> 0
C9: 7
C10: 8
C11: 9 | M11: =L11*I11 -> 0 | X11: =W11*T11 -> 0
C12: 10 | M12: =L12*I12 -> 0 | X12: =W12*T12 -> 0
D13: 累计净买入 | M13: =SUM(M3:M12) -> 0 | O13: 累计净买入 | X13: =SUM(X3:X12) -> 0
D14: 时间 | E14: 市场 | F14: 企业 | G14: 股票代码 | H14: 状态 | I14: 数量 | J14: 平均买价 | K14: 成本 | L14: 当前股价 | M14: 市值 | O14: 时间 | P14: 市场 | Q14: 企业 | R14: 股票代码 | S14: 状态 | T14: 数量 | U14: 平均买价 | V14: 成本 | W14: 当前股价 | X14: 市值
D15: =全班!$R$1 -> 46011 | I15: =SUMIFS($I$3:$I$13,$G$3:$G$13,G15) -> 0 | J15: =K15/I15 -> #DIV/0! | K15: =SUMIFS($M$3:$M$13,$G$3:$G$13,G15) -> 0 | L15: =VLOOKUP(G15,股价!C:D,2,FALSE) -> #N/A | M15: =IFERROR(I15*L15,0) -> 0 | O15: =全班!$R$1 -> 46011 | T15: =SUMIFS($I$3:$I$13,$G$3:$G$13,R15) -> 0 | U15: =V15/T15 -> #DIV/0! | V15: =SUMIFS($X$3:$X$13,$R$3:$R$13,R15) -> 0 | W15: =VLOOKUP(R15,股价!C:D,2,FALSE) -> #N/A | X15: =T15*W15 -> #N/A
D19: 市值结余 | M19: =SUM(M15:M18) -> 0 | O19: 市值结余 | X19: =SUM(X15:X18) -> #N/A
D20: 累计分红 | M20: =L33 -> 0 | O20: 累计分红 | X20: =W33 -> 0
D21: 现金结余 | M21: =M26-M13+M20 -> 1000000 | O21: 现金结余 | X21: =X26-X13+X20 -> #REF!
D22: 结余总额 | M22: =M19+M21 -> 1000000 | O22: 结余总额 | X22: =X19+X21 -> #N/A
D23: 累计盈利 | M23: =M22-M26 -> 0 | O23: 累计盈利 | X23: =X22-X26 -> #N/A
D24: 盈利率 | M24: =M23/M26 -> 0 | O24: 盈利率 | X24: =X23/X26 -> #N/A
D26: 本金 | M26: =本金与余额!D17 -> 1000000 | O26: 本金 | X26: =本金与余额!#REF! -> #REF!
D27: 登记日 | E27: 市场 | F27: 企业 | G27: 股票代码 | H27: 状态 | I27: 数量 | J27: 分红方案 | K27: 实施 | L27: 红利金额 | M27: 除权日 | O27: 登记日 | P27: 市场 | Q27: 企业 | R27: 股票代码 | S27: 状态 | T27: 数量 | U27: 分红方案 | V27: 实施 | W27: 红利金额 | X27: 除权日
D33: 累计分红 | L33: =SUM(L28:L32) -> 0 | O33: 累计分红 | W33: =SUM(W28:W32) -> 0

Sheet 艺娜
A1: back | D1: 操盘：赵艺娜
D2: 时间 | E2: 市场 | F2: 企业 | G2: 股票代码 | H2: 操作 | I2: 数量 | J2: 平均买价 | K2: 成本 | L2: 买卖价格 | M2: 市值
C3: 1 | D3: 45976 | E3: CN | F3: 亿帆医药 | G3: 002019 | H3: 买入 | I3: 1000 | L3: 13.16 | M3: =L3*I3 -> 13160
C4: 2 | D4: 45976 | E4: CN | F4: 中金公司 | G4: 601995 | H4: 买入 | I4: 1000 | L4: 35.41 | M4: =L4*I4 -> 35410
C5: 3 | D5: 45976 | E5: CN | F5: 东方精工 | G5: 002611 | H5: 买入 | I5: 1000 | L5: 18.02 | M5: =L5*I5 -> 18020
C6: 4 | M6: =L6*I6 -> 0
C7: 5 | M7: =L7*I7 -> 0
C8: 6 | M8: =L8*I8 -> 0
C9: 7 | M9: =L9*I9 -> 0
C10: 8 | M10: =L10*I10 -> 0
C11: 9 | M11: =L11*I11 -> 0
C12: 10 | M12: =L12*I12 -> 0
D13: 累计净买入 | M13: =SUM(M3:M12) -> 66590
D14: 时间 | E14: 市场 | F14: 企业 | G14: 股票代码 | H14: 状态 | I14: 数量 | J14: 平均买价 | K14: 成本 | L14: 当前股价 | M14: 市值
D15: =全班!$R$1 -> 46011 | E15: CN | F15: 亿帆医药 | G15: 002019 | H15: 持有 | I15: =SUMIFS($I$3:$I$13,$G$3:$G$13,G15) -> 1000 | J15: =K15/I15 -> 13.16 | K15: =SUMIFS($M$3:$M$13,$G$3:$G$13,G15) -> 13160 | L15: =VLOOKUP(G15,股价!C:D,2,FALSE) -> 12 | M15: =IFERROR(I15*L15,0) -> 12000
D16: =全班!$R$1 -> 46011 | E16: CN | F16: 中金公司 | G16: 601995 | H16: 持有 | I16: =SUMIFS($I$3:$I$13,$G$3:$G$13,G16) -> 1000 | J16: =K16/I16 -> 35.41 | K16: =SUMIFS($M$3:$M$13,$G$3:$G$13,G16) -> 35410 | L16: =VLOOKUP(G16,股价!C:D,2,FALSE) -> 35.92 | M16: =IFERROR(I16*L16,0) -> 35920
D17: =全班!$R$1 -> 46011 | E17: CN | F17: 东方精工 | G17: 002611 | H17: 持有 | I17: =SUMIFS($I$3:$I$13,$G$3:$G$13,G17) -> 1000 | J17: =K17/I17 -> 18.02 | K17: =SUMIFS($M$3:$M$13,$G$3:$G$13,G17) -> 18020 | L17: =VLOOKUP(G17,股价!C:D,2,FALSE) -> 17.68 | M17: =IFERROR(I17*L17,0) -> 17680
D22: 市值结余 | M22: =SUM(M15:M21) -> 65600
D23: 累计分红 | M23: =L36 -> 0
D24: 现金结余 | M24: =M29-M13+M23 -> 933410
D25: 结余总额 | M25: =M22+M24 -> 999010
D26: 累计盈利 | M26: =M25-M29 -> -990
D27: 盈利率 | M27: =M26/M29 -> -0.00099
D29: 本金 | M29: =本金与余额!D14 -> 1000000
D30: 登记日 | E30: 市场 | F30: 企业 | G30: 股票代码 | H30: 状态 | I30: 数量 | J30: 分红方案 | K30: 实施 | L30: 红利金额 | M30: 除权日
D36: 累计分红 | L36: =SUM(L31:L35) -> 0

Sheet 季生
A1: back | D1: 操盘：季院生
D2: 时间 | E2: 市场 | F2: 企业 | G2: 股票代码 | H2: 操作 | I2: 数量 | J2: 平均买价 | K2: 成本 | L2: 买卖价格 | M2: 市值
C3: 1 | D3: 45150 | E3: HK | F3: 山东黄金 | G3: 1787 | H3: 买入 | I3: 2500 | L3: 15.3 | M3: =L3*I3 -> 38250
C4: 2 | D4: 45157 | E4: HK | F4: 山东黄金 | G4: 1787 | H4: 买入 | I4: 3000 | L4: 14.9 | M4: =L4*I4 -> 44700
C5: 3 | D5: 45178 | E5: CN | F5: 比亚迪 | G5: 002594 | H5: 买入 | I5: 3757 | L5: 244.05 | M5: =L5*I5 -> 916895.85
C6: 4 | D6: 45353 | E6: CN | F6: 比亚迪 | G6: 002594 | H6: 卖出 | I6: -3757 | L6: 192.18 | M6: =L6*I6 -> -722020.26
C7: 5 | D7: 45353 | E7: HK | F7: 山东黄金 | G7: 1787 | H7: 买入 | I7: 55637 | L7: 12.98 | M7: =L7*I7 -> 722168.26
C8: 6 | D8: 45395 | E8: HK | F8: 山东黄金 | G8: 1787 | H8: 卖出 | I8: -61137 | L8: 19.66 | M8: =L8*I8 -> -1201953.4
C9: 7 | D9: 45395 | E9: CN | F9: 同花顺 | G9: 300033 | H9: 买入 | I9: 3200 | L9: 112.91 | M9: =L9*I9 -> 361312
C10: 8 | D10: 45409 | E10: CN | F10: 同花顺 | G10: 300033 | H10: 买入 | I10: 2085 | L10: 121 | M10: =L10*I10 -> 252285
C11: 9 | D11: 45437 | E11: CN | F11: 同花顺 | G11: 300033 | H11: 买入 | I11: 5140 | L11: 114.46 | M11: =L11*I11 -> 588324.4
D12: 45542 | E12: CN | F12: 同花顺 | G12: 300033 | H12: 卖出 | I12: -10425 | L12: 99.6 | M12: =L12*I12 -> -1038330
D13: 45542 | E13: US | F13: 英伟达 | G13: NVDA | H13: 买入 | I13: 1294 | L13: 802.074 | M13: =L13*I13 -> 1037883.8
D14: 45612 | E14: US | F14: 英伟达 | G14: NVDA | H14: 卖出 | I14: -1294 | L14: 1107.444 | M14: =L14*I14 -> -1433032.5
D15: 45612 | E15: HK | F15: 山东黄金 | G15: 01787 | H15: 买入 | I15: 106502 | L15: 13.46 | M15: =L15*I15 -> 1433516.9
D16: 45640 | E16: HK | F16: 山东黄金 | G16: 01787 | H16: 卖出 | I16: -106502 | L16: 13.54 | M16: =L16*I16 -> -1442037.1
D17: 45640 | E17: US | F17: 谷歌 | G17: GOOGL | H17: 买入 | I17: 973 | L17: 1481.376 | M17: =L17*I17 -> 1441378.8
D18: 45752 | E18: US | F18: 谷歌 | G18: GOOGL | H18: 卖出 | I18: -486 | L18: 1135.68 | M18: =L18*I18 -> -551940.48
D19: 45752 | E19: US | F19: 纳斯达克100三倍做空 | G19: SQQQ | H19: 买入 | I19: 703 | L19: 392.808 | M19: =L19*I19 -> 276144.02
D20: 45759 | E20: US | F20: 纳斯达克100三倍做空 | G20: SQQQ | H20: 卖出 | I20: -703 | L20: 282.516 | M20: =L20*I20 -> -198608.75
D21: 45759 | E21: US | F21: 丰田工业ADR | G21: TYIDY | H21: 买入 | I21: 419 | L21: 659.802 | M21: =L21*I21 -> 276457.04
D22: 45787 | E22: US | F22: 谷歌 | G22: GOOGL | H22: 卖出 | I22: -243 | L22: 1191.45 | M22: =L22*I22 -> -289522.35
D23: 45794 | E23: US | F23: 谷歌 | G23: GOOGL | H23: 卖出 | I23: -244 | L23: 1296.282 | M23: =L23*I23 -> -316292.81
... D52: 46011 | E52: US | F52: 英伟达 | G52: NVDA | H52: 买入 | I52: 355 | L52: 1411.722 | M52: =L52*I52 -> 501161.31
M53: =L53*I53 -> 0
M54: =L54*I54 -> 0
M55: =L55*I55 -> 0
M56: =L56*I56 -> 0
M57: =L57*I57 -> 0
C58: 10 | M58: =L58*I58 -> 0
D59: 累计净买入 | M59: =SUM(M3:M58) -> -24432.978
D60: 时间 | E60: 市场 | F60: 企业 | G60: 股票代码 | H60: 状态 | I60: 数量 | J60: 平均买价 | K60: 成本 | L60: 当前价格 | M60: 市值
D61: =全班!$R$1 -> 46011 | E61: US | F61: 甲骨文 | G61: ORCL | H61: 持有 | I61: =SUMIFS($I$51:$I$59,$G$51:$G$59,G61) -> 333 | J61: =K61/I61 -> 1497.366 | K61: =SUMIFS($M$51:$M$59,$G$51:$G$59,G61) -> 498622.88 | L61: =VLOOKUP(G61,股价!C:D,2,FALSE) -> 1497.366 | M61: =IFERROR(I61*L61,0) -> 498622.88
D62: =全班!$R$1 -> 46011 | E62: US | F62: 英伟达 | G62: NVDA | H62: 持有 | I62: =SUMIFS($I$51:$I$59,$G$51:$G$59,G62) -> 355 | J62: =K62/I62 -> 1411.722 | K62: =SUMIFS($M$51:$M$59,$G$51:$G$59,G62) -> 501161.31 | L62: =VLOOKUP(G62,股价!C:D,2,FALSE) -> 1411.722 | M62: =IFERROR(I62*L62,0) -> 501161.31
D63: =全班!$R$1 -> 46011 | H63: 持有 | I63: =SUMIFS($I$51:$I$59,$G$51:$G$59,G63) -> 0 | J63: =K63/I63 -> #DIV/0! | K63: =SUMIFS($M$51:$M$59,$G$51:$G$59,G63) -> 0 | L63: =VLOOKUP(G63,股价!C:D,2,FALSE) -> #N/A | M63: =IFERROR(I63*L63,0) -> 0
M64: =IFERROR(I64*L64,0) -> 0
D65: 市值结余 | M65: =SUM(M61:M64) -> 999784.19
D66: 累计分红 | M66: =L79 -> 0
D67: 现金结余 | M67: =M72-M59+M66 -> 1024433
D68: 结余总额 | M68: =M65+M67 -> 2024217.2
D69: 累计盈利 | M69: =M68-M72 -> 1024217.2
D70: 盈利率 | M70: =M69/M72 -> 1.0242172
D72: 本金 | M72: =本金与余额!D19 -> 1000000
D73: 登记日 | E73: 市场 | F73: 企业 | G73: 股票代码 | H73: 状态 | I73: 数量 | J73: 分红方案 | K73: 实施 | L73: 红利金额 | M73: 除权日
D79: 累计分红 | L79: =SUM(L74:L78) -> 0
M81: =M67*0.3/L61 -> 205.24701

Sheet 万辉
A1: back | D1: 操盘：于万辉
D2: 时间 | E2: 市场 | F2: 企业 | G2: 股票代码 | H2: 操作 | I2: 数量 | J2: 平均买价 | K2: 成本 | L2: 买卖价格 | M2: 市值
C3: 1 | D3: 45136 | E3: CN | F3: 证券ETF | G3: 512880 | H3: 买入 | I3: 400000 | L3: 1.017 | M3: =L3*I3 -> 406800
C4: 2 | D4: 45157 | E4: CN | F4: 证券ETF | G4: 512880 | H4: 卖出 | I4: -200000 | L4: 1.021 | M4: =L4*I4 -> -204200
C5: 3 | D5: 45255 | E5: CN | F5: 证券ETF | G5: 512880 | H5: 卖出 | I5: -200000 | L5: 0.957 | M5: =L5*I5 -> -191400
C6: 4 | D6: 45255 | E6: CN | F6: 智飞生物 | G6: 300122 | H6: 买入 | I6: 1000 | L6: 66.12 | M6: =L6*I6 -> 66120
C7: 5 | D7: 45283 | E7: CN | F7: 智飞生物 | G7: 300122 | H7: 卖出 | I7: -1000 | L7: 57.79 | M7: =L7*I7 -> -57790
C8: 6 | D8: 45136 | E8: US | F8: 英伟达 | G8: NVDA | H8: 买入 | I8: 2 | L8: =467.5*7.8 -> 3646.5 | M8: =L8*I8 -> 7293
C9: 7 | D9: 45150 | E9: US | F9: 英伟达 | G9: NVDA | H9: 卖出 | I9: -2 | L9: 3186.69 | M9: =L9*I9 -> -6373.38
C10: 8 | D10: 45136 | E10: HK | F10: 中芯国际 | G10: 981 | H10: 买入 | I10: 1000 | L10: 19.62 | M10: =L10*I10 -> 19620
C11: 9 | D11: 45178 | E11: HK | F11: 中芯国际 | G11: 981 | H11: 卖出 | I11: -1000 | L11: 19.8 | M11: =L11*I11 -> -19800
C12: 10 | D12: 45136 | E12: HK | F12: 融创中国 | G12: 1918 | H12: 买入 | I12: 10000 | L12: 1.38 | M12: =L12*I12 -> 13800
C13: 11 | D13: 45178 | E13: HK | F13: 融创中国 | G13: 1918 | H13: 卖出 | I13: -10000 | L13: 2.48 | M13: =L13*I13 -> -24800
C14: 12 | D14: 45136 | E14: CN | F14: 华熙生物 | G14: 688363 | H14: 买入 | I14: 1000 | L14: 96.97 | M14: =L14*I14 -> 96970
C15: 13 | D15: 45178 | E15: CN | F15: 华熙生物 | G15: 688363 | H15: 卖出 | I15: -1000 | L15: 89 | M15: =L15*I15 -> -89000
C16: 14 | D16: 45164 | E16: CN | F16: 中国平安 | G16: 601318 | H16: 买入 | I16: 5000 | L16: 47.01 | M16: =L16*I16 -> 235050
C17: 15 | D17: 45178 | E17: CN | F17: 中国平安 | G17: 601318 | H17: 卖出 | I17: -4000 | L17: 50.12 | M17: =L17*I17 -> -200480
C18: 16 | D18: 45234 | E18: CN | F18: 中国平安 | G18: 601318 | H18: 买入 | I18: 3000 | L18: 45.24 | M18: =L18*I18 -> 135720
C19: 17 | D19: 45290 | E19: CN | F19: 中国平安 | G19: 601318 | H19: 卖出 | I19: -4000 | L19: 40.3 | M19: =L19*I19 -> -161200
C20: 18 | D20: 45192 | E20: CN | F20: 万泰生物 | G20: 603392 | H20: 买入 | I20: 8000 | L20: 48.71 | M20: =L20*I20 -> 389680
C21: 19 | D21: 45290 | E21: CN | F21: 万泰生物 | G21: 603392 | H21: 卖出 | I21: -4000 | L21: 75.13 | M21: =L21*I21 -> -300520
... C24: 22 | D24: 45178 | E24: CN | F24: 宁德时代 | G24: 300750 | H24: 卖出 | I24: -900 | L24: 222.94 | M24: =L24*I24 -> -200646
C25: 23 | D25: =全班!$R$1 -> 46011 | E25: CN | F25: 宁德时代 | G25: 300750 | H25: 买入 | I25: 1691 | L25: 156.29 | M25: =L25*I25 -> 264286.39
C26: 24 | D26: 45346 | E26: CN | F26: 宁德时代 | G26: 300750 | H26: 卖出 | I26: -1791 | L26: 160.5 | M26: =L26*I26 -> -287455.5
C27: 25 | D27: 45290 | E27: CN | F27: 上海沪工 | G27: 603131 | H27: 买入 | I27: 10000 | L27: 14.76 | M27: =L27*I27 -> 147600
C28: 26 | D28: 45304 | E28: CN | F28: 上海沪工 | G28: 603131 | H28: 买入 | I28: 5000 | L28: 15.32 | M28: =L28*I28 -> 76600
C29: 27 | D29: 45360 | E29: CN | F29: 上海沪工 | G29: 603131 | H29: 卖出 | I29: -15000 | L29: 19.07 | M29: =L29*I29 -> -286050
C30: 28 | D30: 45360 | E30: CN | F30: 罗欣药业 | G30: 002793 | H30: 买入 | I30: 30000 | L30: 4.52 | M30: =L30*I30 -> 135600
C31: 29 | D31: 45367 | E31: CN | F31: 罗欣药业 | G31: 002793 | H31: 卖出 | I31: -30000 | L31: 4.13 | M31: =L31*I31 -> -123900
D32: 45409 | E32: CN | F32: 上海沪工 | G32: 603131 | H32: 买入 | I32: 5000 | L32: 13.18 | M32: =L32*I32 -> 65900
D33: 45437 | E33: CN | F33: 上海沪工 | G33: 603131 | H33: 卖出 | I33: -5000 | L33: 14.8 | M33: =L33*I33 -> -74000
D34: 45388 | E34: CN | F34: 明阳智能 | G34: 601615 | H34: 买入 | I34: 5000 | L34: 9.58 | M34: =L34*I34 -> 47900
D35: 45444 | E35: CN | F35: 明阳智能 | G35: 601615 | H35: 卖出 | I35: -5000 | L35: 10.17 | M35: =L35*I35 -> -50850
D36: 45444 | E36: CN | F36: 罗欣药业 | G36: 002793 | H36: 卖出 | I36: -10000 | L36: 4.8 | M36: =L36*I36 -> -48000
D37: 45388 | E37: CN | F37: 罗欣药业 | G37: 002793 | H37: 买入 | I37: 10000 | L37: 4.54 | M37: =L37*I37 -> 45400
D38: 45444 | E38: US | F38: 富时中国50三倍做空ETF | G38: YANG | H38: 买入 | I38: 300 | L38: 64.428 | M38: =L38*I38 -> 19328.4
D39: 45465 | E39: US | F39: 富时中国50三倍做空ETF | G39: YANG | H39: 卖出 | I39: -300 | L39: 65.364 | M39: =L39*I39 -> -19609.2
D40: 45367 | E40: US | F40: 苹果 | G40: AAPL | H40: 买入 | I40: 200 | L40: 1346.436 | M40: =L40*I40 -> 269287.2
D41: 45367 | E41: US | F41: 谷歌-A | G41: GOOGL | H41: 买入 | I41: 200 | L41: 1101.204 | M41: =L41*I41 -> 220240.8
D42: 45493 | E42: US | F42: 苹果 | G42: AAPL | H42: 卖出 | I42: -200 | L42: 1749.618 | M42: =L42*I42 -> -349923.6
D43: 45493 | E43: US | F43: 谷歌-A | G43: GOOGL | H43: 卖出 | I43: -200 | L43: 1385.748 | M43: =L43*I43 -> -277149.6
C44: 30 | D44: 45150 | E44: CN | F44: 北方华创 | G44: 002371 | H44: 买入 | I44: 100 | L44: 278.6 | M44: =L44*I44 -> 27860
C45: 31 | D45: 45234 | E45: CN | F45: 北方华创 | G45: 002371 | H45: 买入 | I45: 400 | L45: 257.04 | M45: =L45*I45 -> 102816
D46: 45374 | E46: CN | F46: 北方华创 | G46: 002371 | H46: 卖出 | I46: -250 | L46: 312.51 | M46: =L46*I46 -> -78127.5
D47: 45388 | E47: CN | F47: 北方华创 | G47: 002371 | H47: 卖出 | I47: -250 | L47: 297.68 | M47: =L47*I47 -> -74420
D48: 45409 | E48: CN | F48: 证券ETF | G48: 512880 | H48: 买入 | I48: 300000 | L48: 0.878 | M48: =L48*I48 -> 263400
D49: 45430 | E49: CN | F49: 证券ETF | G49: 512880 | H49: 卖出 | I49: -300000 | L49: 0.871 | M49: =L49*I49 -> -261300
D50: 45493 | E50: US | F50: 拼多多 | G50: PDD | H50: 买入 | I50: 200 | L50: 1037.712 | M50: =L50*I50 -> 207542.4
D51: 45521 | E51: US | F51: 京东 | G51: JD | H51: 买入 | I51: 1000 | L51: 228.462 | M51: =L51*I51 -> 228462
D52: 45563 | E52: CN | F52: 润和软件 | G52: 300339 | H52: 买入 | I52: 1000 | L52: 31.14 | M52: =L52*I52 -> 31140
D53: 45577 | E53: US | F53: 拼多多 | G53: PDD | H53: 卖出 | I53: -200 | L53: 1129.128 | M53: =L53*I53 -> -225825.6
D54: 45577 | E54: US | F54: 京东 | G54: JD | H54: 卖出 | I54: -1000 | L54: 341.874 | M54: =L54*I54 -> -341874
D55: 45577 | E55: CN | F55: 润和软件 | G55: 300339 | H55: 卖出 | I55: -1000 | L55: 50.38 | M55: =L55*I55 -> -50380
D56: 45605 | E56: CN | F56: TCL科技 | G56: 000100 | H56: 买入 | I56: 40000 | L56: 5.24 | M56: =L56*I56 -> 209600
D57: 45675 | E57: CN | F57: TCL科技 | G57: 000100 | H57: 卖出 | I57: -40000 | L57: 4.92 | M57: =L57*I57 -> -196800
D58: 45584 | E58: CN | F58: 科创芯片ETF | G58: 588200 | H58: 买入 | I58: 40000 | L58: 1.434 | M58: =L58*I58 -> 57360
D59: 45591 | E59: CN | F59: 科创芯片ETF | G59: 588200 | H59: 卖出 | I59: -40000 | L59: 1.394 | M59: =L59*I59 -> -55760
D60: 45577 | E60: US | F60: 特斯拉 | G60: TSLA | H60: 买入 | I60: 100 | L60: 1698.84 | M60: =L60*I60 -> 169884
D61: 45598 | E61: US | F61: 特斯拉 | G61: TSLA | H61: 卖出 | I61: -100 | L61: 1942.044 | M61: =L61*I61 -> -194204.4
... D69: 45563 | E69: CN | F69: 智飞生物 | G69: 300122 | H69: 买入 | I69: 5000 | L69: 27.82 | M69: =L69*I69 -> 139100
D70: 45430 | E70: CN | F70: 中国平安 | G70: 601318 | H70: 买入 | I70: 10000 | L70: 45.2 | M70: =L70*I70 -> 452000
D71: 45444 | E71: CN | F71: 中国平安 | G71: 601318 | H71: 卖出 | I71: -5000 | L71: 43.07 | M71: =L71*I71 -> -215350
D72: 45563 | E72: CN | F72: 中国平安 | G72: 601318 | H72: 买入 | I72: 3000 | L72: 51.9 | M72: =L72*I72 -> 155700
D73: 45591 | E73: CN | F73: 中国平安 | G73: 601318 | H73: 卖出 | I73: -4000 | L73: 57.7 | M73: =L73*I73 -> -230800
D74: =全班!$R$1 -> 46011 | E74: CN | F74: 中国平安 | G74: 601318 | H74: 卖出 | I74: -2000 | L74: 51.2 | M74: =L74*I74 -> -102400
D75: 45724 | E75: CN | F75: 中国平安 | G75: 601318 | H75: 卖出 | I75: -2000 | L75: 51.5 | M75: =L75*I75 -> -103000
D76: 45738 | E76: US | F76: 默沙东 | G76: MRK | H76: 卖出 | I76: -300 | L76: 726.258 | M76: =L76*I76 -> -217877.4
D77: 45738 | E77: CN | F77: 海大集团 | G77: 002311 | H77: 卖出 | I77: -2000 | L77: 48.89 | M77: =L77*I77 -> -97780
D78: 45738 | E78: HK | F78: 康龙化成 | G78: 03759 | H78: 卖出 | I78: -5000 | L78: 16.4 | M78: =L78*I78 -> -82000
D79: 45794 | E79: CN | F79: 洛阳钼业 | G79: 603993 | H79: 卖出 | I79: -20000 | L79: 7.32 | M79: =L79*I79 -> -146400
D80: 45794 | E80: US | F80: 阿里巴巴 | G80: BABA | H80: 卖出 | I80: -100 | L80: 962.988 | M80: =L80*I80 -> -96298.8
D81: 45801 | E81: US | F81: 博通 | G81: AVGO | H81: 卖出 | I81: -100 | L81: 1784.016 | M81: =L81*I81 -> -178401.6
D82: 45577 | E82: US | F82: 默沙东 | G82: MRK | H82: 买入 | I82: 200 | L82: 855.894 | M82: =L82*I82 -> 171178.8
D83: 45591 | E83: US | F83: 默沙东 | G83: MRK | H83: 卖出 | I83: -200 | L83: 811.044 | M83: =L83*I83 -> -162208.8
D84: 45591 | E84: HK | F84: 康龙化成 | G84: 03759 | H84: 买入 | I84: 5000 | L84: 15.94 | M84: =L84*I84 -> 79700
D85: 45598 | E85: CN | F85: 洛阳钼业 | G85: 603993 | H85: 买入 | I85: 20000 | L85: 7.93 | M85: =L85*I85 -> 158600
D86: 45710 | E86: HK | F86: 康龙化成 | G86: 03759 | H86: 卖出 | I86: -2500 | L86: 19.22 | M86: =L86*I86 -> -48050
D87: 45605 | E87: CN | F87: 海大集团 | G87: 002311 | H87: 买入 | I87: 2000 | L87: 49.3 | M87: =L87*I87 -> 98600
... D112: 45969 | E112: HK | F112: 康方生物 | G112: 09926 | H112: 买入 | I112: 500 | L112: 112.2 | M112: =L112*I112 -> 56100
M113: =L113*I113 -> 0
D114: 累计净买入 | M114: =SUM(M3:M113) -> -603139.09
D115: 时间 | E115: 市场 | F115: 企业 | G115: 股票代码 | H115: 状态 | I115: 数量 | J115: 平均买价 | K115: 成本 | L115: 当前价格 | M115: 市值
D116: =全班!$R$1 -> 46011 | E116: US | F116: 英伟达 | G116: NVDA | H116: 持有 | I116: =SUMIFS($I$97:$I$114,$G$97:$G$114,G116) -> 50 | J116: =K116/I116 -> 161.382 | K116: =SUMIFS($M$97:$M$114,$G$97:$G$114,G116) -> 8069.1 | L116: =VLOOKUP(G116,股价!C:D,2,FALSE) -> 1411.722 | M116: =IFERROR(I116*L116,0) -> 70586.1
D117: =全班!$R$1 -> 46011 | E117: US | F117: 谷歌 | G117: GOOGL | H117: 持有 | I117: =SUMIFS($I$97:$I$114,$G$97:$G$114,G117) -> 100 | J117: =K117/I117 -> 1356.108 | K117: =SUMIFS($M$97:$M$114,$G$97:$G$114,G117) -> 135610.8 | L117: =VLOOKUP(G117,股价!C:D,2,FALSE) -> 2395.848 | M117: =IFERROR(I117*L117,0) -> 239584.8
D118: =全班!$R$1 -> 46011 | E118: US | F118: Nauticus Robotics | G118: KITT | H118: 持有 | I118: =SUMIFS($I$97:$I$114,$G$97:$G$114,G118) -> 10000 | J118: =K118/I118 -> 11.076 | K118: =SUMIFS($M$97:$M$114,$G$97:$G$114,G118) -> 110760 | L118: =VLOOKUP(G118,股价!C:D,2,FALSE) -> 6.7782 | M118: =IFERROR(I118*L118,0) -> 67782
D119: =全班!$R$1 -> 46011 | E119: CN | F119: 特宝生物 | G119: 688278 | H119: 持有 | I119: =SUMIFS($I$97:$I$114,$G$97:$G$114,G119) -> 1000 | J119: =K119/I119 -> 73.08 | K119: =SUMIFS($M$97:$M$114,$G$97:$G$114,G119) -> 73080 | L119: =VLOOKUP(G119,股价!C:D,2,FALSE) -> 85 | M119: =IFERROR(I119*L119,0) -> 85000
D120: =全班!$R$1 -> 46011 | E120: HK | F120: 康方生物 | G120: 09926 | H120: 持有 | I120: =SUMIFS($I$97:$I$114,$G$97:$G$114,G120) -> 500 | J120: =K120/I120 -> 112.2 | K120: =SUMIFS($M$97:$M$114,$G$97:$G$114,G120) -> 56100 | L120: =VLOOKUP(G120,股价!C:D,2,FALSE) -> 117.2 | M120: =IFERROR(I120*L120,0) -> 58600
D122: 市值结余 | M122: =SUM(M116:M121) -> 521552.9
D123: 累计分红 | M123: =L137 -> 15183.6
D124: 现金结余 | M124: =M129-M114+M123 -> 1618322.7
D125: 结余总额 | M125: =M122+M124 -> 2139875.6
D126: 累计盈利 | M126: =M125-M129 -> 1139875.6
D127: 盈利率 | M127: =M126/M129 -> 1.1398756
D129: 本金 | M129: =本金与余额!D20 -> 1000000
D130: 登记日 | E130: 市场 | F130: 企业 | G130: 股票代码 | H130: 状态 | I130: 数量 | J130: 分红方案 | K130: 实施 | L130: 红利金额 | M130: 除权日
D131: 45453 | E131: US | F131: 谷歌-A | G131: GOOGL | H131: 分红 | I131: 200 | J131: 1派1.56 | K131: 1派1.56 | L131: =I131*1.56 -> 312 | M131: 45453
D132: 45443 | E132: CN | F132: 中国平安 | G132: 601318 | H132: 分紅 | I132: 5000 | J132: 10派15 | K132: 10派15 | L132: =I132*1.5 -> 7500 | M132: 45499
D133: 45511 | E133: CN | F133: 智飞生物 | G133: 300122 | H133: 分红 | I133: 9000 | J133: 10派8 | K133: 10派8 | L133: =9000/10*8 -> 7200 | M133: 45512
D134: 45819 | E134: US | F134: 英伟达 | G134: NVDA | H134: 分红 | I134: 100 | J134: 1派0.01USD | K134: 1派0.01USD | L134: =I134*0.01*7.8 -> 7.8 | M134: 45819
D135: 45817 | E135: US | F135: 谷歌-A | G135: GOOGL | H135: 分红 | I135: 100 | J135: 1派0.21USD | K135: 1派0.21USD | L135: =I135*0.21*7.8 -> 163.8 | M135: 45817
...

Sheet 柯滔
A1: back | D1: 操盘：柯滔
D2: 时间 | E2: 市场 | F2: 企业 | G2: 股票代码 | H2: 操作 | I2: 数量 | J2: 平均买价 | K2: 成本 | L2: 买卖价格 | M2: 市值
D3: 45479 | E3: US | F3: 苹果 | G3: AAPL | H3: 买入 | I3: 50 | L3: 1765.452 | M3: =L3*I3 -> 88272.6
D4: 45521 | E4: US | F4: 苹果 | G4: AAPL | H4: 卖出 | I4: -50 | L4: 1763.19 | M4: =L4*I4 -> -88159.5
C5: 1 | D5: 45409 | E5: US | F5: 特斯拉 | G5: TSLA | H5: 买入 | I5: 200 | L5: 1312.662 | M5: =L5*I5 -> 262532.4
C6: 4 | D6: 45465 | E6: US | F6: 特斯拉 | G6: TSLA | H6: 买入 | I6: 50 | L6: 1427.478 | M6: =L6*I6 -> 71373.9
D7: 45493 | E7: US | F7: 特斯拉 | G7: TSLA | H7: 卖出 | I7: -100 | L7: 1865.76 | M7: =L7*I7 -> -186576
D8: 45577 | E8: US | F8: 特斯拉 | G8: TSLA | H8: 卖出 | I8: -140 | L8: 1698.84 | M8: =L8*I8 -> -237837.6
D9: 45591 | E9: US | F9: 特斯拉 | G9: TSLA | H9: 卖出 | I9: -10 | L9: 2099.682 | M9: =L9*I9 -> -20996.82
C10: 7 | D10: 45472 | E10: US | F10: 美国超微公司 | G10: AMD | H10: 买入 | I10: 50 | L10: 1265.238 | M10: =L10*I10 -> 63261.9
D11: 45591 | E11: US | F11: 美国超微公司 | G11: AMD | H11: 卖出 | I11: -50 | L11: 1218.594 | M11: =L11*I11 -> -60929.7
C12: 8 | D12: 45472 | E12: US | F12: 博通 | G12: AVGO | H12: 买入 | I12: 10 | L12: 12523.134 | M12: =L12*I12 -> 125231.34
D13: 45486 | E13: US | F13: 博通 | G13: AVGO | H13: 买入 | I13: 20 | L13: 13265.226 | M13: =L13*I13 -> 265304.52
D14: 45488 | E14: US | F14: 博通 | G14: AVGO | H14: 拆股 | I14: 270 | M14: =L14*I14 -> 0
D15: 45493 | E15: US | F15: 博通 | G15: AVGO | H15: 卖出 | I15: -200 | L15: 1227.33 | M15: =L15*I15 -> -245466
D16: 45577 | E16: US | F16: 博通 | G16: AVGO | H16: 卖出 | I16: -80 | L16: 1415.544 | M16: =L16*I16 -> -113243.52
D17: 45647 | E17: US | F17: 博通 | G17: AVGO | H17: 卖出 | I17: -20 | L17: 1722.162 | M17: =L17*I17 -> -34443.24
D18: 45500 | E18: US | F18: 阿斯麦 | G18: ASML | H18: 买入 | I18: 10 | L18: 6929.442 | M18: =L18*I18 -> 69294.42
D19: 45591 | E19: US | F19: 阿斯麦 | G19: ASML | H19: 买入 | I19: 14 | L19: 5551.26 | M19: =L19*I19 -> 77717.64
D20: 45619 | E20: US | F20: 阿斯麦 | G20: ASML | H20: 卖出 | I20: -24 | L20: 5248.464 | M20: =L20*I20 -> -125963.14
C21: 3 | D21: 45444 | E21: US | F21: 加拿大鹅 | G21: GOOS | H21: 买入 | I21: 100 | L21: 112.788 | M21: =L21*I21 -> 11278.8
D22: 45486 | E22: US | F22: 加拿大鹅 | G22: GOOS | H22: 买入 | I22: 100 | L22: 102.258 | M22: =L22*I22 -> 10225.8
D23: 45500 | E23: US | F23: 加拿大鹅 | G23: GOOS | H23: 卖出 | I23: -200 | L23: 88.92 | M23: =L23*I23 -> -17784
C24: 2 | D24: 45409 | E24: US | F24: 脸书 | G24: Meta | H24: 买入 | I24: 50 | L24: 3457.662 | M24: =L24*I24 -> 172883.1
D25: 45486 | E25: US | F25: 脸书 | G25: Meta | H25: 卖出 | I25: -50 | L25: 3891.186 | M25: =L25*I25 -> -194559.3
D26: 45710 | E26: US | F26: 谷歌-A | G26: GOOGL | H26: 买入 | I26: 100 | L26: 1401.348 | M26: =L26*I26 -> 140134.8
D27: 45766 | E27: US | F27: 谷歌-A | G27: GOOGL | H27: 卖出 | I27: -20 | L27: 1179.048 | M27: =L27*I27 -> -23580.96
D28: 45815 | E28: US | F28: 谷歌-A | G28: GOOGL | H28: 卖出 | I28: -80 | L28: 1354.704 | M28: =L28*I28 -> -108376.32
C29: 5 | D29: 45465 | E29: US | F29: 拼多多 | G29: PDD | H29: 买入 | I29: 10 | L29: 1122.108 | M29: =L29*I29 -> 11221.08
D30: 45647 | E30: US | F30: 拼多多 | G30: PDD | H30: 买入 | I30: 112 | L30: 776.178 | M30: =L30*I30 -> 86931.936
D31: 45703 | E31: US | F31: 拼多多 | G31: PDD | H31: 卖出 | I31: -22 | L31: 968.448 | M31: =L31*I31 -> -21305.856
D32: 45717 | E32: US | F32: 拼多多 | G32: PDD | H32: 卖出 | I32: -50 | L32: 886.782 | M32: =L32*I32 -> -44339.1
D33: 45731 | E33: US | F33: 拼多多 | G33: PDD | H33: 卖出 | I33: -50 | L33: 955.812 | M33: =L33*I33 -> -47790.6
D34: 45577 | E34: US | F34: 诺和诺德 | G34: NVO | H34: 买入 | I34: 50 | L34: 936.312 | M34: =L34*I34 -> 46815.6
D35: 45710 | E35: US | F35: 诺和诺德 | G35: NVO | H35: 买入 | I35: 50 | L35: 687.024 | M35: =L35*I35 -> 34351.2
D36: 45745 | E36: US | F36: 诺和诺德 | G36: NVO | H36: 卖出 | I36: -100 | L36: 540.54 | M36: =L36*I36 -> -54054
D37: 45500 | E37: US | F37: 台积电 | G37: TSM | H37: 买入 | I37: 50 | L37: 1263.132 | M37: =L37*I37 -> 63156.6
D38: 45577 | E38: US | F38: 台积电 | G38: TSM | H38: 卖出 | I38: -40 | L38: 1488.318 | M38: =L38*I38 -> -59532.72
D39: 45703 | E39: US | F39: 台积电 | G39: TSM | H39: 卖出 | I39: -3 | L39: 1590.42 | M39: =L39*I39 -> -4771.26
D40: 45745 | E40: US | F40: 台积电 | G40: TSM | H40: 卖出 | I40: -7 | L40: 1288.95 | M40: =L40*I40 -> -9022.65
C41: 6 | D41: 45465 | E41: US | F41: 阿里巴巴 | G41: BABA | H41: 买入 | I41: 20 | L41: 574.626 | M41: =L41*I41 -> 11492.52
D42: 45500 | E42: US | F42: 阿里巴巴 | G42: BABA | H42: 卖出 | I42: -20 | L42: 596.934 | M42: =L42*I42 -> -11938.68
C43: 9 | D43: 45472 | E43: US | F43: 理想汽车 | G43: LI | H43: 买入 | I43: 200 | L43: 139.464 | M43: =L43*I43 -> 27892.8
D44: 45479 | E44: US | F44: 理想汽车 | G44: LI | H44: 卖出 | I44: -200 | L44: 159.588 | M44: =L44*I44 -> -31917.6
D45: 45500 | E45: US | F45: 超微电脑 | G45: SMCI | H45: 买入 | I45: 50 | L45: 5555.082 | M45: =L45*I45 -> 277754.1
D46: 45514 | E46: US | F46: 超微电脑 | G46: SMCI | H46: 买入 | I46: 15 | L46: 3968.328 | M46: =L46*I46 -> 59524.92
D47: 45521 | E47: US | F47: 超微电脑 | G47: SMCI | H47: 买入 | I47: 15 | L47: 4904.64 | M47: =L47*I47 -> 73569.6
D48: 45566 | E48: US | F48: 超微电脑 | G48: SMCI | H48: 拆股 | I48: =800-80 -> 720 | M48: =L48*I48 -> 0
D49: 45577 | E49: US | F49: 超微电脑 | G49: SMCI | H49: 买入 | I49: 975 | L49: 372.84 | M49: =L49*I49 -> 363519
D50: 45619 | E50: US | F50: 超微电脑 | G50: SMCI | H50: 买入 | I50: 505 | L50: 258.57 | M50: =L50*I50 -> 130577.85
D51: 45703 | E51: US | F51: 超微电脑 | G51: SMCI | H51: 卖出 | I51: -80 | L51: 373.698 | M51: =L51*I51 -> -29895.84
D52: 45710 | E52: US | F52: 超微电脑 | G52: SMCI | H52: 卖出 | I52: -500 | L52: 437.346 | M52: =L52*I52 -> -218673
D53: 45815 | E53: US | F53: 超微电脑 | G53: SMCI | H53: 买入 | I53: 300 | L53: 324.09 | M53: =L53*I53 -> 97227
D54: 45822 | E54: US | F54: 超微电脑 | G54: SMCI | H54: 卖出 | I54: -500 | L54: 324.168 | M54: =L54*I54 -> -162084
D55: 45836 | E55: US | F55: 超微电脑 | G55: SMCI | H55: 卖出 | I55: -1000 | L55: 371.124 | M55: =L55*I55 -> -371124
D56: 45871 | E56: US | F56: 超微电脑 | G56: SMCI | H56: 卖出 | I56: -200 | L56: 441.792 | M56: =L56*I56 -> -88358.4
D57: 45878 | E57: US | F57: 超微电脑 | G57: SMCI | H57: 卖出 | I57: -300 | L57: 347.88 | M57: =L57*I57 -> -104364
D58: 45836 | E58: US | F58: Palantir Technologies | G58: PLTR | H58: 买入 | I58: 20 | L58: 1019.772 | M58: =L58*I58 -> 20395.44
D59: 45892 | E59: US | F59: Palantir Technologies | G59: PLTR | H59: 卖出 | I59: -20 | L59: 1238.172 | M59: =L59*I59 -> -24763.44
D60: 45885 | E60: US | F60: 多邻国 | G60: DUOL | H60: 买入 | I60: 20 | L60: 2550.054 | M60: =L60*I60 -> 51001.08
... D143: 46011 | E143: US | F143: applovin corporation-期权 | G143: APP-P600-2026-4-17 | H143: 买入 | I143: 300 | L143: 351 | M143: =L143*I143 -> 105300
M144: =L144*I144 -> 0
M145: =L145*I145 -> 0
M146: =L146*I146 -> 0
M147: =L147*I147 -> 0
D148: 累计净买入 | M148: =SUM(M3:M147) -> 803688.21
D149: 时间 | E149: 市场 | F149: 企业 | G149: 股票代码 | H149: 状态 | I149: 数量 | J149: 平均买价 | K149: 成本 | L149: 当前价格 | M149: 市值
D150: =全班!$R$1 -> 46011 | E150: US | F150: 特斯拉 | G150: TSLA | H150: 持有 | I150: =SUMIFS($I$107:$I$148,$G$107:$G$148,G150) -> 100 | J150: =K150/I150 -> 2227.5404 | K150: =SUMIFS($M$107:$M$148,$G$107:$G$148,G150) -> 222754.04 | L150: =VLOOKUP(G150,股价!C:D,2,FALSE) -> 3753.36 | M150: =IFERROR(I150*L150,0) -> 375336
D151: =全班!$R$1 -> 46011 | E151: US | F151: 阿斯麦 | G151: ASML | H151: 持有 | I151: =SUMIFS($I$107:$I$148,$G$107:$G$148,G151) -> 2 | J151: =K151/I151 -> -284.856 | K151: =SUMIFS($M$107:$M$148,$G$107:$G$148,G151) -> -569.712 | L151: =VLOOKUP(G151,股价!C:D,2,FALSE) -> 8236.956 | M151: =IFERROR(I151*L151,0) -> 16473.912
D152: =全班!$R$1 -> 46011 | E152: US | F152: Rocket Lab Corporation | G152: RKLB | H152: 持有 | I152: =SUMIFS($I$107:$I$148,$G$107:$G$148,G152) -> 200 | J152: =K152/I152 -> 115.635 | K152: =SUMIFS($M$107:$M$148,$G$107:$G$148,G152) -> 23127 | L152: =VLOOKUP(G152,股价!C:D,2,FALSE) -> 550.056 | M152: =IFERROR(I152*L152,0) -> 110011.2
D153: =全班!$R$1 -> 46011 | E153: US | F153: 超微电脑-期权 | G153: SMCI-C50-2026-3-20 | H153: 持有 | I153: =SUMIFS($I$107:$I$148,$G$107:$G$148,G153) -> 1000 | J153: =K153/I153 -> 55.77 | K153: =SUMIFS($M$107:$M$148,$G$107:$G$148,G153) -> 55770 | L153: =VLOOKUP(G153,股价!C:D,2,FALSE) -> 5.928 | M153: =IFERROR(I153*L153,0) -> 5928
D154: =全班!$R$1 -> 46011 | E154: US | F154: Figma-期权 | G154: FIG-C70-2026-6-18 | H154: 持有 | I154: =SUMIFS($I$107:$I$148,$G$107:$G$148,G154) -> 1000 | J154: =K154/I154 -> 68.64 | K154: =SUMIFS($M$107:$M$148,$G$107:$G$148,G154) -> 68640 | L154: =VLOOKUP(G154,股价!C:D,2,FALSE) -> 17.55 | M154: =IFERROR(I154*L154,0) -> 17550
D155: =全班!$R$1 -> 46011 | E155: US | F155: 阿斯麦-期权 | G155: ASML-P870-2026-3-20 | H155: 持有 | I155: =SUMIFS($I$107:$I$148,$G$107:$G$148,G155) -> 1000 | J155: =K155/I155 -> 257.4 | K155: =SUMIFS($M$107:$M$148,$G$107:$G$148,G155) -> 257400 | L155: =VLOOKUP(G155,股价!C:D,2,FALSE) -> 171.6 | M155: =IFERROR(I155*L155,0) -> 171600
D156: =全班!$R$1 -> 46011 | E156: US | F156: 超微电脑 | G156: SMCI | H156: 持有 | I156: =SUMIFS($I$75:$I$148,$G$75:$G$148,G156) -> 200 | J156: =K156/I156 -> 310.128 | K156: =SUMIFS($M$75:$M$148,$G$75:$G$148,G156) -> 62025.6 | L156: =VLOOKUP(G156,股价!C:D,2,FALSE) -> 242.658 | M156: =IFERROR(I156*L156,0) -> 48531.6
D157: =全班!$R$1 -> 46011 | E157: US | F157: 英特尔-期权 | G157: INTC-P30-2026-3-20 | H157: 持有 | I157: =SUMIFS($I$75:$I$148,$G$75:$G$148,G157) -> 1000 | J157: =K157/I157 -> 15.21 | K157: =SUMIFS($M$75:$M$148,$G$75:$G$148,G157) -> 15210 | L157: =VLOOKUP(G157,股价!C:D,2,FALSE) -> 9.048 | M157: =IFERROR(I157*L157,0) -> 9048
D158: =全班!$R$1 -> 46011 | E158: US | F158: 礼来-期权 | G158: LLY-P1000-2026-3-20 | H158: 持有 | I158: =SUMIFS($I$75:$I$148,$G$75:$G$148,G158) -> 300 | J158: =K158/I158 -> 420.42 | K158: =SUMIFS($M$75:$M$148,$G$75:$G$148,G158) -> 126126 | L158: =VLOOKUP(G158,股价!C:D,2,FALSE) -> 344.37 | M158: =IFERROR(I158*L158,0) -> 103311
D159: =全班!$R$1 -> 46011 | E159: US | F159: Tower半导体-期权 | G159: TSEM-P100-2026-4-17 | H159: 持有 | I159: =SUMIFS($I$75:$I$148,$G$75:$G$148,G159) -> 100 | J159: =K159/I159 -> 76.44 | K159: =SUMIFS($M$75:$M$148,$G$75:$G$148,G159) -> 7644 | L159: =VLOOKUP(G159,股价!C:D,2,FALSE) -> 64.74 | M159: =IFERROR(I159*L159,0) -> 6474
D160: =全班!$R$1 -> 46011 | E160: US | F160: 英特尔-期权 | G160: INTC-P40-2026-4-17 | H160: 持有 | I160: =SUMIFS($I$75:$I$148,$G$75:$G$148,G160) -> 1000 | J160: =K160/I160 -> 36.27 | K160: =SUMIFS($M$75:$M$148,$G$75:$G$148,G160) -> 36270 | L160: =VLOOKUP(G160,股价!C:D,2,FALSE) -> 47.58 | M160: =IFERROR(I160*L160,0) -> 47580
D161: =全班!$R$1 -> 46011 | E161: US | F161: 阿斯麦-期权 | G161: ASML-P900-2026-4-17 | H161: 持有 | I161: =SUMIFS($I$75:$I$148,$G$75:$G$148,G161) -> 500 | J161: =K161/I161 -> 247.26 | K161: =SUMIFS($M$75:$M$148,$G$75:$G$148,G161) -> 123630 | L161: =VLOOKUP(G161,股价!C:D,2,FALSE) -> 301.08 | M161: =IFERROR(I161*L161,0) -> 150540
D162: =全班!$R$1 -> 46011 | E162: US | F162: 回声星通信-期权 | G162: SATS-P100-2026-4-17 | H162: 持有 | I162: =SUMIFS($I$107:$I$148,$G$107:$G$148,G162) -> 500 | J162: =K162/I162 -> 89.7 | K162: =SUMIFS($M$107:$M$148,$G$107:$G$148,G162) -> 44850 | L162: =VLOOKUP(G162,股价!C:D,2,FALSE) -> 91.26 | M162: =IFERROR(I162*L162,0) -> 45630
D163: =全班!$R$1 -> 46011 | E163: US | F163: applovin corporation-期权 | G163: APP-P600-2026-4-17 | H163: 持有 | I163: =SUMIFS($I$75:$I$148,$G$75:$G$148,G163) -> 300 | J163: =K163/I163 -> 351 | K163: =SUMIFS($M$75:$M$148,$G$75:$G$148,G163) -> 105300 | L163: =VLOOKUP(G163,股价!C:D,2,FALSE) -> 395.46 | M163: =IFERROR(I163*L163,0) -> 118638
D166: 市值结余 | M166: =SUM(M150:M165) -> 1226651.7
D167: 累计分红 | M167: =L180 -> 269.334
D168: 现金结余 | M168: =M173-M148+M167 -> 196581.12
D169: 结余总额 | M169: =M166+M168 -> 1423232.8
D170: 累计盈利 | M170: =M169-M173 -> 423232.84
D171: 盈利率 | M171: =M170/M173 -> 0.42323284
D173: 本金 | M173: =本金与余额!D21 -> 1000000
D174: 登记日 | E174: 市场 | F174: 企业 | G174: 股票代码 | H174: 状态 | I174: 数量 | J174: 分红方案 | K174: 实施 | L174: 红利金额 | M174: 除权日
D175: 45488 | E175: US | F175: 博通 | G175: AVGO | H175: 拆股 | I175: 30 | J175: 1拆10 | K175: 300
D176: 45566 | E176: US | F176: 超微电脑 | G176: SMCI | H176: 拆股 | I176: 80 | J176: 1拆10 | K176: =I176*10 -> 800 | M176: 45566
D177: 45594 | E177: US | F177: 阿斯麦 | G177: ASML | H177: 分红 | I177: 24 | J177: 1派1.395USD | K177: 1派1.395USD | L177: =I177*1.395*7.8 -> 261.144 | M177: 45594
D178: 45819 | E178: US | F178: 英伟达 | G178: NVDA | H178: 分红 | I178: 105 | J178: 1派0.01USD | K178: 1派0.01USD | L178: =I178*0.01*7.8 -> 8.19 | M178: 45819
D180: 累计分红 | L180: =SUM(L175:L179) -> 269.334

Sheet A股行业分类
B3: 序号 | C3: 细分行业 | D3: 企业名称 | E3: 企业数量占比 | H3: 细分行业 | I3: 股票代码 | J3: 企业名称 | K3: 2023-10-13 收市价 | L3: 市盈(TTM) | M3: 市盈(动) | N3: 市盈(静) | O3: 总市值
B4: 1 | C4: IT设备 | D4: 63 | E4: =D4/$D$114 -> 0.011889036 | H4: IT设备 | I4: 000066 | J4: 中国长城 | K4: 12.23 | N4: 327.99 | O4: 394.52
B5: 2 | C5: 白酒 | D5: 20 | E5: =D5/$D$114 -> 0.003774297 | H5: IT设备 | I5: 000977 | J5: 浪潮信息 | K5: 35.24 | L5: 35.74 | M5: 79.74 | N5: 24.94 | O5: 518.78
B6: 3 | C6: 百货 | D6: 36 | E6: =D6/$D$114 -> 0.0067937347 | H6: IT设备 | I6: 000997 | J6: 新 大 陆 | K6: 18.78 | M6: 17.17 | O6: 193.82
B7: 4 | C7: 半导体 | D7: 168 | E7: =D7/$D$114 -> 0.031704095 | H7: IT设备 | I7: 001229 | J7: 魅视科技 | K7: 30.89 | L7: 37.62 | M7: 46.02 | N7: 36.43 | O7: 30.89
B8: 5 | C8: 保险 | D8: 6 | E8: =D8/$D$114 -> 0.0011322891 | H8: IT设备 | I8: 001339 | J8: 智微智能 | K8: 25.51 | L8: 74.03 | M8: 76.54 | N8: 53.37 | O8: 63.56
B9: 6 | C9: 玻璃 | D9: 18 | E9: =D9/$D$114 -> 0.0033968673 | H9: IT设备 | I9: 002152 | J9: 广电运通 | K9: 12.19 | L9: 34.08 | M9: 31.96 | N9: 36.59 | O9: 302.72
B10: 7 | C10: 仓储物流 | D10: 48 | E10: =D10/$D$114 -> 0.0090583129 | H10: IT设备 | I10: 002180 | J10: 纳思达 | K10: 26.66 | L10: 32.89 | M10: 53.78 | N10: 20.27 | O10: 377.58
B11: 8 | C11: 超市连锁 | D11: 9 | E11: =D11/$D$114 -> 0.0016984337 | H11: IT设备 | I11: 002197 | J11: 证通电子 | K11: 10.42 | M11: 141.14 | O11: 64.02
B12: 9 | C12: 出版业 | D12: 28 | E12: =D12/$D$114 -> 0.0052840159 | H12: IT设备 | I12: 002236 | J12: 大华股份 | K12: 22.14 | L12: 26.23 | M12: 18.46 | N12: 31.38 | O12: 729.4
B13: 10 | C13: 船舶 | D13: 12 | E13: =D13/$D$114 -> 0.0022645782 | H13: IT设备 | I13: 002308 | J13: 威创股份 | K13: 5.45 | L13: 107.97 | M13: 85.09 | N13: 117.8 | O13: 49.39
B14: 11 | C14: 电气设备 | D14: 316 | E14: =D14/$D$114 -> 0.059633893 | H14: IT设备 | I14: 002351 | J14: 漫步者 | K14: 17.12 | L14: 48.34 | M14: 43.67 | N14: 61.74 | O14: 152.22
B15: 12 | C15: 电器连锁 | D15: 2 | E15: =D15/$D$114 -> 0.0003774297 | H15: IT设备 | I15: 002376 | J15: 新北洋 | K15: 7.67 | M15: 230.13 | O15: 49.74
B16: 13 | C16: 电器仪表 | D16: 103 | E16: =D16/$D$114 -> 0.01943763 | H16: IT设备 | I16: 002415 | J16: 海康威视 | K16: 34.41 | L16: 25.86 | M16: 30.07 | N16: 25.01 | O16: 3210.66
B17: 14 | C17: 电信运营 | D17: 6 | E17: =D17/$D$114 -> 0.0011322891 | H17: IT设备 | I17: 002528 | J17: 英飞拓 | K17: 9.28 | O17: 111.24
B18: 15 | C18: 多元金融 | D18: 29 | E18: =D18/$D$114 -> 0.0054727307 | H18: IT设备 | I18: 002577 | J18: 雷柏科技 | K18: 16.4 | L18: 160.45 | M18: 112.72 | N18: 124.57 | O18: 46.39
B19: 16 | C19: 房产服务 | D19: 12 | E19: =D19/$D$114 -> 0.0022645782 | H19: IT设备 | I19: 002835 | J19: 同为股份 | K19: 16.8 | L19: 30.05 | M19: 35.94 | N19: 33.69 | O19: 36.87
B20: 17 | C20: 纺织 | D20: 46 | E20: =D20/$D$114 -> 0.0086808832 | H20: IT设备 | I20: 002866 | J20: 传艺科技 | K20: 20.76 | L20: 85.47 | M20: 74.09 | N20: 52.26 | O20: 60.1
B21: 18 | C21: 纺织机械 | D21: 11 | E21: =D21/$D$114 -> 0.0020758634 | H21: IT设备 | I21: 002912 | J21: 中新赛克 | K21: 32.45 | L21: 96.71 | M21: 37.53 | O21: 55.41
B22: 19 | C22: 服饰 | D22: 68 | E22: =D22/$D$114 -> 0.01283261 | H22: IT设备 | I22: 002955 | J22: 鸿合科技 | K22: 27.31 | L22: 15.38 | M22: 22.43 | N22: 16.18 | O22: 64.09
B23: 20 | C23: 钢加工 | D23: 21 | E23: =D23/$D$114 -> 0.0039630119 | H23: IT设备 | I23: 002970 | J23: 锐明技术 | K23: 30.99 | M23: 44.39 | O23: 53.58
B24: 21 | C24: 港口 | D24: 18 | E24: =D24/$D$114 -> 0.0033968673 | H24: IT设备 | I24: 300042 | J24: 朗科科技 | K24: 29.23 | L24: 299.76 | N24: 94.28 | O24: 58.58
B25: 22 | C25: 工程机械 | D25: 32 | E25: =D25/$D$114 -> 0.0060388753 | H25: IT设备 | I25: 300045 | J25: 华力创通 | K25: 33.07 | O25: 219.15
B26: 23 | C26: 公共交通 | D26: 6 | E26: =D26/$D$114 -> 0.0011322891 | H26: IT设备 | I26: 300076 | J26: GQY视讯 | K26: 5.35 | O26: 22.68
B27: 24 | C27: 公路 | D27: 2 | E27: =D27/$D$114 -> 0.0003774297 | H27: IT设备 | I27: 300130 | J27: 新国都 | K27: 23.8 | L27: 70.28 | M27: 19.32 | N27: 287.21 | O27: 128.61
B28: 25 | C28: 供气供热 | D28: 44 | E28: =D28/$D$114 -> 0.0083034535 | H28: IT设备 | I28: 300155 | J28: 安居宝 | K28: 5.44 | M28: 178.89 | O28: 30.53
B29: 26 | C29: 广告包装 | D29: 53 | E29: =D29/$D$114 -> 0.010001887 | H29: IT设备 | I29: 300249 | J29: 依米康 | K29: 10.38 | O29: 45.72
B30: 27 | C30: 航空 | D30: 51 | E30: =D30/$D$114 -> 0.0096244574 | H30: IT设备 | I30: 300270 | J30: 中威电子 | K30: 7.62 | N30: 471.7 | O30: 23.07
B31: 28 | C31: 红黄酒 | D31: 9 | E31: =D31/$D$114 -> 0.0016984337 | H31: IT设备 | I31: 300333 | J31: 兆日科技 | K31: 7.12 | O31: 23.92
B32: 29 | C32: 互联网 | D32: 88 | E32: =D32/$D$114 -> 0.016606907 | H32: IT设备 | I32: 300368 | J32: 汇金股份 | K32: 7.94 | O32: 42.24
B33: 30 | C33: 化工机械 | D33: 10 | E33: =D33/$D$114 -> 0.0018871485 | H33: IT设备 | I33: 300449 | J33: 汉邦高科 | K33: 5.96 | O33: 17.78
B34: 31 | C34: 化工原料 | D34: 247 | E34: =D34/$D$114 -> 0.046612568 | H34: IT设备 | I34: 300455 | J34: 航天智装 | K34: 11.21 | L34: 92.02 | M34: 179.4 | N34: 93.23 | O34: 80.46
B35: 32 | C35: 化纤 | D35: 30 | E35: =D35/$D$114 -> 0.0056614456 | H35: IT设备 | I35: 300462 | J35: 华铭智能 | K35: 10.97 | L35: 23.9 | N35: 33.99 | O35: 20.65
B36: 33 | C36: 化学制药 | D36: 148 | E36: =D36/$D$114 -> 0.027929798 | H36: IT设备 | I36: 300546 | J36: 雄帝科技 | K36: 17.29 | L36: 44.47 | M36: 375.07 | N36: 87.53 | O36: 32.08
B37: 34 | C37: 环境保护 | D37: 135 | E37: =D37/$D$114 -> 0.025476505 | H37: IT设备 | I37: 300552 | J37: 万集科技 | K37: 21.75 | O37: 46.36
B38: 35 | C38: 黄金 | D38: 10 | E38: =D38/$D$114 -> 0.0018871485 | H38: IT设备 | I38: 300656 | J38: 民德电子 | K38: 26.26 | L38: 63.66 | M38: 165.69 | N38: 50.53 | O38: 45.33
B39: 36 | C39: 火力发电 | D39: 32 | E39: =D39/$D$114 -> 0.0060388753 | H39: IT设备 | I39: 300743 | J39: 天地数码 | K39: 14.15 | L39: 41.4 | M39: 36.73 | N39: 53.89 | O39: 19.74
B40: 37 | C40: 机场 | D40: 5 | E40: =D40/$D$114 -> 0.00094357426 | H40: IT设备 | I40: 300771 | J40: 智莱科技 | K40: 10.43 | L40: 79.5 | N40: 14.53 | O40: 25.03
B41: 38 | C41: 机床制造 | D41: 23 | E41: =D41/$D$114 -> 0.0043404416 | H41: IT设备 | I41: 300793 | J41: 佳禾智能 | K41: 18.99 | L41: 33.42 | M41: 34.67 | N41: 37.02 | O41: 64.26
B42: 39 | C42: 机械基件 | D42: 126 | E42: =D42/$D$114 -> 0.023778071 | H42: IT设备 | I42: 300857 | J42: 协创数据 | K42: 27.5 | L42: 38.79 | M42: 29.66 | N42: 51.22 | O42: 67.05
B43: 40 | C43: 家居用品 | D43: 65 | E43: =D43/$D$114 -> 0.012266465 | H43: IT设备 | I43: 300884 | J43: 狄耐克 | K43: 12.06 | L43: 35.37 | M43: 29.96 | N43: 37.89 | O43: 30.39
B44: 41 | C44: 家用电器 | D44: 86 | E44: =D44/$D$114 -> 0.016229477 | H44: IT设备 | I44: 300941 | J44: 创识科技 | K44: 24.23 | L44: 51.57 | M44: 97.73 | N44: 44.89 | O44: 49.61
B45: 42 | C45: 建筑工程 | D45: 125 | E45: =D45/$D$114 -> 0.023589356 | H45: IT设备 | I45: 301042 | J45: 安联锐视 | K45: 40.2 | L45: 28.8 | M45: 33.85 | N45: 27.17 | O45: 27.88
B46: 43 | C46: 焦炭加工 | D46: 8 | E46: =D46/$D$114 -> 0.0015097188 | H46: IT设备 | I46: 301189 | J46: 奥尼电子 | K46: 29.2 | L46: 122.22 | N46: 52.8 | O46: 33.55
B47: 44 | C47: 酒店餐饮 | D47: 8 | E47: =D47/$D$114 -> 0.0015097188 | H47: IT设备 | I47: 301318 | J47: 维海德 | K47: 30.97 | L47: 34.96 | M47: 34.87 | N47: 25.37 | O47: 32.25
B48: 45 | C48: 空运 | D48: 9 | E48: =D48/$D$114 -> 0.0016984337 | H48: IT设备 | I48: 301330 | J48: 熵基科技 | K48: 33.19 | L48: 30.4 | M48: 36.09 | N48: 33.33 | O48: 64.07
B49: 46 | C49: 矿物制品 | D49: 32 | E49: =D49/$D$114 -> 0.0060388753 | H49: IT设备 | I49: 301391 | J49: 卡莱特 | K49: 83.95 | L49: 38.56 | M49: 40.6 | N49: 43.45 | O49: 57.09
B50: 47 | C50: 林业 | D50: 4 | E50: =D50/$D$114 -> 0.00075485941 | H50: IT设备 | I50: 301503 | J50: 智迪科技 | K50: 34.51 | L50: 34.77 | M50: 40.43 | N50: 37.55 | O50: 27.61
B51: 48 | C51: 路桥 | D51: 19 | E51: =D51/$D$114 -> 0.0035855822 | H51: IT设备 | I51: 430198 | J51: 微创光电 | K51: 4.05 | O51: 6.54
B52: 49 | C52: 旅游服务 | D52: 10 | E52: =D52/$D$114 -> 0.0018871485 | H52: IT设备 | I52: 600100 | J52: 同方股份 | K52: 7.38 | M52: 122.03 | O52: 247.25
B53: 50 | C53: 旅游景点 | D53: 13 | E53: =D53/$D$114 -> 0.0024532931 | H53: IT设备 | I53: 603019 | J53: 中科曙光 | K53: 37.41 | L53: 33.89 | M53: 50.25 | N53: 35.46 | O53: 547.52
B54: 51 | C54: 铝 | D54: 31 | E54: =D54/$D$114 -> 0.0058501604 | H54: IT设备 | I54: 603106 | J54: 恒银科技 | K54: 6.89 | O54: 35.86
B55: 52 | C55: 煤炭开采 | D55: 25 | E55: =D55/$D$114 -> 0.0047178713 | H55: IT设备 | I55: 603496 | J55: 恒为科技 | K55: 38.91 | L55: 161.87 | M55: 369.76 | N55: 163.46 | O55: 124.59
B56: 53 | C56: 摩托车 | D56: 12 | E56: =D56/$D$114 -> 0.0022645782 | H56: IT设备 | I56: 603516 | J56: 淳中科技 | K56: 16.43 | L56: 176.76 | M56: 230.32 | N56: 103.77 | O56: 30.43
B57: 54 | C57: 农药化肥 | D57: 57 | E57: =D57/$D$114 -> 0.010756747 | H57: IT设备 | I57: 603660 | J57: 苏州科达 | K57: 6.51 | O57: 32.74
B58: 55 | C58: 农业综合 | D58: 43 | E58: =D58/$D$114 -> 0.0081147386 | H58: IT设备 | I58: 688208 | J58: 道通科技 | K58: 30.8 | L58: 67.76 | M58: 36.81 | N58: 136.4 | O58: 139.18
B59: 56 | C59: 农用机械 | D59: 12 | E59: =D59/$D$114 -> 0.0022645782 | H59: IT设备 | I59: 688288 | J59: 鸿泉物联 | K59: 24.16 | O59: 24.24
B60: 57 | C60: 批发业 | D60: 5 | E60: =D60/$D$114 -> 0.00094357426 | H60: IT设备 | I60: 688475 | J60: 萤石网络 | K60: 53.25 | L60: 68.11 | M60: 57.93 | N60: 89.93 | O60: 299.53
B61: 58 | C61: 啤酒 | D61: 8 | E61: =D61/$D$114 -> 0.0015097188 | H61: IT设备 | I61: 688489 | J61: 三未信安 | K61: 45.6 | L61: 50.4 | M61: 256.1 | N61: 48.44 | O61: 51.93
B62: 59 | C62: 普钢 | D62: 26 | E62: =D62/$D$114 -> 0.0049065861 | H62: IT设备 | I62: 832876 | J62: 慧为智能 | K62: 6.66 | L62: 21.17 | M62: 19.85 | N62: 17.42 | O62: 4.27
B63: 60 | C63: 其他建材 | D63: 36 | E63: =D63/$D$114 -> 0.0067937347 | H63: IT设备 | I63: 836395 | J63: 朗鸿科技 | K63: 5.73 | L63: 13.44 | M63: 14.74 | N63: 12.45 | O63: 5.25
B64: 61 | C64: 其他商业 | D64: 12 | E64: =D64/$D$114 -> 0.0022645782 | H64: IT设备 | I64: 872190 | J64: 雷神科技 | K64: 9.94 | L64: 15.31 | M64: 20.79 | N64: 14.47 | O64: 9.94
B65: 62 | C65: 汽车服务 | D65: 16 | E65: =D65/$D$114 -> 0.0030194376 | H65: IT设备 | I65: 872374 | J65: 云里物里 | K65: 7.88 | L65: 24.58 | M65: 24.42 | N65: 24.14 | O65: 6.42
B66: 63 | C66: 汽车配件 | D66: 223 | E66: =D66/$D$114 -> 0.042083412 | H66: IT设备 | I66: 872808 | J66: 曙光数创 | K66: 33.51 | L66: 49.94 | M66: 70.19 | N66: 57.34 | O66: 67.02
B67: 64 | C67: 汽车整车 | D67: 23 | E67: =D67/$D$114 -> 0.0043404416 | H67: 白酒 | I67: 000568 | J67: 泸州老窖 | K67: 205.15 | L67: 25.33 | M67: 21.29 | N67: 29.13 | O67: 3019.78
B68: 65 | C68: 铅锌 | D68: 14 | E68: =D68/$D$114 -> 0.0026420079 | H68: 白酒 | I68: 000596 | J68: 古井贡酒 | K68: 266.3 | L68: 35.16 | M68: 25.32 | N68: 44.79 | O68: 1407.66
B69: 66 | C69: 轻工机械 | D69: 7 | E69: =D69/$D$114 -> 0.001321004 | H69: 白酒 | I69: 000799 | J69: 酒鬼酒 | K69: 81.82 | L69: 35.32 | M69: 31.5 | N69: 25.35 | O69: 265.86
B70: 67 | C70: 区域地产 | D70: 49 | E70: =D70/$D$114 -> 0.0092470277 | H70: 白酒 | I70: 000858 | J70: 五 粮 液 | K70: 153.63 | L70: 20.83 | M70: 17.5 | N70: 22.34 | O70: 5963.31
B71: 68 | C71: 全国地产 | D71: 29 | E71: =D71/$D$114 -> 0.0054727307 | H71: 白酒 | I71: 000860 | J71: 顺鑫农业 | K71: 22.78 | O71: 168.97
B72: 69 | C72: 染料涂料 | D72: 31 | E72: =D72/$D$114 -> 0.0058501604 | H72: 白酒 | I72: 000995 | J72: 皇台酒业 | K72: 15.38 | L72: 367.65 | M72: 449.01 | N72: 370.92 | O72: 27.29
B73: 70 | C73: 日用化工 | D73: 18 | E73: =D73/$D$114 -> 0.0033968673 | H73: 白酒 | I73: 002304 | J73: 洋河股份 | K73: 121.87 | L73: 17.75 | M73: 11.68 | N73: 19.58 | O73: 1836.57
B74: 71 | C74: 乳制品 | D74: 21 | E74: =D74/$D$114 -> 0.0039630119 | H74: 白酒 | I74: 002646 | J74: 天佑德酒 | K74: 13.99 | L74: 91.02 | M74: 34.24 | N74: 87.84 | O74: 66.11
B75: 72 | C75: 软件服务 | D75: 295 | E75: =D75/$D$114 -> 0.055670881 | H75: 白酒 | I75: 600197 | J75: 伊力特 | K75: 22.43 | L75: 49.59 | M75: 30 | N75: 63.99 | O75: 105.86
B76: 73 | C76: 软饮料 | D76: 9 | E76: =D76/$D$114 -> 0.0016984337 | H76: 白酒 | I76: 600199 | J76: 金种子酒 | K76: 24.23 | O76: 159.38
B77: 74 | C77: 商贸代理 | D77: 19 | E77: =D77/$D$114 -> 0.0035855822 | H77: 白酒 | I77: 600519 | J77: 贵州茅台 | K77: 1751 | L77: 31.92 | M77: 30.57 | N77: 35.07 | O77: 21996.02
B78: 75 | C78: 商品城 | D78: 4 | E78: =D78/$D$114 -> 0.00075485941 | H78: 白酒 | I78: 600559 | J78: 老白干酒 | K78: 22.85 | L78: 37.2 | M78: 48.16 | N78: 29.54 | O78: 209.02
B79: 76 | C79: 生物制药 | D79: 77 | E79: =D79/$D$114 -> 0.014531044 | H79: 白酒 | I79: 600696 | J79: 岩石股份 | K79: 22.12 | L79: 136.61 | M79: 69.13 | N79: 198.65 | O79: 73.98
B80: 77 | C80: 石油加工 | D80: 10 | E80: =D80/$D$114 -> 0.0018871485 | H80: 白酒 | I80: 600702 | J80: 舍得酒业 | K80: 122.16 | L80: 23 | M80: 22.13 | N80: 24.15 | O80: 407.03
B81: 78 | C81: 石油开采 | D81: 20 | E81: =D81/$D$114 -> 0.003774297 | H81: 白酒 | I81: 600779 | J81: 水井坊 | K81: 58.78 | L81: 27.37 | M81: 70.78 | N81: 23.61 | O81: 287.06
B82: 79 | C82: 石油贸易 | D82: 7 | E82: =D82/$D$114 -> 0.001321004 | H82: 白酒 | I82: 600809 | J82: 山西汾酒 | K82: 230.25 | L82: 28.52 | M82: 20.75 | N82: 34.7 | O82: 2808.97
B83: 80 | C83: 食品 | D83: 92 | E83: =D83/$D$114 -> 0.017361766 | H83: 白酒 | I83: 603198 | J83: 迎驾贡酒 | K83: 70.9 | L83: 28.51 | M83: 26.66 | N83: 33.26 | O83: 567.2
B84: 81 | C84: 水力发电 | D84: 18 | E84: =D84/$D$114 -> 0.0033968673 | H84: 白酒 | I84: 603369 | J84: 今世缘 | K84: 56.29 | L84: 24.06 | M84: 17.22 | N84: 28.21 | O84: 706.16
B85: 82 | C85: 水泥 | D85: 23 | E85: =D85/$D$114 -> 0.0043404416 | H85: 白酒 | I85: 603589 | J85: 口子窖 | K85: 50.12 | L85: 18.13 | M85: 17.74 | N85: 19.4 | O85: 300.72
B86: 83 | C86: 水务 | D86: 17 | E86: =D86/$D$114 -> 0.0032081525 | H86: 白酒 | I86: 603919 | J86: 金徽酒 | K86: 28.06 | L86: 44.1 | M86: 27.98 | N86: 50.79 | O86: 142.34
B87: 84 | C87: 水运 | D87: 17 | E87: =D87/$D$114 -> 0.0032081525 | H87: 百货 | I87: 000417 | J87: 合肥百货 | K87: 5.11 | L87: 12.72 | M87: 7.97 | N87: 23.78 | O87: 39.85
B88: 85 | C88: 饲料 | D88: 21 | E88: =D88/$D$114 -> 0.0039630119 | H88: 百货 | I88: 000419 | J88: 通程控股 | K88: 5.43 | L88: 24.3 | M88: 14.53 | N88: 20.25 | O88: 29.52
B89: 86 | C89: 塑料 | D89: 69 | E89: =D89/$D$114 -> 0.013021325 | H89: 百货 | I89: 000501 | J89: 武商集团 | K89: 9.03 | L89: 45.18 | M89: 29.66 | N89: 22.79 | O89: 69.44
B90: 87 | C90: 陶瓷 | D90: 5 | E90: =D90/$D$114 -> 0.00094357426 | H90: 百货 | I90: 000564 | J90: ST大集 | K90: 1.24 | O90: 237.63
B91: 88 | C91: 特种钢 | D91: 10 | E91: =D91/$D$114 -> 0.0018871485 | H91: 百货 | I91: 000679 | J91: 大连友谊 | K91: 5.85 | O91: 20.85
B92: 89 | C92: 铁路 | D92: 6 | E92: =D92/$D$114 -> 0.0011322891 | H92: 百货 | I92: 000715 | J92: 中兴商业 | K92: 6.9 | L92: 25.2 | M92: 27.49 | N92: 33.5 | O92: 28.68
B93: 90 | C93: 通信设备 | D93: 136 | E93: =D93/$D$114 -> 0.02566522 | H93: 百货 | I93: 000785 | J93: 居然之家 | K93: 3.55 | L93: 15.24 | M93: 12.88 | N93: 13.54 | O93: 223.2
B94: 91 | C94: 铜 | D94: 16 | E94: =D94/$D$114 -> 0.0030194376 | H94: 百货 | I94: 002187 | J94: 广百股份 | K94: 6.4 | M94: 75.36 | O94: 45.06
B95: 92 | C95: 文教休闲 | D95: 51 | E95: =D95/$D$114 -> 0.0096244574 | H95: 百货 | I95: 002277 | J95: 友阿股份 | K95: 3.22 | L95: 106.68 | M95: 26.78 | N95: 135.8 | O95: 44.89
B96: 93 | C96: 橡胶 | D96: 14 | E96: =D96/$D$114 -> 0.0026420079 | H96: 百货 | I96: 002419 | J96: 天虹股份 | K96: 5.45 | L96: 36.48 | M96: 14.83 | N96: 53.04 | O96: 63.7
B97: 94 | C97: 小金属 | D97: 59 | E97: =D97/$D$114 -> 0.011134176 | H97: 百货 | I97: 002561 | J97: 徐家汇 | K97: 8.7 | L97: 55.48 | M97: 54.11 | N97: 147.79 | O97: 36.17
B98: 95 | C98: 新型电力 | D98: 22 | E98: =D98/$D$114 -> 0.0041517267 | H98: 百货 | I98: 600280 | J98: 中央商场 | K98: 3.72 | M98: 270.22 | O98: 41.97
B99: 96 | C99: 医疗保健 | D99: 169 | E99: =D99/$D$114 -> 0.03189281 | H99: 百货 | I99: 600306 | J99: *ST商城 | K99: 10.36 | O99: 23.99
B100: 97 | C100: 医药商业 | D100: 37 | E100: =D100/$D$114 -> 0.0069824495 | H100: 百货 | I100: 600628 | J100: 新世界 | K100: 7.07 | L100: 253.69 | M100: 60.13 | O100: 45.73
B101: 98 | C101: 银行 | D101: 42 | E101: =D101/$D$114 -> 0.0079260238 | H101: 百货 | I101: 600655 | J101: 豫园股份 | K101: 7.23 | L101: 5.25 | M101: 6.35 | N101: 7.36 | O101: 281.6
B102: 99 | C102: 影视音像 | D102: 39 | E102: =D102/$D$114 -> 0.0073598792 | H102: 百货 | I102: 600693 | J102: 东百集团 | K102: 3.9 | L102: 150.12 | M102: 16.88 | N102: 155.74 | O102: 33.92
...

Sheet 桂兰
A1: back | D1: 操盘：郑桂兰
D2: 时间 | E2: 市场 | F2: 企业 | G2: 股票代码 | H2: 操作 | I2: 数量 | J2: 平均买价 | K2: 成本 | L2: 买卖价格 | M2: 市值
C3: 1 | D3: 45150 | E3: CN | F3: 中国医药 | G3: 600056 | H3: 买入 | I3: 2000 | L3: 13.48 | M3: =L3*I3 -> 26960
C4: 2 | D4: 45150 | E4: CN | F4: 新研股份 | G4: 300159 | H4: 买入 | I4: 5000 | L4: 3.25 | M4: =L4*I4 -> 16250
C5: 3 | D5: 45150 | E5: CN | F5: 众泰汽车 | G5: 000980 | H5: 买入 | I5: 5000 | L5: 4.27 | M5: =L5*I5 -> 21350
C6: 4 | D6: 45374 | E6: CN | F6: 中国医药 | G6: 600056 | H6: 卖出 | I6: -2000 | L6: 11.1 | M6: =L6*I6 -> -22200
C7: 5 | D7: 45374 | E7: CN | F7: 新研股份 | G7: 300159 | H7: 卖出 | I7: -5000 | L7: 2.25 | M7: =L7*I7 -> -11250
C8: 6 | D8: 45374 | E8: CN | F8: 众泰汽车 | G8: 000980 | H8: 卖出 | I8: -5000 | L8: 2.61 | M8: =L8*I8 -> -13050
C9: 7 | D9: 45276 | E9: HK | F9: 东方甄选 | G9: 1797 | H9: 买入 | I9: 200 | L9: 26.25 | M9: =L9*I9 -> 5250
C10: 8 | D10: 45367 | E10: US | F10: 亚马逊 | G10: AMZN | H10: 买入 | I10: 20 | L10: 1360.476 | M10: =L10*I10 -> 27209.52
C11: 9 | D11: 45367 | E11: US | F11: 脸书 | G11: Meta | H11: 买入 | I11: 30 | L11: 3775.98 | M11: =L11*I11 -> 113279.4
C12: 10 | D12: 45367 | E12: US | F12: 英伟达 | G12: NVDA | H12: 买入 | I12: 20 | L12: 6851.286 | M12: =L12*I12 -> 137025.72
C13: 11 | D13: 45367 | E13: US | F13: 微软 | G13: MSFT | H13: 买入 | I13: 30 | L13: 3248.076 | M13: =L13*I13 -> 97442.28
C14: 12 | D14: 45374 | E14: US | F14: 英伟达 | G14: NVDA | H14: 买入 | I14: 50 | L14: 7354.542 | M14: =L14*I14 -> 367727.1
C15: 13 | D15: 45374 | E15: US | F15: 微软 | G15: MSFT | H15: 买入 | I15: 40 | L15: 3344.172 | M15: =L15*I15 -> 133766.88
C16: 14 | D16: 45374 | E16: US | F16: 高通 | G16: QCOM | H16: 买入 | I16: 40 | L16: 1326.78 | M16: =L16*I16 -> 53071.2
C17: 15 | D17: 45374 | E17: HK | F17: 小米集团 | G17: 01810 | H17: 买入 | I17: 200 | L17: 14.8 | M17: =L17*I17 -> 2960
C18: 16 | D18: 45374 | E18: US | F18: 台积电 | G18: TSM | H18: 买入 | I18: 40 | L18: 1096.212 | M18: =L18*I18 -> 43848.48
C19: 17 | D19: 45451 | E19: HK | F19: 东方甄选 | G19: 1797 | H19: 卖出 | I19: -200 | L19: 15.32 | M19: =L19*I19 -> -3064
C20: 18 | D20: 45451 | E20: US | F20: 拼多多 | G20: PDD | H20: 买入 | I20: 3 | L20: 1122.42 | M20: =L20*I20 -> 3367.26
C21: 19 | D21: 45458 | E21: US | F21: 英伟达 | G21: NVDA | H21: 拆分 | I21: 630 | L21: 0 | M21: =L21*I21 -> 0
C22: 20 | D22: 45458 | E22: US | F22: 英伟达 | G22: NVDA | H22: 卖出 | I22: -100 | L22: 1028.664 | M22: =L22*I22 -> -102866.4
C23: 21 | D23: 45458 | E23: US | F23: 拼多多 | G23: PDD | H23: 买入 | I23: 37 | L23: 1162.044 | M23: =L23*I23 -> 42995.628
C24: 22 | D24: 45458 | E24: US | F24: 苹果 | G24: AAPL | H24: 买入 | I24: 36 | L24: 1657.422 | M24: =L24*I24 -> 59667.192
C25: 23 | D25: 45528 | E25: US | F25: 亚马逊 | G25: AMZN | H25: 卖出 | I25: -20 | L25: 1380.912 | M25: =L25*I25 -> -27618.24
C26: 24 | D26: 45528 | E26: US | F26: 脸书 | G26: Meta | H26: 卖出 | I26: -30 | L26: 4118.4 | M26: =L26*I26 -> -123552
C27: 25 | D27: 45528 | E27: US | F27: 英伟达 | G27: NVDA | H27: 卖出 | I27: -600 | L27: 1009.086 | M27: =L27*I27 -> -605451.6
C28: 26 | D28: 45528 | E28: US | F28: 微软 | G28: MSFT | H28: 卖出 | I28: -70 | L28: 3250.962 | M28: =L28*I28 -> -227567.34
C29: 27 | D29: 45528 | E29: US | F29: 高通 | G29: QCOM | H29: 卖出 | I29: -40 | L29: 1353.3 | M29: =L29*I29 -> -54132
C30: 28 | D30: 45528 | E30: HK | F30: 小米集团 | G30: 01810 | H30: 卖出 | I30: -200 | L30: 18.82 | M30: =L30*I30 -> -3764
C31: 29 | D31: 45528 | E31: US | F31: 台积电 | G31: TSM | H31: 卖出 | I31: -40 | L31: 1335.984 | M31: =L31*I31 -> -53439.36
... C33: 31 | D33: 45528 | E33: US | F33: 苹果 | G33: AAPL | H33: 卖出 | I33: -36 | L33: 1769.352 | M33: =L33*I33 -> -63696.672
D34: 45570 | E34: CN | F34: 国信证券 | G34: 002736 | H34: 买入 | I34: 16906 | L34: 11.83 | M34: =L34*I34 -> 199997.98
D35: 45570 | E35: CN | F35: 中信证券 | G35: 600030 | H35: 买入 | I35: 7352 | L35: 27.2 | M35: =L35*I35 -> 199974.4
D36: 45570 | E36: CN | F36: 招商证券 | G36: 600999 | H36: 买入 | I36: 10288 | L36: 19.44 | M36: =L36*I36 -> 199998.72
D37: 45570 | E37: HK | F37: 小米集团 | G37: 01810 | H37: 买入 | I37: 4073 | L37: 24.55 | M37: =L37*I37 -> 99992.15
D38: 45570 | E38: US | F38: 拼多多 | G38: PDD | H38: 买入 | I38: 83 | L38: 1203.306 | M38: =L38*I38 -> 99874.398
D39: 45605 | E39: US | F39: 英伟达 | G39: NVDA | H39: 买入 | I39: 175 | L39: 1151.514 | M39: =L39*I39 -> 201514.95
D40: 45605 | E40: US | F40: 特斯拉 | G40: TSLA | H40: 买入 | I40: 80 | L40: 2505.516 | M40: =L40*I40 -> 200441.28
M41: =L41*I41 -> 0
D42: 累计净买入 | M42: =SUM(M3:M41) -> 998673.49
D43: 时间 | E43: 市场 | F43: 企业 | G43: 股票代码 | H43: 状态 | I43: 数量 | J43: 平均买价 | K43: 成本 | L43: 当前价格 | M43: 市值
D44: =全班!$R$1 -> 46011 | E44: CN | F44: 国信证券 | G44: 002736 | H44: 持有 | I44: =SUMIFS($I$34:$I$42,$G$34:$G$42,G44) -> 16906 | J44: =K44/I44 -> 11.83 | K44: =SUMIFS($M$34:$M$42,$G$34:$G$42,G44) -> 199997.98 | L44: =VLOOKUP(G44,股价!C:D,2,FALSE) -> 13.17 | M44: =IFERROR(I44*L44,0) -> 222652.02
D45: =全班!$R$1 -> 46011 | E45: CN | F45: 中信证券 | G45: 600030 | H45: 持有 | I45: =SUMIFS($I$34:$I$42,$G$34:$G$42,G45) -> 7352 | J45: =K45/I45 -> 27.2 | K45: =SUMIFS($M$34:$M$42,$G$34:$G$42,G45) -> 199974.4 | L45: =VLOOKUP(G45,股价!C:D,2,FALSE) -> 28.68 | M45: =IFERROR(I45*L45,0) -> 210855.36
D46: =全班!$R$1 -> 46011 | E46: CN | F46: 招商证券 | G46: 600999 | H46: 持有 | I46: =SUMIFS($I$34:$I$42,$G$34:$G$42,G46) -> 10288 | J46: =K46/I46 -> 19.44 | K46: =SUMIFS($M$34:$M$42,$G$34:$G$42,G46) -> 199998.72 | L46: =VLOOKUP(G46,股价!C:D,2,FALSE) -> 16.82 | M46: =IFERROR(I46*L46,0) -> 173044.16
D47: =全班!$R$1 -> 46011 | E47: HK | F47: 小米集团 | G47: 01810 | H47: 持有 | I47: =SUMIFS($I$34:$I$42,$G$34:$G$42,G47) -> 4073 | J47: =K47/I47 -> 24.55 | K47: =SUMIFS($M$34:$M$42,$G$34:$G$42,G47) -> 99992.15 | L47: =VLOOKUP(G47,股价!C:D,2,FALSE) -> 40.54 | M47: =IFERROR(I47*L47,0) -> 165119.42
D48: =全班!$R$1 -> 46011 | E48: US | F48: 拼多多 | G48: PDD | H48: 持有 | I48: =SUMIFS($I$34:$I$42,$G$34:$G$42,G48) -> 83 | J48: =K48/I48 -> 1203.306 | K48: =SUMIFS($M$34:$M$42,$G$34:$G$42,G48) -> 99874.398 | L48: =VLOOKUP(G48,股价!C:D,2,FALSE) -> 854.178 | M48: =IFERROR(I48*L48,0) -> 70896.774
D49: =全班!$R$1 -> 46011 | E49: US | F49: 英伟达 | G49: NVDA | H49: 持有 | I49: =SUMIFS($I$34:$I$42,$G$34:$G$42,G49) -> 175 | J49: =K49/I49 -> 1151.514 | K49: =SUMIFS($M$34:$M$42,$G$34:$G$42,G49) -> 201514.95 | L49: =VLOOKUP(G49,股价!C:D,2,FALSE) -> 1411.722 | M49: =IFERROR(I49*L49,0) -> 247051.35
D50: =全班!$R$1 -> 46011 | E50: US | F50: 特斯拉 | G50: TSLA | H50: 持有 | I50: =SUMIFS($I$34:$I$42,$G$34:$G$42,G50) -> 80 | J50: =K50/I50 -> 2505.516 | K50: =SUMIFS($M$34:$M$42,$G$34:$G$42,G50) -> 200441.28 | L50: =VLOOKUP(G50,股价!C:D,2,FALSE) -> 3753.36 | M50: =IFERROR(I50*L50,0) -> 300268.8
D52: 市值结余 | M52: =SUM(M44:M51) -> 1389887.9
D53: 累计分红 | M53: =L66 -> 13.65
D54: 现金结余 | M54: =M59-M42+M53 -> 1340.164
D55: 结余总额 | M55: =M52+M54 -> 1391228
D56: 累计盈利 | M56: =M55-M59 -> 391228.05
D57: 盈利率 | M57: =M56/M59 -> 0.39122805
D59: 本金 | M59: =本金与余额!D22 -> 1000000
D60: 登记日 | E60: 市场 | F60: 企业 | G60: 股票代码 | H60: 状态 | I60: 数量 | J60: 分红方案 | K60: 实施 | L60: 红利金额 | M60: 除权日
D61: 45458 | E61: US | F61: 英伟达 | G61: NVDA | H61: 拆分 | I61: 70 | J61: 1拆10 | K61: 700
D62: 45819 | E62: US | F62: 英伟达 | G62: NVDA | H62: 分红 | I62: 175 | J62: 1派0.01USD | K62: 1派0.01USD | L62: =I62*0.01*7.8 -> 13.65 | M62: 45819
D66: 累计分红 | L66: =SUM(L61:L65) -> 13.65

Sheet 徐成
A1: back | D1: 操盘：徐成
D2: 时间 | E2: 市场 | F2: 企业 | G2: 股票代码 | H2: 操作 | I2: 数量 | J2: 平均买价 | K2: 成本 | L2: 买卖价格 | M2: 市值
D3: 45416 | E3: CN | F3: 大族数控 | G3: 301200 | H3: 买入 | I3: 1000 | L3: 34.99 | M3: =L3*I3 -> 34990
D4: 45423 | E4: CN | F4: 大族数控 | G4: 301200 | H4: 卖出 | I4: -400 | L4: 34.5 | M4: =L4*I4 -> -13800
D5: 45430 | E5: CN | F5: 大族数控 | G5: 301200 | H5: 卖出 | I5: -600 | L5: 34.99 | M5: =L5*I5 -> -20994
D6: 45416 | E6: HK | F6: 京东健康 | G6: 6618 | H6: 买入 | I6: 2000 | L6: 30.5 | M6: =L6*I6 -> 61000
D7: 45423 | E7: HK | F7: 京东健康 | G7: 6618 | H7: 卖出 | I7: -1000 | L7: 29.5 | M7: =L7*I7 -> -29500
D8: 45430 | E8: HK | F8: 京东健康 | G8: 6618 | H8: 卖出 | I8: -1000 | L8: 30.3 | M8: =L8*I8 -> -30300
D9: 45430 | E9: HK | F9: 农夫山泉 | G9: 9633 | H9: 买入 | I9: 30 | L9: 46.4 | M9: =L9*I9 -> 1392
D10: 45437 | E10: HK | F10: 农夫山泉 | G10: 9633 | H10: 卖出 | I10: -30 | L10: 43.35 | M10: =L10*I10 -> -1300.5
C11: 1 | D11: 45402 | E11: CN | F11: 鹏辉能源 | G11: 300438 | H11: 买入 | I11: 11344 | L11: 22.92 | M11: =L11*I11 -> 260004.48
C12: 5 | D12: 45409 | E12: CN | F12: 鹏辉能源 | G12: 300438 | H12: 卖出 | I12: -10667 | L12: 22.5 | M12: =L12*I12 -> -240007.5
D13: 45416 | E13: CN | F13: 鹏辉能源 | G13: 300438 | H13: 买入 | I13: 60 | L13: 23.96 | M13: =L13*I13 -> 1437.6
D14: 45423 | E14: CN | F14: 鹏辉能源 | G14: 300438 | H14: 卖出 | I14: -237 | L14: 24.39 | M14: =L14*I14 -> -5780.43
D15: 45437 | E15: CN | F15: 鹏辉能源 | G15: 300438 | H15: 卖出 | I15: -500 | L15: 22.56 | M15: =L15*I15 -> -11280
D16: 45444 | E16: CN | F16: 天银机电 | G16: 300342 | H16: 买入 | I16: 1200 | L16: 17.81 | M16: =L16*I16 -> 21372
D17: 45451 | E17: CN | F17: 天银机电 | G17: 300342 | H17: 卖出 | I17: -1200 | L17: 14.4 | M17: =L17*I17 -> -17280
D18: 45458 | E18: US | F18: 帕卡 | G18: PCAR | H18: 买入 | I18: 30 | L18: 832.416 | M18: =L18*I18 -> 24972.48
D19: 45465 | E19: US | F19: 帕卡 | G19: PCAR | H19: 卖出 | I19: -30 | L19: 826.488 | M19: =L19*I19 -> -24794.64
D20: 45430 | E20: CN | F20: 中国银行 | G20: 601988 | H20: 买入 | I20: 300 | L20: 4.49 | M20: =L20*I20 -> 1347
D21: 45458 | E21: CN | F21: 中国银行 | G21: 601988 | H21: 卖出 | I21: -200 | L21: 4.48 | M21: =L21*I21 -> -896
D22: 45486 | E22: CN | F22: 中国银行 | G22: 601988 | H22: 卖出 | I22: -100 | L22: 4.77 | M22: =L22*I22 -> -477
D23: 45493 | E23: US | F23: 爱芬奇 | G23: ANF | H23: 买入 | I23: 60 | L23: 1236.378 | M23: =L23*I23 -> 74182.68
D24: 45528 | E24: US | F24: 爱芬奇 | G24: ANF | H24: 买入 | I24: 40 | L24: 1324.674 | M24: =L24*I24 -> 52986.96
... D46: 45493 | E46: CN | F46: 工商银行 | G46: 601398 | H46: 卖出 | I46: -200 | L46: 5.91 | M46: =L46*I46 -> -1182
C47: 2 | D47: 45402 | E47: CN | F47: 大族激光 | G47: 002008 | H47: 买入 | I47: 7912 | L47: 18.96 | M47: =L47*I47 -> 150011.52
C48: 7 | D48: 45409 | E48: CN | F48: 大族激光 | G48: 002008 | H48: 买入 | I48: 1490 | L48: 20.14 | M48: =L48*I48 -> 30008.6
D49: 45416 | E49: CN | F49: 大族激光 | G49: 002008 | H49: 买入 | I49: 800 | L49: 21.09 | M49: =L49*I49 -> 16872
D50: 45423 | E50: CN | F50: 大族激光 | G50: 002008 | H50: 卖出 | I50: -6000 | L50: 21.11 | M50: =L50*I50 -> -126660
D51: 45437 | E51: CN | F51: 大族激光 | G51: 002008 | H51: 买入 | I51: 300 | L51: 20.2 | M51: =L51*I51 -> 6060
D52: 45458 | E52: CN | F52: 大族激光 | G52: 002008 | H52: 卖出 | I52: -502 | L52: 20.82 | M52: =L52*I52 -> -10451.64
D53: 45472 | E53: CN | F53: 大族激光 | G53: 002008 | H53: 买入 | I53: 4000 | L53: 20.8 | M53: =L53*I53 -> 83200
D54: 45479 | E54: CN | F54: 大族激光 | G54: 002008 | H54: 卖出 | I54: -2000 | L54: 19.93 | M54: =L54*I54 -> -39860
D55: 45486 | E55: CN | F55: 大族激光 | G55: 002008 | H55: 卖出 | I55: -4000 | L55: 21.57 | M55: =L55*I55 -> -86280
D56: 45493 | E56: CN | F56: 大族激光 | G56: 002008 | H56: 买入 | I56: 11000 | L56: 22.09 | M56: =L56*I56 -> 242990
D57: 45528 | E57: CN | F57: 大族激光 | G57: 002008 | H57: 卖出 | I57: -13000 | L57: 18.61 | M57: =L57*I57 -> -241930
C58: 3 | D58: 45402 | E58: CN | F58: 京华激光 | G58: 603607 | H58: 买入 | I58: 7605 | L58: 13.15 | M58: =L58*I58 -> 100005.75
C59: 4 | D59: 45402 | E59: US | F59: 贝壳 | G59: BEKE | H59: 买入 | I59: 306 | L59: 98.124 | M59: =L59*I59 -> 30025.944
C60: 6 | D60: 45409 | E60: CN | F60: 京华激光 | G60: 603607 | H60: 买入 | I60: 2197 | L60: 13.66 | M60: =L60*I60 -> 30011.02
C61: 8 | D61: 45409 | E61: US | F61: 贝壳 | G61: BEKE | H61: 买入 | I61: 1297 | L61: 115.674 | M61: =L61*I61 -> 150029.18
C62: 9 | D62: 45409 | E62: US | F62: 拼多多 | G62: PDD | H62: 买入 | I62: 219 | L62: 1008.618 | M62: =L62*I62 -> 220887.34
D63: 45416 | E63: CN | F63: 京华激光 | G63: 603607 | H63: 卖出 | I63: -6000 | L63: 14.09 | M63: =L63*I63 -> -84540
D64: 45416 | E64: US | F64: 贝壳 | G64: BEKE | H64: 买入 | I64: 40 | L64: 136.266 | M64: =L64*I64 -> 5450.64
D65: 45416 | E65: US | F65: 拼多多 | G65: PDD | H65: 卖出 | I65: -120 | L65: 1093.404 | M65: =L65*I65 -> -131208.48
D66: 45423 | E66: US | F66: 贝壳 | G66: BEKE | H66: 买入 | I66: 158 | L66: 133.38 | M66: =L66*I66 -> 21074.04
D67: 45423 | E67: US | F67: 拼多多 | G67: PDD | H67: 买入 | I67: 111 | L67: 1062.906 | M67: =L67*I67 -> 117982.57
D68: 45423 | E68: CN | F68: 京华激光 | G68: 603607 | H68: 买入 | I68: 600 | L68: 13.93 | M68: =L68*I68 -> 8358
D69: 45430 | E69: US | F69: 贝壳 | G69: BEKE | H69: 买入 | I69: 30 | L69: 151.866 | M69: =L69*I69 -> 4555.98
D70: 45430 | E70: US | F70: 拼多多 | G70: PDD | H70: 买入 | I70: 50 | L70: 1140.282 | M70: =L70*I70 -> 57014.1
D71: 45437 | E71: CN | F71: 京华激光 | G71: 603607 | H71: 买入 | I71: 200 | L71: 13.35 | M71: =L71*I71 -> 2670
D72: =全班!$R$1 -> 46011 | E72: US | F72: 贝壳 | G72: BEKE | H72: 买入 | I72: 100 | L72: 129.948 | M72: =L72*I72 -> 12994.8
D73: 45437 | E73: US | F73: 拼多多 | G73: PDD | H73: 买入 | I73: 40 | L73: 1229.046 | M73: =L73*I73 -> 49161.84
D74: 45444 | E74: CN | F74: 京华激光 | G74: 603607 | H74: 卖出 | I74: -2000 | L74: 13.76 | M74: =L74*I74 -> -27520
D75: 45458 | E75: CN | F75: 京华激光 | G75: 603607 | H75: 卖出 | I75: -1602 | L75: 13.11 | M75: =L75*I75 -> -21002.22
D76: 45458 | E76: US | F76: 贝壳 | G76: BEKE | H76: 卖出 | I76: -1000 | L76: 122.538 | M76: =L76*I76 -> -122538
D77: 45458 | E77: US | F77: 拼多多 | G77: PDD | H77: 卖出 | I77: -100 | L77: 1162.044 | M77: =L77*I77 -> -116204.4
D78: 45458 | E78: US | F78: 亚马逊 | G78: AMZN | H78: 买入 | I78: 30 | L78: 1432.548 | M78: =L78*I78 -> 42976.44
D79: 45458 | E79: US | F79: 脸书 | G79: Meta | H79: 买入 | I79: 20 | L79: 3932.448 | M79: =L79*I79 -> 78648.96
D80: 45458 | E80: US | F80: 英伟达 | G80: NVDA | H80: 买入 | I80: 60 | L80: 1028.664 | M80: =L80*I80 -> 61719.84
D81: 45465 | E81: US | F81: 贝壳 | G81: BEKE | H81: 卖出 | I81: -631 | L81: 120.822 | M81: =L81*I81 -> -76238.682
D82: 45472 | E82: US | F82: 英伟达 | G82: NVDA | H82: 卖出 | I82: -60 | L82: 963.612 | M82: =L82*I82 -> -57816.72
D83: 45472 | E83: CN | F83: 京华激光 | G83: 603607 | H83: 买入 | I83: 1000 | L83: 12.51 | M83: =L83*I83 -> 12510
D84: 45472 | E84: US | F84: 贝壳 | G84: BEKE | H84: 买入 | I84: 900 | L84: 110.37 | M84: =L84*I84 -> 99333
D85: 45472 | E85: US | F85: 脸书 | G85: Meta | H85: 卖出 | I85: -20 | L85: 3932.916 | M85: =L85*I85 -> -78658.32
D86: =全班!$R$1 -> 46011 | E86: US | F86: 亚马逊 | G86: AMZN | H86: 买入 | I86: 40 | L86: 1517.022 | M86: =L86*I86 -> 60680.88
D87: 45493 | E87: CN | F87: 京华激光 | G87: 603607 | H87: 买入 | I87: 1000 | L87: 14.31 | M87: =L87*I87 -> 14310
D88: 45493 | E88: US | F88: 贝壳 | G88: BEKE | H88: 卖出 | I88: -600 | L88: 110.136 | M88: =L88*I88 -> -66081.6
D89: 45493 | E89: US | F89: 拼多多 | G89: PDD | H89: 卖出 | I89: -150 | L89: 1037.712 | M89: =L89*I89 -> -155656.8
D90: 45493 | E90: US | F90: 亚马逊 | G90: AMZN | H90: 卖出 | I90: -70 | L90: 1428.414 | M90: =L90*I90 -> -99988.98
D91: 45493 | E91: US | F91: 脸书 | G91: Meta | H91: 买入 | I91: 42 | L91: 3718.962 | M91: =L91*I91 -> 156196.4
D92: 45500 | E92: US | F92: 脸书 | G92: Meta | H92: 买入 | I92: 8 | L92: 1302.6 | M92: =L92*I92 -> 10420.8
D93: 45528 | E93: CN | F93: 京华激光 | G93: 603607 | H93: 卖出 | I93: -2000 | L93: 11.98 | M93: =L93*I93 -> -23960
D94: 45528 | E94: US | F94: 贝壳 | G94: BEKE | H94: 买入 | I94: 200 | L94: 117.78 | M94: =L94*I94 -> 23556
D95: 45528 | E95: US | F95: 拼多多 | G95: PDD | H95: 买入 | I95: 30 | L95: 1090.986 | M95: =L95*I95 -> 32729.58
D96: 45528 | E96: US | F96: 脸书 | G96: Meta | H96: 买入 | I96: 30 | L96: 4118.4 | M96: =L96*I96 -> 123552
D97: 45528 | E97: US | F97: 微软 | G97: MSFT | H97: 买入 | I97: 50 | L97: 3250.962 | M97: =L97*I97 -> 162548.1
D98: 45528 | E98: US | F98: 阿斯麦 | G98: ASML | H98: 买入 | I98: 20 | L98: 7076.628 | M98: =L98*I98 -> 141532.56
... D105: 45962 | E105: US | F105: 贝壳 | G105: BEKE | H105: 卖出 | I105: -500 | L105: 132.99 | M105: =L105*I105 -> -66495
D106: =全班!$R$1 -> 46011 | E106: CN | F106: 京华激光 | G106: 603607 | H106: 卖出 | I106: -1500 | L106: 23.45 | M106: =L106*I106 -> -35175
D107: 45962 | E107: US | F107: 英伟达 | G107: NVDA | H107: 卖出 | I107: -5 | L107: 1579.422 | M107: =L107*I107 -> -7897.11
D108: 45962 | E108: HK | F108: 腾讯集团 | G108: 00700 | H108: 买入 | I108: 100 | L108: 629 | M108: =L108*I108 -> 62900
D109: 45962 | E109: HK | F109: 中芯国际 | G109: 00981 | H109: 买入 | I109: 600 | L109: 75 | M109: =L109*I109 -> 45000
M110: =L110*I110 -> 0
M111: =L111*I111 -> 0
M112: =L112*I112 -> 0
D113: 累计净买入 | M113: =SUM(M3:M112) -> 998652.65
D114: 时间 | E114: 市场 | F114: 企业 | G114: 股票代码 | H114: 状态 | I114: 数量 | J114: 平均买价 | K114: 成本 | L114: 当前价格 | M114: 市值
D115: =全班!$R$1 -> 46011 | E115: CN | F115: 京华激光 | G115: 603607 | H115: 持有 | I115: =SUMIFS($I$58:$I$113,$G$58:$G$113,G115) -> 500 | J115: =K115/I115 -> -0.1849 | K115: =SUMIFS($M$58:$M$113,$G$58:$G$113,G115) -> -92.45 | L115: =VLOOKUP(G115,股价!C:D,2,FALSE) -> 26.04 | M115: =IFERROR(I115*L115,0) -> 13020
D116: =全班!$R$1 -> 46011 | E116: US | F116: 贝壳 | G116: BEKE | H116: 持有 | I116: =SUMIFS($I$58:$I$113,$G$58:$G$113,G116) -> 300 | J116: =K116/I116 -> 52.221 | K116: =SUMIFS($M$58:$M$113,$G$58:$G$113,G116) -> 15666.3 | L116: =VLOOKUP(G116,股价!C:D,2,FALSE) -> 124.8 | M116: =IFERROR(I116*L116,0) -> 37440
D117: =全班!$R$1 -> 46011 | E117: US | F117: 拼多多 | G117: PDD | H117: 持有 | I117: =SUMIFS($I$58:$I$113,$G$58:$G$113,G117) -> 34 | J117: =K117/I117 -> 833.80165 | K117: =SUMIFS($M$58:$M$113,$G$58:$G$113,G117) -> 28349.256 | L117: =VLOOKUP(G117,股价!C:D,2,FALSE) -> 854.178 | M117: =IFERROR(I117*L117,0) -> 29042.052
D118: =全班!$R$1 -> 46011 | E118: US | F118: 脸书 | G118: Meta | H118: 持有 | I118: =SUMIFS($I$58:$I$113,$G$58:$G$113,G118) -> 80 | J118: =K118/I118 -> 3626.998 | K118: =SUMIFS($M$58:$M$113,$G$58:$G$113,G118) -> 290159.84 | L118: =VLOOKUP(G118,股价!C:D,2,FALSE) -> 5138.406 | M118: =IFERROR(I118*L118,0) -> 411072.48
D119: =全班!$R$1 -> 46011 | E119: US | F119: 微软 | G119: MSFT | H119: 持有 | I119: =SUMIFS($I$58:$I$113,$G$58:$G$113,G119) -> 80 | J119: =K119/I119 -> 3546.7965 | K119: =SUMIFS($M$58:$M$113,$G$58:$G$113,G119) -> 283743.72 | L119: =VLOOKUP(G119,股价!C:D,2,FALSE) -> 3790.176 | M119: =IFERROR(I119*L119,0) -> 303214.08
D120: =全班!$R$1 -> 46011 | E120: US | F120: 阿斯麦 | G120: ASML | H120: 持有 | I120: =SUMIFS($I$58:$I$113,$G$58:$G$113,G120) -> 20 | J120: =K120/I120 -> 7076.628 | K120: =SUMIFS($M$58:$M$113,$G$58:$G$113,G120) -> 141532.56 | L120: =VLOOKUP(G120,股价!C:D,2,FALSE) -> 8236.956 | M120: =IFERROR(I120*L120,0) -> 164739.12
D121: =全班!$R$1 -> 46011 | E121: HK | F121: 腾讯集团 | G121: 00700 | H121: 持有 | I121: =SUMIFS($I$58:$I$113,$G$58:$G$113,G121) -> 100 | J121: =K121/I121 -> 629 | K121: =SUMIFS($M$58:$M$113,$G$58:$G$113,G121) -> 62900 | L121: =VLOOKUP(G121,股价!C:D,2,FALSE) -> 614 | M121: =IFERROR(I121*L121,0) -> 61400
D122: =全班!$R$1 -> 46011 | E122: HK | F122: 中芯国际 | G122: 00981 | H122: 持有 | I122: =SUMIFS($I$58:$I$113,$G$58:$G$113,G122) -> 600 | J122: =K122/I122 -> 75 | K122: =SUMIFS($M$58:$M$113,$G$58:$G$113,G122) -> 45000 | L122: =VLOOKUP(G122,股价!C:D,2,FALSE) -> 65.05 | M122: =IFERROR(I122*L122,0) -> 39030
D124: 市值结余 | M124: =SUM(M115:M123) -> 1058957.7
D125: 累计分红 | M125: =L138 -> 875.6904
D126: 现金结余 | M126: =M131-M113+M125 -> 2223.0404
D127: 结余总额 | M127: =M124+M126 -> 1061180.8
D128: 累计盈利 | M128: =M127-M131 -> 61180.772
...

Sheet 股价
A1: 序号 | B1: 企业 | C1: 股票代码 | D1: 46011 | E1: 美元/期权卖价 | F1: 美元/期权买价 | G1: 标记2 | H1: 46004 | I1: 45997 | J1: 45990 | K1: 45983 | L1: 45976 | M1: 45969 | N1: 45962 | O1: 45955 | P1: 45948 | Q1: 45941 | R1: 45934 | S1: 45927 | T1: 45920 | U1: 45913 | V1: 45906 | W1: 45899 | X1: 45892 | Y1: 45885 | Z1: 45878 | AA1: 45871 | AB1: 45864 | AC1: 45857 | AD1: 45850 | AE1: 45843 | AF1: 45836 | AG1: 45829 | AH1: 45822 | AI1: 45815 | AJ1: 45808 | AK1: 45801 | AL1: 45794 | AM1: 45787 | AN1: 45780 | AO1: 45773 | AP1: 45766 | AQ1: 45759 | AR1: 45752 | AS1: 45745 | AT1: 45738 | AU1: 45731 | AV1: 45724 | AW1: 45717 | AX1: 45710 | AY1: 45703 | AZ1: 45696 | BA1: 45689 | BB1: 45682 | BC1: 45675 | BD1: 45668 | BE1: 45661 | BF1: 周涨跌额 | BG1: 周涨跌率 | BH1: 汇率 | BJ1: 代码
A2: =ROW()-1 -> 1 | B2: 标普500ETF | C2: VOO | D2: =E2*BH2 -> 4894.968 | E2: 627.56 | BF2: =D2-H2 -> 4894.968 | BG2: =BF2/H2 -> #DIV/0! | BH2: 7.8
A3: =ROW()-1 -> 2 | B3: 威州能源 | C3: WEC | D3: =E3*BH3 -> 810.732 | E3: 103.94 | BF3: =D3-H3 -> 810.732 | BG3: =BF3/H3 -> #DIV/0! | BH3: 7.8
A4: =ROW()-1 -> 3 | B4: 杜克能源 | C4: DUK | D4: =E4*BH4 -> 901.368 | E4: 115.56 | BF4: =D4-H4 -> 901.368 | BG4: =BF4/H4 -> #DIV/0! | BH4: 7.8
A5: =ROW()-1 -> 4 | B5: 2倍做空特斯拉ETF | C5: TSDD | D5: =E5*BH5 -> 57.798 | E5: 7.41 | BF5: =D5-H5 -> 57.798 | BG5: =BF5/H5 -> #DIV/0! | BH5: 7.8
A6: =ROW()-1 -> 5 | B6: 小鹏汽车 | C6: XPEV | D6: =E6*BH6 -> 154.908 | E6: 19.86 | H6: 148.122 | BF6: =D6-H6 -> 6.786 | BG6: =BF6/H6 -> 0.045813586 | BH6: 7.8
A7: =ROW()-1 -> 6 | B7: Coinbase Global | C7: COIN | D7: =E7*BH7 -> 1911.936 | E7: 245.12 | H7: 2086.188 | I7: 2103.894 | J7: 2127.996 | K7: 1875.198 | BF7: =D7-H7 -> -174.252 | BG7: =BF7/H7 -> -0.083526509 | BH7: 7.8
A8: =ROW()-1 -> 7 | B8: 强生 | C8: JNJ | D8: =E8*BH8 -> 1609.686 | E8: 206.37 | H8: 1650.324 | I8: 1575.054 | J8: 1613.976 | K8: 1590.42 | BF8: =D8-H8 -> -40.638 | BG8: =BF8/H8 -> -0.024624256 | BH8: 7.8
A9: =ROW()-1 -> 8 | B9: 瑞辉 | C9: PFE | D9: =E9*BH9 -> 196.482 | E9: 25.19 | H9: 201.63 | I9: 203.034 | J9: 200.772 | K9: 195.312 | BF9: =D9-H9 -> -5.148 | BG9: =BF9/H9 -> -0.025531915 | BH9: 7.8
A10: =ROW()-1 -> 9 | B10: 英特尔 | C10: INTC | D10: =E10*BH10 -> 287.196 | E10: 36.82 | H10: 294.918 | I10: 322.998 | J10: 316.368 | K10: 269.1 | BF10: =D10-H10 -> -7.722 | BG10: =BF10/H10 -> -0.026183549 | BH10: 7.8
A11: =ROW()-1 -> 10 | B11: 特斯拉2倍做多ETF | C11: TSLL | D11: =E11*BH11 -> 172.458 | E11: 22.11 | H11: 158.184 | I11: 160.758 | J11: 144.456 | K11: 120.354 | L11: 129.324 | BF11: =D11-H11 -> 14.274 | BG11: =BF11/H11 -> 0.090236686 | BH11: 7.8
A12: =ROW()-1 -> 11 | B12: Nauticus Robotics | C12: KITT | D12: =E12*BH12 -> 6.7782 | E12: 0.869 | H12: 7.0902 | I12: 8.736 | J12: 6.5832 | K12: 6.825 | L12: 10.218 | M12: 11.076 | BF12: =D12-H12 -> -0.312 | BG12: =BF12/H12 -> -0.0440044 | BH12: 7.8
A13: =ROW()-1 -> 12 | B13: 可口可乐 | C13: KO | D13: =E13*BH13 -> 546.468 | E13: 70.06 | H13: 550.056 | I13: 546 | J13: 570.336 | K13: 569.01 | L13: 555.048 | M13: 550.29 | BF13: =D13-H13 -> -3.588 | BG13: =BF13/H13 -> -0.0065229722 | BH13: 7.8
A14: =ROW()-1 -> 13 | B14: Nebius Group N.V. | C14: NBIS | D14: =E14*BH14 -> 697.788 | E14: 89.46 | H14: 683.982 | I14: 764.712 | J14: 739.986 | K14: 649.428 | L14: 651.612 | M14: 867.984 | BF14: =D14-H14 -> 13.806 | BG14: =BF14/H14 -> 0.020184742 | BH14: 7.8
A15: =ROW()-1 -> 14 | B15: 甲骨文 | C15: ORCL | D15: =E15*BH15 -> 1497.366 | E15: 191.97 | H15: 1481.766 | I15: 1697.124 | J15: 1575.21 | K15: 1550.328 | L15: 1738.23 | M15: 1866.228 | BF15: =D15-H15 -> 15.6 | BG15: =BF15/H15 -> 0.010527978 | BH15: 7.8
A16: =ROW()-1 -> 15 | B16: 美国运通 | C16: AXP | D16: =E16*BH16 -> 2936.778 | E16: 376.51 | H16: 2983.968 | I16: 2888.73 | J16: 2849.106 | K16: 2752.542 | L16: 2786.004 | M16: 2874.612 | BF16: =D16-H16 -> -47.19 | BG16: =BF16/H16 -> -0.015814513 | BH16: 7.8
A17: =ROW()-1 -> 16 | B17: Circle Internet Group.Inc. | C17: CRCL | D17: =E17*BH17 -> 671.814 | E17: 86.13 | H17: 651.066 | I17: 667.836 | J17: 623.454 | K17: 556.374 | L17: 638.742 | M17: 804.492 | N17: 990.444 | O17: 1107.99 | P17: 986.622 | Q17: 1036.932 | R17: 1137.084 | S17: 990.522 | T17: 1124.292 | U17: 977.496 | V17: 893.568 | W17: 1029.444 | X17: 1053.312 | Y17: 1164.228 | BF17: =D17-H17 -> 20.748 | BG17: =BF17/H17 -> 0.031867737 | BH17: 7.8
A18: =ROW()-1 -> 17 | B18: 美国原油EETF | C18: USO | D18: =E18*BH18 -> 530.634 | E18: 68.03 | H18: 536.718 | I18: 560.976 | J18: 554.346 | K18: 540.54 | L18: 556.764 | M18: 555.828 | N18: 565.968 | O18: 570.804 | P18: 530.244 | BF18: =D18-H18 -> -6.084 | BG18: =BF18/H18 -> -0.011335562 | BH18: 7.8
A19: =ROW()-1 -> 18 | B19: 燃料电池能源 | C19: FCEL | D19: =E19*BH19 -> 65.052 | E19: 8.34 | H19: 68.328 | I19: 65.286 | J19: 52.338 | K19: 48.672 | L19: 54.912 | M19: 58.656 | N19: 69.81 | O19: 62.01 | P19: 66.144 | Q19: 72.228 | R19: 79.638 | S19: =7.9*7.8 -> 61.62 | BF19: =D19-H19 -> -3.276 | BG19: =BF19/H19 -> -0.047945205 | BH19: 7.8
A20: =ROW()-1 -> 19 | B20: Rocket Lab Corporation | C20: RKLB | D20: =E20*BH20 -> 550.056 | E20: 70.52 | H20: 479.622 | I20: 382.668 | J20: 328.692 | K20: 314.34 | L20: 355.212 | M20: 402.792 | N20: 491.244 | O20: 503.568 | P20: 516.906 | Q20: 501.228 | R20: 438.048 | S20: 360.828 | T20: 372.762 | U20: 416.052 | V20: 357.552 | BF20: =D20-H20 -> 70.434 | BG20: =BF20/H20 -> 0.14685315 | BH20: 7.8
A21: =ROW()-1 -> 20 | B21: Sofi Technogogies.Inc | C21: SOFI | D21: =E21*BH21 -> 212.472 | E21: 27.24 | H21: 212.784 | I21: 216.684 | J21: 231.816 | K21: 196.482 | L21: 216.996 | M21: 220.038 | N21: 231.504 | O21: 226.278 | P21: 207.012 | Q21: 204.282 | R21: 196.872 | S21: 218.244 | T21: 230.178 | U21: 207.09 | V21: 199.68 | W21: 199.212 | BF21: =D21-H21 -> -0.312 | BG21: =BF21/H21 -> -0.0014662757 | BH21: 7.8
A22: =ROW()-1 -> 21 | B22: 谷歌-C | C22: GOOG | D22: =E22*BH22 -> 2407.158 | E22: 308.61 | H22: 2422.056 | I22: 2518.62 | J22: 2496.936 | K22: 2337.27 | L22: 2160.444 | M22: 2181.66 | N22: 2198.196 | O22: 2031.978 | P22: 1979.562 | Q22: 1852.422 | R22: 1922.31 | S22: 1928.004 | T22: 1990.872 | U22: 1882.764 | V22: 1834.326 | W22: 1665.534 | BF22: =D22-H22 -> -14.898 | BG22: =BF22/H22 -> -0.0061509726 | BH22: 7.8
A23: =ROW()-1 -> 22 | B23: Him&Hers Health.Inc | C23: HIMS | D23: =E23*BH23 -> 277.368 | E23: 35.56 | H23: 290.238 | I23: 305.76 | J23: 310.128 | K23: 270.738 | L23: 288.444 | M23: 320.034 | N23: 354.588 | O23: 380.484 | P23: 388.284 | Q23: 420.81 | R23: 409.812 | S23: 455.52 | T23: 450.996 | U23: 432.9 | V23: 377.598 | W23: 330.33 | BF23: =D23-H23 -> -12.87 | BG23: =BF23/H23 -> -0.044342919 | BH23: 7.8
A24: =ROW()-1 -> 23 | B24: Bitmine Immersion Technologies.Inc | C24: BMNR | D24: =E24*BH24 -> 244.608 | E24: 31.36 | H24: 271.908 | I24: 265.668 | J24: 258.336 | K24: 202.8 | L24: 268.32 | M24: 313.794 | N24: 363.87 | O24: 393.198 | P24: 388.83 | Q24: 409.266 | R24: 441.87 | S24: 393.9 | T24: 478.062 | U24: 429.702 | V24: 327.912 | W24: 340.236 | X24: 417.222 | BF24: =D24-H24 -> -27.3 | BG24: =BF24/H24 -> -0.10040161 | BH24: 7.8
A25: =ROW()-1 -> 24 | B25: 联合健康 | C25: UNH | D25: =E25*BH25 -> 2553.876 | E25: 327.42 | H25: 2666.352 | I25: 2581.098 | J25: 2572.206 | K25: 2495.766 | L25: 2510.508 | M25: 2528.838 | N25: 2664.168 | O25: 2827.5 | P25: 2781.48 | Q25: 2765.1 | R25: 2809.56 | S25: 2683.824 | T25: 2626.182 | U25: 2749.578 | V25: 2460.042 | W25: 2416.986 | X25: 2397.876 | Y25: 2371.278 | BF25: =D25-H25 -> -112.476 | BG25: =BF25/H25 -> -0.042183478 | BH25: 7.8
A26: =ROW()-1 -> 25 | B26: 多邻国 | C26: DUOL | D26: =E26*BH26 -> 1450.488 | E26: 185.96 | H26: 1530.984 | I26: 1558.05 | J26: 1492.998 | K26: 1347.684 | L26: 1443.546 | M26: 1569.438 | N26: 2110.992 | O26: 2433.6 | P26: 2527.356 | Q26: 2535 | R26: 2516.514 | S26: 2545.842 | T26: 2269.02 | U26: 2401.698 | V26: 2115.204 | W26: 2323.308 | X26: 2588.586 | Y26: 2550.054 | Z26: 2888.652 | AA26: 2644.122 | AB26: 2839.902 | AC26: 2889.822 | BF26: =D26-H26 -> -80.496 | BG26: =BF26/H26 -> -0.05257795 | BH26: 7.8
A27: =ROW()-1 -> 26 | B27: 阿里巴巴 | C27: BABA | D27: =E27*BH27 -> 1168.362 | E27: 149.79 | H27: 1214.304 | I27: 1234.896 | J27: 1226.94 | K27: 1192.854 | L27: 1199.64 | M27: 1297.452 | N27: 1329.354 | O27: 1362.66 | P27: 1302.99 | Q27: 1240.278 | R27: 1466.634 | S27: 1340.898 | T27: 1269.918 | U27: 1209.468 | V27: 1057.524 | W27: 1053 | X27: 958.932 | Y27: 945.828 | Z27: 938.808 | AA27: 913.146 | AB27: 936.234 | AC27: 937.794 | AD27: 1286.376 | AE27: 847.86 | AF27: 889.824 | AG27: 881.478 | AH27: 880.386 | AI27: 931.164 | AJ27: 887.952 | AK27: 941.694 | AL27: 962.988 | AM27: 977.574 | AN27: 980.928 | AO27: 938.184 | AP27: 849.186 | AQ27: 840.294 | AR27: 909.012 | AS27: 1032.954 | AT27: 1054.092 | AU27: 1100.58 | AV27: 1096.836 | AW27: 1033.578 | AX27: 1121.25 | AY27: 972.894 | AZ27: 807.378 | BA27: 770.952 | BB27: 695.292 | BC27: 663.936 | BD27: 628.134 | BE27: 667.212 | BF27: =D27-H27 -> -45.942 | BG27: =BF27/H27 -> -0.037834018 | BH27: 7.8
A28: =ROW()-1 -> 27 | B28: sharplink gaming | C28: SBET | D28: =E28*BH28 -> 76.518 | E28: 9.81 | H28: 81.978 | I28: 83.616 | J28: 82.836 | K28: 74.256 | L28: 84.942 | M28: 93.288 | N28: 107.952 | O28: 108.576 | P28: 111.852 | Q28: 119.496 | R28: 141.804 | S28: 124.8 | T28: 135.174 | U28: 138.06 | V28: 116.532 | W28: 138.996 | X28: 162.786 | Y28: 154.83 | Z28: 186.576 | AA28: 133.692 | AB28: 171.522 | AC28: 226.044 | AD28: 168.87 | BF28: =D28-H28 -> -5.46 | BG28: =BF28/H28 -> -0.066603235 | BH28: 7.8
A29: =ROW()-1 -> 28 | B29: Robinhood Market | C29: HOOD | D29: =E29*BH29 -> 946.53 | E29: 121.35 | H29: 932.1 | I29: 1029.21 | J29: 1002.222 | K29: 836.94 | L29: 955.5 | M29: 1016.808 | N29: 1144.884 | O29: 1090.362 | P29: 1013.298 | Q29: 1083.888 | R29: 1159.626 | S29: 949.884 | T29: 973.284 | U29: 897.234 | V29: 789.75 | W29: 811.434 | X29: 852.696 | Y29: 890.526 | Z29: 894.114 | AA29: 779.22 | AB29: 817.83 | AC29: 855.972 | AD29: 767.052 | AE29: 736.32 | AF29: 647.634 | AG29: 612.3 | AH29: 566.28 | AI29: 584.064 | AJ29: 515.97 | AK29: 492.726 | AL29: 481.728 | AM29: 426.27 | AN29: 379.002 | AO29: 385.71 | AP29: 321.204 | AQ29: 340.704 | AR29: 269.178 | AS29: 326.976 | AT29: 346.008 | BF29: =D29-H29 -> 14.43 | BG29: =BF29/H29 -> 0.015481172 | BH29: 7.8
A30: =ROW()-1 -> 29 | B30: 新思科技 | C30: SNPS | D30: =E30*BH30 -> 3617.094 | E30: 463.73 | H30: 3533.01 | I30: 3640.728 | J30: 3260.478 | K30: 3029.208 | L30: 3040.674 | M30: 3068.754 | N30: 3539.796 | O30: 3620.604 | P30: 3491.592 | Q30: 3423.576 | R30: 3659.526 | S30: 3804.528 | T30: 3864.9 | U30: 3318.51 | V30: 4665.492 | W30: 4707.456 | X30: 4730.856 | Y30: 4819.698 | Z30: 4831.476 | AA30: 4825.47 | AB30: 4692.09 | AC30: 4561.128 | AD30: 4362.384 | AE30: 4280.172 | AF30: 3920.514 | AG30: 3670.134 | AH30: 3735.108 | AI30: 3790.8 | AJ30: 3619.044 | AK30: 3891.03 | AL30: 4012.554 | AM30: 3766.62 | AN30: 3683.784 | AO30: 3483.636 | AP30: 3223.896 | AQ30: 3285.438 | AR30: 3027.414 | AS30: 3416.01 | AT30: 3499.08 | AU30: 3480.594 | AV30: 3516.864 | AW30: 3566.784 | AX30: 3703.752 | BF30: =D30-H30 -> 84.084 | BG30: =BF30/H30 -> 0.023799536 | BH30: 7.8
A31: =ROW()-1 -> 30 | B31: Palantir Technologies | C31: PLTR | D31: =E31*BH31 -> 1508.364 | E31: 193.38 | H31: 1431.846 | I31: 1417.728 | J31: 1313.91 | K31: 1207.83 | L31: 1357.278 | M31: 1387.854 | N31: 1563.666 | O31: 1440.114 | P31: 1389.57 | Q31: 1368.432 | R31: 1349.946 | S31: 1385.046 | T31: 1422.642 | U31: 1337.154 | V31: 1194.258 | W31: 1222.338 | X31: 1238.172 | Y31: 1381.926 | Z31: 1458.288 | AA31: 1203.306 | AB31: 1238.64 | AC31: 1197.456 | AD31: 1108.38 | AE31: 1048.008 | AF31: 1019.772 | AG31: 1070.94 | AH31: 1071.72 | AI31: 996.216 | AJ31: 1027.884 | AK31: 961.818 | AL31: 1010.256 | AM31: 914.94 | AN31: 969.384 | AO31: 879.684 | AP31: 731.484 | AQ31: 690.69 | AR31: 577.278 | AS31: 669.63 | AT31: 709.488 | AU31: 672.672 | AV31: 662.298 | AW31: 662.376 | AX31: 790.53 | BF31: =D31-H31 -> 76.518 | BG31: =BF31/H31 -> 0.053440105 | BH31: 7.8
A32: =ROW()-1 -> 31 | B32: Tempus Ai | C32: TEM | D32: =E32*BH32 -> 502.788 | E32: 64.46 | H32: 550.758 | I32: 597.948 | J32: 607.854 | K32: 548.262 | L32: 534.144 | M32: 558.168 | N32: 700.83 | O32: 695.994 | P32: 684.684 | Q32: 751.842 | R32: 714.948 | S32: 612.144 | T32: 688.272 | U32: 673.764 | V32: 621.036 | W32: 591.708 | X32: 628.056 | Y32: 575.484 | Z32: 474.786 | AA32: 428.142 | AB32: 503.022 | AC32: 475.644 | AD32: 443.664 | AE32: 475.566 | AF32: 518.856 | AG32: 532.818 | AH32: 555.984 | AI32: 484.146 | AJ32: 430.404 | AK32: 487.968 | AL32: 510.822 | AM32: 478.686 | AN32: 445.068 | AO32: 412.62 | AP32: 315.51 | AQ32: 328.536 | AR32: 332.124 | AS32: 373.074 | AT32: 400.53 | AU32: 367.926 | AV32: 382.98 | AW32: 438.204 | AX32: 531.102 | AY32: 697.632 | AZ32: 537.888 | BF32: =D32-H32 -> -47.97 | BG32: =BF32/H32 -> -0.087098145 | BH32: 7.8
A33: =ROW()-1 -> 32 | B33: 摩根士丹利 | C33: MS | D33: =E33*BH33 -> 1380.444 | E33: 176.98 | H33: 1391.598 | I33: 1376.778 | J33: 1323.348 | K33: 1233.726 | L33: 1278.108 | M33: 1266.408 | N33: 1279.2 | O33: 1278.108 | P33: 1237.626 | Q33: 1184.508 | R33: 1229.202 | S33: 1248.858 | T33: 1247.298 | U33: 1219.842 | V33: 1155.102 | W33: 1173.744 | X33: 1154.556 | Y33: 1128.114 | Z33: 1116.804 | AA33: 1084.902 | AB33: 1115.478 | AC33: 1098.474 | AD33: 1109.784 | AE33: 1124.292 | AF33: 1097.382 | AG33: 1035.138 | AH33: 1010.022 | AI33: 1028.196 | AJ33: 998.634 | AK33: 983.346 | AL33: 1031.004 | AM33: 949.26 | AN33: 937.716 | AO33: 904.878 | AP33: 851.604 | AQ33: 843.336 | AR33: 778.674 | AS33: 899.574 | AT33: 937.092 | AU33: 899.652 | AV33: 930.462 | AW33: 1038.258 | AX33: 1027.182 | AY33: 1083.81 | AZ33: 1091.844 | BA33: 1079.754 | BB33: 1074.996 | BF33: =D33-H33 -> -11.154 | BG33: =BF33/H33 -> -0.0080152458 | BH33: 7.8
A34: =ROW()-1 -> 33 | B34: applovin corporation | C34: APP | D34: =E34*BH34 -> 5626.686 | E34: 721.37 | H34: 5231.226 | I34: 5397.132 | J34: 4675.944 | K34: 4058.028 | L34: 4350.06 | M34: 4835.454 | N34: 4971.174 | O34: 4836 | P34: 4674.618 | Q34: 4445.142 | R34: 5325.528 | S34: 5224.908 | T34: 5066.802 | U34: 4539.6 | V34: 3823.872 | W34: 3733.002 | X34: 3445.104 | Y34: 3421.704 | Z34: 3556.644 | AA34: 2957.526 | AB34: 2840.292 | AC34: 2842.788 | AD34: 2613.78 | AE34: 2664.792 | AF34: 2603.484 | AG34: 2532.66 | AH34: 2843.022 | AI34: 3259.542 | AJ34: 3065.4 | AK34: 2763.462 | AL34: 2826.252 | AM34: 2562.612 | AN34: 2399.124 | AO34: 2159.274 | AP34: 1858.116 | AQ34: 1949.61 | AR34: 1711.086 | AS34: 2124.564 | AT34: 2449.434 | AU34: 2284.542 | AV34: 2109.744 | AW34: 2540.772 | AX34: 3239.418 | AY34: 3979.014 | AZ34: 2930.616 | BA34: 2882.802 | BB34: 2832.18 | BC34: 2670.252 | BD34: 2484.144 | BE34: 2735.07 | BF34: =D34-H34 -> 395.46 | BG34: =BF34/H34 -> 0.075596046 | BH34: 7.8
A35: =ROW()-1 -> 34 | B35: 美团 | C35: MPNGY | D35: =E35*BH35 -> 201.474 | E35: 25.83 | H35: 202.332 | I35: 198.354 | J35: 201.24 | K35: 193.752 | L35: 198.198 | M35: 204.906 | N35: 205.686 | O35: 202.332 | P35: 195.78 | Q35: 188.76 | R35: 211.692 | S35: 202.8 | T35: 212.082 | U35: 191.412 | V35: 205.14 | W35: 207.48 | X35: 241.176 | Y35: 242.502 | Z35: 241.176 | AA35: 240.24 | AB35: 257.79 | AC35: 265.824 | AD35: 236.964 | AE35: 243.126 | AF35: 257.322 | AG35: 253.5 | AH35: 272.22 | AI35: 285.09 | AJ35: 269.646 | AK35: 269.646 | AL35: 260.676 | AM35: 282.204 | AN35: 270.114 | AO35: 258.804 | AP35: 267.072 | AQ35: 291.72 | AR35: 289.458 | AS35: 317.85 | AT35: 318.396 | AU35: 351.78 | AV35: 364.494 | AW35: 326.352 | AX35: 323.154 | AY35: 337.662 | AZ35: 307.32 | BA35: 297.57 | BB35: 305.604 | BC35: 302.328 | BD35: 275.808 | BE35: 309.66 | BF35: =D35-H35 -> -0.858 | BG35: =BF35/H35 -> -0.0042405551 | BH35: 7.8
A36: =ROW()-1 -> 35 | B36: 赛富时 | C36: CRM | D36: =E36*BH36 -> 2027.298 | E36: 259.91 | H36: 2045.394 | I36: 2032.446 | J36: 1798.212 | K36: 1771.458 | L36: 1900.548 | M36: 1871.064 | N36: 2031.198 | O36: 1987.674 | P36: 1896.024 | Q36: 1885.104 | R36: 1874.808 | S36: 1898.754 | T36: 1927.302 | U36: 1893.528 | V36: 1955.928 | W36: 1998.75 | X36: 1936.662 | Y36: 1891.032 | Z36: 1875.978 | AA36: 1955.772 | AB36: 2099.058 | AC36: 2046.564 | AD36: 2012.946 | AE36: 2122.77 | AF36: 2132.676 | AG36: 2032.914 | AH36: 2015.52 | AI36: 2141.178 | AJ36: 2069.886 | AK36: 2130.414 | AL36: 2270.97 | AM36: 2148.276 | AN36: 2145.624 | AO36: 2089.23 | AP36: 1928.628 | AQ36: 1989 | AR36: 1877.928 | AS36: 2105.766 | AT36: 2188.836 | AU36: 2179.32 | AV36: 2206.542 | AW36: 2323.23 | AX36: 2416.44 | AY36: 2547.012 | AZ36: 2541.474 | BA36: 2665.26 | BB36: 2604.264 | BC36: 2531.568 | BD36: 2479.23 | BE36: 2596.62 | BF36: =D36-H36 -> -18.096 | BG36: =BF36/H36 -> -0.0088471952 | BH36: 7.8
A37: =ROW()-1 -> 36 | B37: 麦当劳 | C37: MCD | D37: =E37*BH37 -> 2463.552 | E37: 315.84 | H37: 2470.416 | I37: 2427.594 | J37: 2432.196 | K37: 2412.93 | L37: 2394.834 | M37: 2337.348 | N37: 2327.754 | O37: 2385.162 | P37: 2403.102 | Q37: 2316.678 | R37: 2347.644 | S37: 2380.872 | T37: 2358.564 | U37: 2382.12 | V37: 2452.164 | W37: 2445.612 | X37: 2449.746 | Y37: 2409.654 | Z37: 2382.51 | AA37: 2362.542 | AB37: 2328.066 | AC37: 2317.146 | AD37: 2339.298 | AE37: 2293.824 | AF37: 2274.09 | AG37: 2242.188 | AH37: 2354.898 | AI37: 2397.408 | AJ37: 2448.03 | AK37: 2453.646 | AL37: 2485.158 | AM37: 2446.704 | AN37: 2433.288 | AO37: 2470.572 | AP37: 2428.14 | AQ37: 2417.22 | AR37: 2340.858 | AS37: 2395.302 | AT37: 2382.432 | AU37: 2338.674 | AV37: 2506.062 | AW37: 2404.974 | AX37: 2377.518 | AY37: 2406.69 | AZ37: 2295.54 | BA37: 2251.86 | BB37: 2226.588 | BC37: 2191.41 | BD37: 2202.018 | BE37: 2299.284 | BF37: =D37-H37 -> -6.864 | BG37: =BF37/H37 -> -0.0027784794 | BH37: 7.8
A38: =ROW()-1 -> 37 | B38: 花旗银行 | C38: C | D38: =E38*BH38 -> 895.908 | E38: 114.86 | H38: 872.04 | I38: 849.264 | J38: 808.08 | K38: 769.86 | L38: 782.34 | M38: 786.162 | N38: 789.594 | O38: 770.484 | P38: 757.146 | Q38: 732.654 | R38: 762.372 | S38: 806.676 | T38: 800.904 | U38: 775.632 | V38: 744.12 | W38: 753.246 | X38: 743.028 | Y38: 730.782 | Z38: 723.294 | AA38: 716.274 | AB38: 749.346 | AC38: 728.91 | AD38: 676.494 | AE38: 692.016 | AF38: 658.164 | AG38: 611.91 | AH38: 595.608 | AI38: 610.428 | AJ38: 587.496 | AK38: 570.102 | AL38: 590.616 | AM38: 557.31 | AN38: 550.602 | AO38: 533.754 | AP38: 493.35 | AQ38: 480.792 | AR38: 453.414 | AS38: 548.574 | AT38: 561.444 | AU38: 536.484 | AV38: 549.588 | AW38: 623.61 | AX38: 621.27 | AY38: 659.958 | AZ38: 637.416 | BA38: 635.154 | BB38: 635.544 | BC38: 623.922 | BD38: 556.92 | BE38: 553.8 | BF38: =D38-H38 -> 23.868 | BG38: =BF38/H38 -> 0.027370304 | BH38: 7.8
A39: =ROW()-1 -> 38 | B39: 高盛 | C39: GS | D39: =E39*BH39 -> 6969.144 | E39: 893.48 | H39: 6926.088 | I39: 6665.568 | J39: 6443.112 | K39: 6037.434 | L39: 6169.098 | M39: 6133.452 | N39: 6157.086 | O39: 6114.264 | P39: 5856.006 | Q39: 5962.008 | R39: 6161.844 | S39: 6259.578 | T39: 6279 | U39: 6084.468 | V39: 5758.038 | W39: 5812.95 | X39: 5786.742 | Y39: 5699.616 | Z39: 5625.906 | AA39: 5534.646 | AB39: 5686.044 | AC39: 5524.428 | AD39: 5498.61 | AE39: 5644.704 | AF39: 5388.318 | AG39: 4998.24 | AH39: 4785.612 | AI39: 4789.2 | AJ39: 4683.51 | AK39: 4668.612 | AL39: 4828.434 | AM39: 4423.38 | AN39: 4415.58 | AO39: 4249.908 | AP39: 3974.022 | AQ39: 3856.632 | AR39: 3672.318 | AS39: 4236.336 | AT39: 4408.092 | AU39: 4222.998 | AV39: 4365.426 | AW39: 4853.862 | AX39: 4879.68 | AY39: 5152.29 | AZ39: 5116.02 | BA39: 4995.12 | BB39: 4967.82 | BC39: 4882.332 | BD39: 4368 | BE39: 4525.014 | BF39: =D39-H39 -> 43.056 | BG39: =BF39/H39 -> 0.0062164962 | BH39: 7.8
A40: =ROW()-1 -> 39 | B40: 伯克希尔B | C40: BRK.B | D40: =E40*BH40 -> 3857.334 | E40: 494.53 | H40: 3896.256 | I40: 3933.852 | J40: 4007.718 | K40: 3931.512 | L40: 3969.732 | M40: 3892.668 | N40: 3724.812 | O40: 3838.38 | P40: 3840.876 | Q40: 3815.214 | R40: 3890.25 | S40: 3900.234 | T40: 3844.23 | U40: 3851.172 | V40: 3898.206 | W40: 3923.244 | X40: 3814.2 | Y40: 3722.16 | Z40: 3630.12 | AA40: 3688.152 | AB40: 3775.746 | AC40: 3695.64 | AD40: 3711.708 | AE40: 3783 | AF40: 3788.304 | AG40: 3781.83 | AH40: 3802.812 | AI40: 3849.534 | AJ40: 3930.888 | AK40: 3926.988 | AL40: 4011.618 | AM40: 4007.172 | AN40: 4210.44 | AO40: 4141.488 | AP40: 4042.038 | AQ40: 4088.058 | AR40: 3849.612 | AS40: 4105.218 | AT40: 4070.898 | AU40: 4013.88 | AV40: 3865.836 | AW40: 4007.874 | AX40: 3734.172 | AY40: 3740.802 | AZ40: 3687.372 | BA40: 3655.626 | BB40: 3612.882 | BC40: 3650.01 | BD40: 3452.748 | BE40: 3537.768 | BF40: =D40-H40 -> -38.922 | BG40: =BF40/H40 -> -0.00998959 | BH40: 7.8
A41: =ROW()-1 -> 40 | B41: 携程 | C41: TCOM | D41: =E41*BH41 -> 563.316 | E41: 72.22 | H41: 552.24 | I41: 559.65 | J41: 545.376 | K41: 544.83 | L41: 561.834 | M41: 548.106 | N41: 551.07 | O41: 567.762 | P41: 547.092 | Q41: 546.624 | R41: 571.896 | S41: 592.176 | T41: 612.456 | U41: 576.186 | V41: 567.762 | W41: 575.25 | X41: 506.376 | Y41: 486.486 | Z41: 458.64 | AA41: 472.914 | AB41: 502.554 | AC41: 496.158 | AD41: 482.976 | AE41: 458.172 | AF41: 457.626 | AG41: 435.63 | AH41: 467.844 | AI41: 472.758 | AJ41: 488.67 | AK41: 486.174 | AL41: 506.766 | AM41: 479.31 | AN41: 469.326 | AO41: 448.656 | AP41: 427.83 | AQ41: 426.894 | AR41: 435.942 | AS41: 488.904 | AT41: 500.994 | AU41: 483.834 | AV41: 497.874 | AW41: 442.104 | AX41: 522.756 | AY41: 540.15 | AZ41: 539.916 | BA41: 547.326 | BB41: 557.856 | BC41: 523.848 | BD41: 492.57 | BE41: 527.28 | BF41: =D41-H41 -> 11.076 | BG41: =BF41/H41 -> 0.020056497 | BH41: 7.8
A42: =ROW()-1 -> 41 | B42: 沃尔玛 | C42: WMT | D42: =E42*BH42 -> 892.008 | E42: 114.36 | H42: 910.26 | I42: 897.858 | J42: 861.978 | K42: 821.496 | L42: 799.344 | M42: 800.202 | N42: 789.204 | O42: 828.126 | P42: 840.294 | Q42: 794.352 | R42: 796.146 | S42: 804.648 | T42: 798.174 | U42: 807.222 | V42: 783.978 | W42: 756.444 | X42: 755.274 | Y42: 780 | Z42: 809.094 | AA42: 768.222 | AB42: 760.266 | AC42: 741.39 | AD42: 736.32 | AE42: 767.208 | AF42: 758.706 | AG42: 749.736 | AH42: 736.632 | AI42: 760.266 | AJ42: 770.016 | AK42: 751.452 | AL42: 766.272 | AM42: 754.416 | AN42: 770.25 | AO42: 741.702 | AP42: 727.116 | AQ42: 723.84 | AR42: 648.882 | AS42: 664.17 | AT42: 670.644 | AU42: 665.73 | AV42: 715.416 | AW42: 769.158 | AX42: 739.284 | AY42: 811.512 | AZ42: 788.97 | BA42: 765.648 | BB42: 739.128 | BC42: 717.132 | BD42: 725.4 | BE42: 708.084 | BF42: =D42-H42 -> -18.252 | BG42: =BF42/H42 -> -0.020051414 | BH42: 7.8
A43: =ROW()-1 -> 42 | B43: 贝壳 | C43: BEKE | D43: =E43*BH43 -> 124.8 | E43: 16 | H43: 134.784 | I43: 134.004 | J43: 134.394 | K43: 136.5 | L43: 131.43 | M43: 121.68 | N43: 132.99 | O43: 139.23 | P43: 142.506 | Q43: 137.67 | R43: 145.86 | S43: 151.71 | T43: 153.972 | U43: 156.546 | V43: 148.122 | W43: 137.124 | X43: 144.534 | Y43: 142.974 | Z43: 136.968 | AA43: 141.96 | AB43: 152.178 | AC43: 146.562 | AD43: 144.144 | AE43: 137.826 | AF43: 144.612 | AG43: 140.4 | AH43: 144.066 | AI43: 146.562 | AJ43: 143.988 | AK43: 143.754 | AL43: 149.994 | AM43: 150.54 | AN43: 162.162 | AO43: 166.92 | AP43: 148.434 | AQ43: 143.832 | AR43: 152.568 | AS43: 160.602 | AT43: 160.992 | AU43: 190.242 | AV43: 189.228 | AW43: 173.706 | AX43: 163.02 | AY43: 159.9 | AZ43: 139.776 | BA43: 135.954 | BB43: 133.458 | BC43: 133.38 | BD43: 127.92 | BE43: 140.634 | BF43: =D43-H43 -> -9.984 | BG43: =BF43/H43 -> -0.074074074 | BH43: 7.8
A44: =ROW()-1 -> 43 | B44: 美国超微公司 | C44: AMD | D44: =E44*BH44 -> 1664.754 | E44: 213.43 | H44: 1644.084 | I44: 1700.166 | J44: 1696.734 | K44: 1589.484 | L44: 1925.118 | M44: 1821.612 | N44: 1997.736 | O44: 1972.776 | P44: 1818.024 | Q44: 1676.22 | R44: 1284.426 | S44: 1243.788 | T44: 1227.642 | U44: 1236.846 | V44: 1178.892 | W44: 1268.514 | X44: 1308.528 | Y44: 1384.578 | Z44: 1347.528 | AA44: 1339.26 | AB44: 1298.466 | AC44: 1224.522 | AD44: 1142.076 | AE44: 1075.698 | AF44: 1121.718 | AG44: 1000.272 | AH44: 906.048 | AI44: 906.282 | AJ44: 863.694 | AK44: 860.418 | AL44: 913.926 | AM44: 802.152 | AN44: 770.64 | AO44: 753.87 | AP44: 682.5 | AQ44: 728.52 | AR44: 668.928 | AS44: 805.116 | AT44: 830.232 | AU44: 787.566 | AV44: 782.418 | AW44: 778.908 | AX44: 864.552 | AY44: 882.18 | AZ44: 838.968 | BA44: 904.41 | BB44: 958.152 | BC44: 947.388 | BD44: 905.112 | BE44: 977.886 | BF44: =D44-H44 -> 20.67 | BG44: =BF44/H44 -> 0.01257235 | BH44: 7.8
A45: =ROW()-1 -> 44 | B45: 吉利汽车 | C45: GELYY | D45: =E45*BH45 -> 341.172 | E45: 43.74 | H45: 350.142 | I45: 347.568 | J45: 343.044 | K45: 343.044 | L45: 353.496 | M45: 354.744 | N45: 370.578 | O45: 390.39 | P45: 381.498 | Q45: 365.04 | R45: 387.582 | S45: 366.678 | T45: 379.314 | U45: 368.16 | V45: 374.79 | W45: 396.162 | X45: 406.848 | Y45: 381.03 | Z45: 367.848 | AA45: 347.49 | AB45: 386.334 | AC45: 376.428 | AD45: 347.88 | AE45: 328.536 | AF45: 317.382 | AG45: 318.24 | AH45: 322.296 | AI45: 357.786 | AJ45: 346.242 | AK45: 400.686 | AL45: 393.744 | AM45: 366.99 | AN45: 337.974 | AO45: 323.076 | AP45: 306.774 | AQ45: 324.09 | AR45: 310.752 | AS45: 330.486 | AT45: 345.072 | AU45: 357.006 | AV45: 356.07 | AW45: 353.808 | AX45: 349.284 | AY45: 340.938 | AZ45: 347.178 | BA45: 287.196 | BB45: 289.77 | BC45: 287.976 | BD45: 274.17 | BE45: 285.558 | BF45: =D45-H45 -> -8.97 | BG45: =BF45/H45 -> -0.025618178 | BH45: 7.8
... A61: =ROW()-1 -> 60 | B61: 苹果 | C61: AAPL | D61: =E61*BH61 -> 2134.626 | E61: 273.67 | H61: 2170.584 | I61: 2174.484 | J61: 2175.03 | K61: 2117.622 | L61: 2124.798 | M61: 2094.066 | N61: 2108.886 | O61: 2049.996 | P61: 1967.862 | Q61: 1913.106 | R61: 2012.556 | S61: 1992.588 | T61: 1914.9 | U61: 1825.746 | V61: 1869.582 | W61: 1810.692 | X61: 1776.528 | Y61: 1806.402 | Z61: 1788.93 | AA61: 1578.564 | AB61: 1668.264 | AC61: 1647.204 | AD61: 1647.048 | AE61: 1665.69 | AF61: 1568.424 | AG61: 1567.8 | AH61: 1532.31 | AI61: 1590.576 | AJ61: 1566.63 | AK61: 1523.106 | AL61: 1647.828 | AM61: 1548.534 | AN61: 1601.73 | AO61: 1632.384 | AP61: 1536.444 | AQ61: 1545.57 | AR61: 1469.364 | AS61: 1699.62 | AT61: 1702.506 | AU61: 1665.222 | AV61: 1864.746 | AW61: 1886.352 | AX61: 1915.29 | AY61: 1907.88 | AZ61: 1775.514 | BA61: 1840.8 | BB61: 1737.684 | BC61: 1793.844 | BD61: 1847.43 | BE61: 1898.208 | BF61: =D61-H61 -> -35.958 | BG61: =BF61/H61 -> -0.016566049 | BH61: 7.8
A62: =ROW()-1 -> 61 | B62: 上善黄金 | C62: 01939 | D62: 1.22 | H62: 1.37 | I62: 1.47 | J62: 5.1 | BF62: =D62-H62 -> -0.15 | BG62: =BF62/H62 -> -0.10948905 | BH62: 7.8 | BJ62: 01939 | BK62: =VLOOKUP(BJ62,[1]香港主板20251220!$A:$D,4,FALSE) -> 1.22
A63: =ROW()-1 -> 62 | B63: 赛力斯 | C63: 09927 | D63: 108.2 | H63: 111.6 | I63: 114.6 | J63: 115 | BF63: =D63-H63 -> -3.4 | BG63: =BF63/H63 -> -0.03046595 | BH63: 7.8 | BJ63: 09927 | BK63: =VLOOKUP(BJ63,[1]香港主板20251220!$A:$D,4,FALSE) -> 108.2
A64: =ROW()-1 -> 63 | B64: 周六福 | C64: 06168 | D64: 36.62 | H64: 39.24 | I64: 39.08 | J64: 41.74 | BF64: =D64-H64 -> -2.62 | BG64: =BF64/H64 -> -0.066768603 | BH64: 7.8 | BJ64: 06168 | BK64: =VLOOKUP(BJ64,[1]香港主板20251220!$A:$D,4,FALSE) -> 36.62
A65: =ROW()-1 -> 64 | B65: 东方电气 | C65: 01072 | D65: 24 | H65: 24.9 | I65: 21.32 | J65: 21.4 | BF65: =D65-H65 -> -0.9 | BG65: =BF65/H65 -> -0.036144578 | BH65: 7.8 | BJ65: 01072 | BK65: =VLOOKUP(BJ65,[1]香港主板20251220!$A:$D,4,FALSE) -> 24
A66: =ROW()-1 -> 65 | B66: 中远海控 | C66: 01919 | D66: 13.53 | H66: 13.68 | I66: 13.88 | J66: 13.25 | BF66: =D66-H66 -> -0.15 | BG66: =BF66/H66 -> -0.010964912 | BH66: 7.8 | BJ66: 01919 | BK66: =VLOOKUP(BJ66,[1]香港主板20251220!$A:$D,4,FALSE) -> 13.53
A67: =ROW()-1 -> 66 | B67: 新鸿基地产 | C67: 00016 | D67: 95.5 | H67: 99.25 | I67: 98.6 | J67: 98.6 | K67: 96.95 | BF67: =D67-H67 -> -3.75 | BG67: =BF67/H67 -> -0.037783375 | BH67: 7.8 | BJ67: 00016 | BK67: =VLOOKUP(BJ67,[1]香港主板20251220!$A:$D,4,FALSE) -> 95.5
A68: =ROW()-1 -> 67 | B68: 港铁 | C68: 00066 | D68: 30.02 | H68: 30.86 | I68: 31.06 | J68: 30.88 | K68: 30.34 | BF68: =D68-H68 -> -0.84 | BG68: =BF68/H68 -> -0.027219702 | BH68: 7.8 | BJ68: 00066 | BK68: =VLOOKUP(BJ68,[1]香港主板20251220!$A:$D,4,FALSE) -> 30.02
A69: =ROW()-1 -> 68 | B69: 中电控股 | C69: 00002 | D69: 68.85 | H69: 67.8 | I69: 68.25 | J69: 68 | K69: 67.95 | BF69: =D69-H69 -> 1.05 | BG69: =BF69/H69 -> 0.015486726 | BH69: 7.8 | BJ69: 00002 | BK69: =VLOOKUP(BJ69,[1]香港主板20251220!$A:$D,4,FALSE) -> 68.85
A70: =ROW()-1 -> 69 | B70: 阿里巴巴 | C70: 09988 | D70: 145.3 | H70: 154.1 | I70: 155 | J70: 151.5 | K70: 147.6 | L70: 154.9 | M70: 160.1 | N70: 165.1 | O70: 168.3 | P70: 154.4 | Q70: 165.4 | R70: 185.1 | S70: 166.5 | T70: 159.1 | U70: 151.1 | V70: 131.8 | W70: 115.7 | BF70: =D70-H70 -> -8.8 | BG70: =BF70/H70 -> -0.057105775 | BH70: 7.8 | BJ70: 09988 | BK70: =VLOOKUP(BJ70,[1]香港主板20251220!$A:$D,4,FALSE) -> 145.3
A71: =ROW()-1 -> 70 | B71: 药明生物 | C71: 02269 | D71: 34.16 | H71: 33.48 | I71: 32.62 | J71: 31.16 | K71: 30.56 | L71: 33.32 | M71: 33.78 | N71: 36.2 | O71: 36.26 | P71: 35.16 | Q71: 37.86 | R71: 42.18 | S71: 39.06 | T71: 37.78 | U71: 36.48 | V71: 36.94 | W71: 33.2 | X71: 32.92 | Y71: 30.94 | Z71: 29.36 | AA71: 31.35 | AB71: 31.5 | BF71: =D71-H71 -> 0.68 | BG71: =BF71/H71 -> 0.020310633 | BH71: 7.8 | BJ71: 02269 | BK71: =VLOOKUP(BJ71,[1]香港主板20251220!$A:$D,4,FALSE) -> 34.16
A72: =ROW()-1 -> 71 | B72: 京东集团SW | C72: 09618 | D72: 111.3 | H72: 115.6 | I72: 117 | J72: 116.5 | K72: 110.3 | L72: 116.9 | M72: 124 | N72: 127.6 | O72: 128.8 | P72: 124.1 | Q72: 131.8 | R72: 140.2 | S72: 132.5 | T72: 138.8 | U72: 131.7 | V72: 122.1 | W72: 117.8 | X72: 121.4 | Y72: 120.8 | Z72: 122.9 | AA72: 122.7 | AB72: 130.5 | AC72: 128.2 | BF72: =D72-H72 -> -4.3 | BG72: =BF72/H72 -> -0.037197232 | BH72: 7.8 | BJ72: 09618 | BK72: =VLOOKUP(BJ72,[1]香港主板20251220!$A:$D,4,FALSE) -> 111.3
A73: =ROW()-1 -> 72 | B73: 中国联通 | C73: 00762 | D73: 8.41 | H73: 8.6 | I73: 8.89 | J73: 9 | K73: 9.21 | L73: 9.57 | M73: 9.83 | N73: 9.35 | O73: 9.39 | P73: 9.04 | Q73: 8.95 | R73: 8.89 | S73: 8.82 | T73: 9.6 | U73: 9.84 | V73: 9.44 | W73: 9.9 | X73: 10.4 | Y73: 10.19 | Z73: 9.91 | AA73: 9.63 | AB73: 9.45 | AC73: 9.38 | BF73: =D73-H73 -> -0.19 | BG73: =BF73/H73 -> -0.022093023 | BH73: 7.8 | BJ73: 00762 | BK73: =VLOOKUP(BJ73,[1]香港主板20251220!$A:$D,4,FALSE) -> 8.41
A74: =ROW()-1 -> 73 | B74: 海天国际 | C74: 01882 | D74: 21.6 | H74: 22.4 | I74: 22.74 | J74: 21.82 | K74: 21.6 | L74: 22.32 | M74: 22.24 | N74: 21.24 | O74: 21.66 | P74: 21.26 | Q74: 22.12 | R74: 21.94 | S74: 21.38 | T74: 22.18 | U74: 22.6 | V74: 22.14 | W74: 22.02 | X74: 21.9 | Y74: 21.76 | Z74: 21.32 | AA74: 21.1 | AB74: 22.4 | AC74: 20.95 | BF74: =D74-H74 -> -0.8 | BG74: =BF74/H74 -> -0.035714286 | BH74: 7.8 | BJ74: 01882 | BK74: =VLOOKUP(BJ74,[1]香港主板20251220!$A:$D,4,FALSE) -> 21.6
A75: =ROW()-1 -> 74 | B75: 中国宏桥 | C75: 01378 | D75: 31.7 | H75: 32.68 | I75: 33.74 | J75: 30.86 | K75: 29.52 | L75: 33.52 | M75: 32.32 | N75: 29.52 | O75: 27.72 | P75: 25.26 | Q75: 26.1 | R75: 26.84 | S75: 24.96 | T75: 26.46 | U75: 26.84 | V75: 24.96 | W75: 25.44 | X75: 24.64 | Y75: 23.38 | Z75: 22.66 | AA75: 20.35 | AB75: 21.55 | AC75: 19.26 | BF75: =D75-H75 -> -0.98 | BG75: =BF75/H75 -> -0.02998776 | BH75: 7.8 | BJ75: 01378 | BK75: =VLOOKUP(BJ75,[1]香港主板20251220!$A:$D,4,FALSE) -> 31.7
A76: =ROW()-1 -> 75 | B76: 中石化油服 | C76: 01033 | D76: 0.7 | H76: 0.71 | I76: 0.76 | J76: 0.74 | K76: 0.74 | L76: 0.82 | M76: 0.77 | N76: 0.77 | O76: 0.8 | P76: 0.73 | Q76: 0.79 | R76: 0.76 | S76: 0.76 | T76: 0.79 | U76: 0.79 | V76: 0.77 | W76: 0.77 | X76: 0.81 | Y76: 0.82 | Z76: 0.8 | AA76: 0.76 | AB76: 0.83 | AC76: 0.82 | AD76: 0.78 | AE76: 0.7 | AF76: 0.68 | AG76: 0.8 | AH76: 0.8 | BF76: =D76-H76 -> -0.01 | BG76: =BF76/H76 -> -0.014084507 | BH76: 7.8 | BJ76: 01033 | BK76: =VLOOKUP(BJ76,[1]香港主板20251220!$A:$D,4,FALSE) -> 0.7
A77: =ROW()-1 -> 76 | B77: 康方生物 | C77: 09926 | D77: 117.2 | H77: 124.5 | I77: 124.1 | J77: 122.9 | K77: 107 | L77: 118.8 | M77: 112.2 | N77: 113.4 | O77: 115.2 | P77: 122.6 | Q77: 128 | R77: 139.8 | S77: 132.7 | T77: 129.7 | U77: 135.5 | V77: 154.7 | W77: 155.7 | X77: 176.9 | Y77: 165.5 | Z77: 160.4 | AA77: 156.3 | AB77: 149.1 | AC77: 140.7 | AD77: 113.2 | AE77: 116.1 | AF77: 92.5 | AG77: 91.3 | AH77: 95.85 | AI77: 82.25 | BF77: =D77-H77 -> -7.3 | BG77: =BF77/H77 -> -0.058634538 | BH77: 7.8 | BJ77: 09926 | BK77: =VLOOKUP(BJ77,[1]香港主板20251220!$A:$D,4,FALSE) -> 117.2
A78: =ROW()-1 -> 77 | B78: 中银香港 | C78: 02388 | D78: 38.34 | H78: 38.04 | I78: 37.34 | J78: 37.46 | K78: 37.74 | L78: 39.52 | M78: 38.7 | N78: 38.18 | O78: 37.98 | P78: 36.1 | Q78: 36.86 | R78: 36.4 | S78: 36.72 | T78: 37.22 | U78: 38.68 | V78: 37.28 | W78: 35.22 | X78: 36.82 | Y78: 36.16 | Z78: 36.9 | AA78: 35.15 | AB78: 35.9 | AC78: 37.1 | AD78: 36.8 | AE78: 34 | AF78: 36.15 | AG78: 35.4 | AH78: 34.75 | AI78: 34.2 | AJ78: 33.1 | AK78: 33.55 | AL78: 33.1 | AM78: 32.65 | AN78: 31.8 | AO78: 30.5 | AP78: 29.25 | AQ78: 29 | AR78: 30.85 | AS78: 31.3 | AT78: 29.95 | AU78: 29.45 | AV78: 29.75 | AW78: 27.35 | AX78: 27.15 | AY78: 26.8 | AZ78: 25.65 | BA78: 25.25 | BB78: 25.05 | BC78: 24.4 | BD78: 24.45 | BE78: 24.85 | BF78: =D78-H78 -> 0.3 | BG78: =BF78/H78 -> 0.0078864353 | BH78: 7.8 | BJ78: 02388 | BK78: =VLOOKUP(BJ78,[1]香港主板20251220!$A:$D,4,FALSE) -> 38.34
A79: =ROW()-1 -> 78 | B79: 农夫山泉 | C79: 09633 | D79: 47.5 | H79: 46.94 | I79: 48.08 | J79: 48.82 | K79: 50.3 | L79: 54.25 | M79: 52.6 | N79: 51.6 | O79: 53.95 | P79: 53.3 | Q79: 54.05 | R79: 53.75 | S79: 52.2 | T79: 54.4 | U79: 52.3 | V79: 50.95 | W79: 49.98 | X79: 46.44 | Y79: 46.68 | Z79: 46.52 | AA79: 44.95 | AB79: 46.5 | AC79: 43 | AD79: 39.1 | AE79: 40.15 | AF79: 40.4 | AG79: 38.35 | AH79: 39.15 | AI79: 39.55 | AJ79: 38.4 | AK79: 36.6 | AL79: 38.45 | AM79: 38.2 | AN79: 36.05 | AO79: 36.6 | AP79: 36.65 | AQ79: 35.1 | AR79: 34.45 | AS79: 34.65 | AT79: 37.05 | AU79: 38.05 | AV79: 37.35 | AW79: 34.7 | AX79: 33.7 | AY79: 36.05 | AZ79: 35.7 | BA79: 36.55 | BB79: 35.1 | BC79: 34.7 | BD79: 32.75 | BE79: 33.65 | BF79: =D79-H79 -> 0.56 | BG79: =BF79/H79 -> 0.011930124 | BH79: 7.8 | BJ79: 09633 | BK79: =VLOOKUP(BJ79,[1]香港主板20251220!$A:$D,4,FALSE) -> 47.5
A80: =ROW()-1 -> 79 | B80: 小米集团 | C80: 01810 | D80: 40.54 | H80: 42.96 | I80: 42.78 | J80: 41.02 | K80: 38.08 | L80: 42.36 | M80: 42.24 | N80: 43.2 | O80: 45.92 | P80: 45.96 | Q80: 52.05 | R80: 55 | S80: 54.65 | T80: 56.7 | U80: 55.15 | V80: 53.65 | W80: 52.85 | X80: 52.55 | Y80: 52.85 | Z80: 51.25 | AA80: 53.4 | AB80: 57.4 | AC80: 57 | AD80: 57.35 | AE80: 57.5 | AF80: 58.95 | AG80: 54.05 | AH80: 51.95 | AI80: 53.1 | AJ80: 50.95 | AK80: 53 | AL80: 51 | AM80: 51.35 | AN80: 53.1 | AO80: 47.7 | AP80: 41.95 | AQ80: 44.25 | AR80: 45.9 | AS80: 51.05 | AT80: 54.7 | AU80: 53.85 | AV80: 54.35 | AW80: 51.85 | AX80: 51.7 | AY80: 44.7 | AZ80: 42.45 | BA80: 38.3 | BB80: 36.85 | BC80: 34.95 | BD80: 33.55 | BE80: 36.25 | BF80: =D80-H80 -> -2.42 | BG80: =BF80/H80 -> -0.056331471 | BH80: 7.8 | BJ80: 01810 | BK80: =VLOOKUP(BJ80,[1]香港主板20251220!$A:$D,4,FALSE) -> 40.54
A81: =ROW()-1 -> 80 | B81: 中芯国际 | C81: 00981 | D81: 65.05 | H81: 67.7 | I81: 69.75 | J81: 68.8 | K81: 68.8 | L81: 73.5 | M81: 75.45 | N81: 75 | O81: 80 | P81: 69.1 | Q81: 77.55 | R81: 90.9 | S81: 72.95 | T81: 69.75 | U81: 62.75 | V81: 58.7 | W81: 60.7 | X81: 56.9 | Y81: 52.75 | Z81: 48.66 | AA81: 50.05 | AB81: 52.75 | AC81: 47.1 | AD81: 45.95 | AE81: 43.95 | AF81: 44.85 | AG81: 39.5 | AH81: 40 | AI81: 40.2 | AJ81: 40.55 | AK81: 41.85 | AL81: 41.7 | AM81: 43 | AN81: 47.5 | AO81: 45.05 | AP81: 46 | AQ81: 46.7 | AR81: 45.05 | AS81: 48 | AT81: 46.95 | AU81: 50.5 | AV81: 54.6 | AW81: 53.6 | AX81: 54.2 | AY81: 45.55 | AZ81: 46.65 | BA81: 38 | BB81: 41.3 | BC81: 39.45 | BD81: 32.35 | BE81: 29.55 | BF81: =D81-H81 -> -2.65 | BG81: =BF81/H81 -> -0.039143279 | BH81: 7.8 | BJ81: 00981 | BK81: =VLOOKUP(BJ81,[1]香港主板20251220!$A:$D,4,FALSE) -> 65.05
A82: =ROW()-1 -> 81 | B82: 携程集团 | C82: 09961 | D82: 560 | H82: 550 | I82: 554.5 | J82: 535 | K82: 537.5 | L82: 576 | M82: 546.5 | N82: 543.5 | O82: 564 | P82: 532 | Q82: 569 | R82: 574.5 | S82: 582.5 | T82: 606.5 | U82: 577.5 | V82: 572 | W82: 578 | X82: 505 | Y82: 489 | Z82: 482 | AA82: 484.8 | AB82: 503.5 | AC82: 498 | AD82: 488.2 | AE82: 466 | AF82: 459.2 | AG82: 446.4 | AH82: 468.8 | AI82: 466.8 | AJ82: 494 | AK82: 487.6 | AL82: 506 | AM82: 478.6 | AN82: 471 | AO82: 450.4 | AP82: 449.8 | AQ82: 427.6 | AR82: 488 | AS82: 507 | AT82: 498 | AU82: 481 | AV82: 511.5 | AW82: 436.6 | AX82: 512.5 | AY82: 556 | AZ82: 532.5 | BA82: 548 | BB82: 541 | BC82: 513 | BD82: 498 | BE82: 516.5 | BF82: =D82-H82 -> 10 | BG82: =BF82/H82 -> 0.018181818 | BH82: 7.8 | BJ82: 09961 | BK82: =VLOOKUP(BJ82,[1]香港主板20251220!$A:$D,4,FALSE) -> 560
A83: =ROW()-1 -> 82 | B83: 比亚迪股份 | C83: 01211 | D83: 93.7 | H83: 98.5 | I83: 99.15 | J83: 97.5 | K83: 92.75 | L83: 100.6 | M83: 97.9 | N83: 100.6 | O83: 104 | P83: 103.2 | Q83: 108.2 | R83: 109.4 | S83: 106.5 | T83: 113.5 | U83: 104.5 | V83: 105.6 | W83: 114.4 | X83: 114.3 | Y83: 112.8 | Z83: 111.2 | AA83: 116.2 | AB83: 129.6 | AC83: 126.4 | AD83: 120.1 | AE83: 121.5 | AF83: 124.2 | AG83: 125.8 | AH83: 131.1 | AI83: 403 | AJ83: 392.8 | AK83: 465.2 | AL83: 434.2 | AM83: 387 | AN83: 382.4 | AO83: 397 | AP83: 366 | AQ83: 368.8 | AR83: 374.8 | AS83: 406.8 | AT83: 391.6 | AU83: 385.8 | AV83: 355.2 | AW83: 371.6 | AX83: 392.4 | AY83: 364.2 | AZ83: 330 | BA83: 273 | BB83: 274.4 | BC83: 263.8 | BD83: 251.4 | BE83: 258 | BF83: =D83-H83 -> -4.8 | BG83: =BF83/H83 -> -0.048730964 | BH83: 7.8 | BJ83: 01211 | BK83: =VLOOKUP(BJ83,[1]香港主板20251220!$A:$D,4,FALSE) -> 93.7
A84: =ROW()-1 -> 83 | B84: 腾讯集团 | C84: 00700 | D84: 614 | H84: 616 | I84: 610 | J84: 611.5 | K84: 610 | L84: 641 | M84: 634 | N84: 629 | O84: 637.5 | P84: 608 | Q84: 651.5 | R84: 673.5 | S84: 644 | T84: 642.5 | U84: 643.5 | V84: 605.5 | W84: 596.5 | X84: 600 | Y84: 592 | Z84: 561 | AA84: 535 | AB84: 550.5 | AC84: 519 | AD84: 496.6 | AE84: 496.8 | AF84: 513 | AG84: 505.5 | AH84: 510 | AI84: 515 | AJ84: 498.2 | AK84: 518 | AL84: 508 | AM84: 494.6 | AN84: 487.8 | AO84: 478.2 | AP84: 458 | AQ84: 443.4 | AR84: 497.8 | AS84: 509.5 | AT84: 511.5 | AU84: 521.5 | AV84: 533.5 | AW84: 478.6 | AX84: 517 | AY84: 474.8 | AZ84: 428.2 | BA84: 401.2 | BB84: 390.6 | BC84: 379.8 | BD84: 369.6 | BE84: 414.2 | BF84: =D84-H84 -> -2 | BG84: =BF84/H84 -> -0.0032467532 | BH84: 7.8 | BJ84: 00700 | BK84: =VLOOKUP(BJ84,[1]香港主板20251220!$A:$D,4,FALSE) -> 614
B85: 海南瑞泽 | C85: 002596 | D85: 5.35 | BF85: =D85-H85 -> 5.35 | BG85: =BF85/H85 -> #DIV/0! | BH85: 7.8 | BJ85: 002596 | BK85: =VLOOKUP(BJ85,[2]全部Ａ股20251220!$A:$D,4,FALSE) -> 5.35
A86: =ROW()-1 -> 85 | B86: 航天智造 | C86: 300446 | D86: 26.25 | BF86: =D86-H86 -> 26.25 | BG86: =BF86/H86 -> #DIV/0! | BH86: 7.8 | BJ86: 300446 | BK86: =VLOOKUP(BJ86,[2]全部Ａ股20251220!$A:$D,4,FALSE) -> 26.25
A87: =ROW()-1 -> 86 | B87: 航天电子 | C87: 600879 | D87: 18.07 | BF87: =D87-H87 -> 18.07 | BG87: =BF87/H87 -> #DIV/0! | BH87: 7.8 | BJ87: 600879 | BK87: =VLOOKUP(BJ87,[2]全部Ａ股20251220!$A:$D,4,FALSE) -> 18.07
A88: =ROW()-1 -> 87 | B88: 西部材料 | C88: 002149 | D88: 37.72 | BF88: =D88-H88 -> 37.72 | BG88: =BF88/H88 -> #DIV/0! | BH88: 7.8 | BJ88: 002149 | BK88: =VLOOKUP(BJ88,[2]全部Ａ股20251220!$A:$D,4,FALSE) -> 37.72
A89: =ROW()-1 -> 88 | B89: 航天发展 | C89: 000547 | D89: 22.3 | H89: 21.31 | I89: 20.57 | J89: 13.51 | BF89: =D89-H89 -> 0.99 | BG89: =BF89/H89 -> 0.046457062 | BH89: 7.8 | BJ89: 000547 | BK89: =VLOOKUP(BJ89,[2]全部Ａ股20251220!$A:$D,4,FALSE) -> 22.3
A90: =ROW()-1 -> 89 | B90: 浙江世宝 | C90: 002703 | D90: 17.51 | BF90: =D90-H90 -> 17.51 | BG90: =BF90/H90 -> #DIV/0! | BH90: 7.8 | BJ90: 002703 | BK90: =VLOOKUP(BJ90,[2]全部Ａ股20251220!$A:$D,4,FALSE) -> 17.51
A91: =ROW()-1 -> 90 | B91: 华菱线缆 | C91: 001208 | D91: 21.17 | H91: 16.34 | BF91: =D91-H91 -> 4.83 | BG91: =BF91/H91 -> 0.29559364 | BH91: 7.8 | BJ91: 001208 | BK91: =VLOOKUP(BJ91,[2]全部Ａ股20251220!$A:$D,4,FALSE) -> 21.17
A92: =ROW()-1 -> 91 | B92: 雪人集团 | C92: 002639 | D92: 20.34 | H92: 18.16 | BF92: =D92-H92 -> 2.18 | BG92: =BF92/H92 -> 0.12004405 | BH92: 7.8 | BJ92: 002639 | BK92: =VLOOKUP(BJ92,[2]全部Ａ股20251220!$A:$D,4,FALSE) -> 20.34
A93: =ROW()-1 -> 92 | B93: 顺灏股份 | C93: 002565 | D93: 16.58 | H93: 15.95 | BF93: =D93-H93 -> 0.63 | BG93: =BF93/H93 -> 0.039498433 | BH93: 7.8 | BJ93: 002565 | BK93: =VLOOKUP(BJ93,[2]全部Ａ股20251220!$A:$D,4,FALSE) -> 16.58
A94: =ROW()-1 -> 93 | B94: 般天动力 | C94: 600343 | D94: 38.62 | H94: 40.12 | BF94: =D94-H94 -> -1.5 | BG94: =BF94/H94 -> -0.037387836 | BH94: 7.8 | BJ94: 600343 | BK94: =VLOOKUP(BJ94,[2]全部Ａ股20251220!$A:$D,4,FALSE) -> 38.62
A95: =ROW()-1 -> 94 | B95: 摩尔线程 | C95: 688795 | D95: 664.1 | H95: 814.88 | I95: 600.5 | BF95: =D95-H95 -> -150.78 | BG95: =BF95/H95 -> -0.18503338 | BH95: 7.8 | BJ95: 688795 | BK95: =VLOOKUP(BJ95,[2]全部Ａ股20251220!$A:$D,4,FALSE) -> 664.1
A96: =ROW()-1 -> 95 | B96: 航天电机 | C96: 600151 | D96: 18.88 | H96: 15.4 | I96: 13.65 | BF96: =D96-H96 -> 3.48 | BG96: =BF96/H96 -> 0.22597403 | BH96: 7.8 | BJ96: 600151 | BK96: =VLOOKUP(BJ96,[2]全部Ａ股20251220!$A:$D,4,FALSE) -> 18.88
A97: =ROW()-1 -> 96 | B97: 太阳线缆 | C97: 002300 | D97: 10.67 | H97: 10.69 | I97: 10.36 | BF97: =D97-H97 -> -0.02 | BG97: =BF97/H97 -> -0.0018709074 | BH97: 7.8 | BJ97: 002300 | BK97: =VLOOKUP(BJ97,[2]全部Ａ股20251220!$A:$D,4,FALSE) -> 10.67
A98: =ROW()-1 -> 97 | B98: 力星股份 | C98: 300421 | D98: 27.16 | H98: 29.79 | I98: 28.78 | BF98: =D98-H98 -> -2.63 | BG98: =BF98/H98 -> -0.088284659 | BH98: 7.8 | BJ98: 300421 | BK98: =VLOOKUP(BJ98,[2]全部Ａ股20251220!$A:$D,4,FALSE) -> 27.16
A99: =ROW()-1 -> 98 | B99: 国机重装 | C99: 601399 | D99: 5.57 | H99: 5.18 | I99: 4.63 | BF99: =D99-H99 -> 0.39 | BG99: =BF99/H99 -> 0.075289575 | BH99: 7.8 | BJ99: 601399 | BK99: =VLOOKUP(BJ99,[2]全部Ａ股20251220!$A:$D,4,FALSE) -> 5.57
A100: =ROW()-1 -> 99 | B100: 瑞康医药 | C100: 002589 | D100: 3.55 | H100: 3.51 | I100: 4.26 | BF100: =D100-H100 -> 0.04 | BG100: =BF100/H100 -> 0.011396011 | BH100: 7.8 | BJ100: 002589 | BK100: =VLOOKUP(BJ100,[2]全部Ａ股20251220!$A:$D,4,FALSE) -> 3.55
A101: =ROW()-1 -> 100 | B101: 道明光学 | C101: 002632 | D101: 12.3 | H101: 13.03 | I101: 15 | J101: 12.44 | BF101: =D101-H101 -> -0.73 | BG101: =BF101/H101 -> -0.056024559 | BH101: 7.8 | BJ101: 002632 | BK101: =VLOOKUP(BJ101,[2]全部Ａ股20251220!$A:$D,4,FALSE) -> 12.3
A102: =ROW()-1 -> 101 | B102: 乾照光电 | C102: 300102 | D102: 24.76 | H102: 26.32 | I102: 23.88 | J102: 19.07 | BF102: =D102-H102 -> -1.56 | BG102: =BF102/H102 -> -0.059270517 | BH102: 7.8 | BJ102: 300102 | BK102: =VLOOKUP(BJ102,[2]全部Ａ股20251220!$A:$D,4,FALSE) -> 24.76
A103: =ROW()-1 -> 102 | B103: 雷科防务 | C103: 002413 | D103: 9.26 | H103: 9.07 | I103: 8.79 | J103: 7.66 | BF103: =D103-H103 -> 0.19 | BG103: =BF103/H103 -> 0.020948181 | BH103: 7.8 | BJ103: 002413 | BK103: =VLOOKUP(BJ103,[2]全部Ａ股20251220!$A:$D,4,FALSE) -> 9.26
A104: =ROW()-1 -> 103 | B104: 梦天家居 | C104: 603216 | D104: 36.02 | H104: 33.23 | I104: 30.76 | J104: 28.66 | BF104: =D104-H104 -> 2.79 | BG104: =BF104/H104 -> 0.083960277 | BH104: 7.8 | BJ104: 603216 | BK104: =VLOOKUP(BJ104,[2]全部Ａ股20251220!$A:$D,4,FALSE) -> 36.02
A105: =ROW()-1 -> 104 | B105: 宣亚国际 | C105: 300612 | D105: 16.16 | H105: 16.38 | I105: 17.33 | J105: 19.85 | BF105: =D105-H105 -> -0.22 | BG105: =BF105/H105 -> -0.013431013 | BH105: 7.8 | BJ105: 300612 | BK105: =VLOOKUP(BJ105,[2]全部Ａ股20251220!$A:$D,4,FALSE) -> 16.16
A106: =ROW()-1 -> 105 | B106: 紫金矿业 | C106: 601899 | D106: 31.12 | H106: 31.7 | I106: 31.32 | J106: 28.58 | K106: 28.14 | BF106: =D106-H106 -> -0.58 | BG106: =BF106/H106 -> -0.01829653 | BH106: 7.8 | BJ106: 601899 | BK106: =VLOOKUP(BJ106,[2]全部Ａ股20251220!$A:$D,4,FALSE) -> 31.12
A107: =ROW()-1 -> 106 | B107: 恒瑞医药 | C107: 600276 | D107: 60.85 | H107: 63.28 | I107: 61.62 | J107: 62.08 | K107: 59.5 | BF107: =D107-H107 -> -2.43 | BG107: =BF107/H107 -> -0.038400759 | BH107: 7.8 | BJ107: 600276 | BK107: =VLOOKUP(BJ107,[2]全部Ａ股20251220!$A:$D,4,FALSE) -> 60.85
A108: =ROW()-1 -> 107 | B108: 海天味业 | C108: 603288 | D108: 37.78 | H108: 36.49 | I108: 36.51 | J108: 36.96 | K108: 37.29 | L108: 38.42 | BF108: =D108-H108 -> 1.29 | BG108: =BF108/H108 -> 0.035352151 | BH108: 7.8 | BJ108: 603288 | BK108: =VLOOKUP(BJ108,[2]全部Ａ股20251220!$A:$D,4,FALSE) -> 37.78
A109: =ROW()-1 -> 108 | B109: 蜂助手 | C109: 301382 | D109: 33.13 | H109: 33.17 | I109: 34.49 | J109: 37 | K109: 36.87 | L109: 34.29 | BF109: =D109-H109 -> -0.04 | BG109: =BF109/H109 -> -0.001205909 | BH109: 7.8 | BJ109: 301382 | BK109: =VLOOKUP(BJ109,[2]全部Ａ股20251220!$A:$D,4,FALSE) -> 33.13
A110: =ROW()-1 -> 109 | B110: 山东黄金 | C110: 600547 | D110: 36.42 | H110: 36 | I110: 36.33 | J110: 36.46 | K110: 35.1 | L110: 35.83 | BF110: =D110-H110 -> 0.42 | BG110: =BF110/H110 -> 0.011666667 | BH110: 7.8 | BJ110: 600547 | BK110: =VLOOKUP(BJ110,[2]全部Ａ股20251220!$A:$D,4,FALSE) -> 36.42
A111: =ROW()-1 -> 110 | B111: 国际复材 | C111: 301526 | D111: 6.42 | H111: 7.09 | I111: 7.25 | J111: 5.72 | K111: 5.42 | L111: 5.92 | BF111: =D111-H111 -> -0.67 | BG111: =BF111/H111 -> -0.094499295 | BH111: 7.8 | BJ111: 301526 | BK111: =VLOOKUP(BJ111,[2]全部Ａ股20251220!$A:$D,4,FALSE) -> 6.42
A112: =ROW()-1 -> 111 | B112: 曼恩斯特 | C112: 301325 | D112: 49.15 | H112: 49.4 | I112: 50.15 | J112: 52.46 | K112: 52.01 | L112: 63.3 | BF112: =D112-H112 -> -0.25 | BG112: =BF112/H112 -> -0.0050607287 | BH112: 7.8 | BJ112: 301325 | BK112: =VLOOKUP(BJ112,[2]全部Ａ股20251220!$A:$D,4,FALSE) -> 49.15
A113: =ROW()-1 -> 112 | B113: 中国中免 | C113: 601888 | D113: 82.81 | H113: 79.2 | I113: 81.02 | J113: 79.03 | K113: 79.05 | L113: 88.28 | BF113: =D113-H113 -> 3.61 | BG113: =BF113/H113 -> 0.045580808 | BH113: 7.8 | BJ113: 601888 | BK113: =VLOOKUP(BJ113,[2]全部Ａ股20251220!$A:$D,4,FALSE) -> 82.81
A114: =ROW()-1 -> 113 | B114: 长江电力 | C114: 600900 | D114: 27.85 | H114: 28.04 | I114: 28.07 | J114: 27.98 | K114: 28.16 | L114: 28.34 | BF114: =D114-H114 -> -0.19 | BG114: =BF114/H114 -> -0.0067760342 | BH114: 7.8 | BJ114: 600900 | BK114: =VLOOKUP(BJ114,[2]全部Ａ股20251220!$A:$D,4,FALSE) -> 27.85
A115: =ROW()-1 -> 114 | B115: 航发动力 | C115: 600893 | D115: 39.18 | H115: 36.88 | I115: 36.99 | J115: 37.18 | K115: 36.56 | L115: 37.71 | BF115: =D115-H115 -> 2.3 | BG115: =BF115/H115 -> 0.062364425 | BH115: 7.8 | BJ115: 600893 | BK115: =VLOOKUP(BJ115,[2]全部Ａ股20251220!$A:$D,4,FALSE) -> 39.18
...

Sheet 全班
R1: =股价!D1 -> 46011
A2: 组别 | B2: 学号 | C2: 姓名 | D2: 市场 | E2: 企业 | F2: 股票代码 | G2: 状态 | H2: 数量 | I2: 平均买价 | J2: 成本 | K2: 当前股价 | L2: 市值 | M2: 现金结余 | N2: 结余总额 | O2: 盈利 | P2: 盈利率 | Q2: 本金 | R2: 单股盈利 | S2: 盈利率
C3: 徐伟伟 | D3: =伟伟!E125 -> US | E3: =伟伟!F125 -> 英伟达 | F3: =伟伟!G125 -> NVDA | G3: =伟伟!H125 -> 持有 | H3: =伟伟!I125 -> 58 | I3: =伟伟!J125 -> -1131.8136 | J3: =伟伟!K125 -> -65645.19 | K3: =伟伟!L125 -> 1411.722 | L3: =伟伟!M125 -> 81879.876 | M3: =伟伟!M141 -> 211002.75 | N3: =M3+SUM(L3:L13) -> 1317997.3 | O3: =N3-Q3 -> 317997.31 | P3: =O3/Q3 -> 0.31799731 | Q3: 1000000 | R3: =IFERROR(L3-J3,0) -> 147525.07 | S3: =IFERROR((R3/J3),"") -> -2.2473096
D4: =伟伟!E126 -> US | E4: =伟伟!F126 -> 脸书 | F4: =伟伟!G126 -> Meta | G4: =伟伟!H126 -> 持有 | H4: =伟伟!I126 -> 23 | I4: =伟伟!J126 -> 3218.5852 | J4: =伟伟!K126 -> 74027.46 | K4: =伟伟!L126 -> 5138.406 | L4: =伟伟!M126 -> 118183.34 | R4: =IFERROR(L4-J4,0) -> 44155.878 | S4: =IFERROR((R4/J4),"") -> 0.59647971
D5: =伟伟!E127 -> US | E5: =伟伟!F127 -> 特斯拉 | F5: =伟伟!G127 -> TSLA | G5: =伟伟!H127 -> 持有 | H5: =伟伟!I127 -> 98 | I5: =伟伟!J127 -> 2022.9021 | J5: =伟伟!K127 -> 198244.41 | K5: =伟伟!L127 -> 3753.36 | L5: =伟伟!M127 -> 367829.28 | R5: =IFERROR(L5-J5,0) -> 169584.87 | S5: =IFERROR((R5/J5),"") -> 0.8554333
D6: =伟伟!E128 -> US | E6: =伟伟!F128 -> 超微电脑 | F6: =伟伟!G128 -> SMCI | G6: =伟伟!H128 -> 持有 | H6: =伟伟!I128 -> 15 | I6: =伟伟!J128 -> 7534.8572 | J6: =伟伟!K128 -> 113022.86 | K6: =伟伟!L128 -> 242.658 | L6: =伟伟!M128 -> 3639.87 | R6: =IFERROR(L6-J6,0) -> -109382.99 | S6: =IFERROR((R6/J6),"") -> -0.96779528
D7: =伟伟!E129 -> US | E7: =伟伟!F129 -> 台积电 | F7: =伟伟!G129 -> TSM | G7: =伟伟!H129 -> 持有 | H7: =伟伟!I129 -> 28 | I7: =伟伟!J129 -> 873.39107 | J7: =伟伟!K129 -> 24454.95 | K7: =伟伟!L129 -> 2253.81 | L7: =伟伟!M129 -> 63106.68 | R7: =IFERROR(L7-J7,0) -> 38651.73 | S7: =IFERROR((R7/J7),"") -> 1.5805279
D8: =伟伟!E130 -> US | E8: =伟伟!F130 -> 阿斯麦 | F8: =伟伟!G130 -> ASML | G8: =伟伟!H130 -> 持有 | H8: =伟伟!I130 -> 28 | I8: =伟伟!J130 -> 5236.4409 | J8: =伟伟!K130 -> 146620.34 | K8: =伟伟!L130 -> 8236.956 | L8: =伟伟!M130 -> 230634.77 | R8: =IFERROR(L8-J8,0) -> 84014.424 | S8: =IFERROR((R8/J8),"") -> 0.57300659
D9: =伟伟!E131 -> US | E9: =伟伟!F131 -> Robinhood Market | F9: =伟伟!G131 -> HOOD | G9: =伟伟!H131 -> 持有 | H9: =伟伟!I131 -> 50 | I9: =伟伟!J131 -> 44.382 | J9: =伟伟!K131 -> 2219.1 | K9: =伟伟!L131 -> 946.53 | L9: =伟伟!M131 -> 47326.5 | R9: =IFERROR(L9-J9,0) -> 45107.4 | S9: =IFERROR((R9/J9),"") -> 20.326889
D10: =伟伟!E132 -> US | E10: =伟伟!F132 -> 博通 | F10: =伟伟!G132 -> AVGO | G10: =伟伟!H132 -> 持有 | H10: =伟伟!I132 -> 8 | I10: =伟伟!J132 -> -266.98425 | J10: =伟伟!K132 -> -2135.874 | K10: =伟伟!L132 -> 2654.808 | L10: =伟伟!M132 -> 21238.464 | R10: =IFERROR(L10-J10,0) -> 23374.338 | S10: =IFERROR((R10/J10),"") -> -10.943688
D11: =伟伟!E133 -> US | E11: =伟伟!F133 -> applovin corporation | F11: =伟伟!G133 -> APP | G11: =伟伟!H133 -> 持有 | H11: =伟伟!I133 -> 18 | I11: =伟伟!J133 -> -133.536 | J11: =伟伟!K133 -> -2403.648 | K11: =伟伟!L133 -> 5626.686 | L11: =伟伟!M133 -> 101280.35 | R11: =IFERROR(L11-J11,0) -> 103684 | S11: =IFERROR((R11/J11),"") -> -43.136098
D12: =伟伟!E134 -> US | E12: =伟伟!F134 -> 谷歌 | F12: =伟伟!G134 -> GOOGL | G12: =伟伟!H134 -> 持有 | H12: =伟伟!I134 -> 30 | I12: =伟伟!J134 -> 2410.408 | J12: =伟伟!K134 -> 72312.24 | K12: =伟伟!L134 -> 2395.848 | L12: =伟伟!M134 -> 71875.44 | R12: =IFERROR(L12-J12,0) -> -436.8 | S12: =IFERROR((R12/J12),"") -> -0.0060404712
D13: =伟伟!E138 -> 0 | E13: =伟伟!F138 -> 0 | F13: =伟伟!G138 -> 0 | G13: =伟伟!H138 -> 0 | H13: =伟伟!I138 -> 0 | I13: =伟伟!J138 -> 0 | J13: =伟伟!K138 -> 0 | K13: =伟伟!L138 -> 0 | L13: =伟伟!M138 -> 0 | R13: =IFERROR(L13-J13,0) -> 0 | S13: =IFERROR((R13/J13),"")
C14: 何凤 | D14: =何凤!E114 -> US | E14: =何凤!F114 -> 英伟达 | F14: =何凤!G114 -> NVDA | G14: =何凤!H114 -> 持有 | H14: =何凤!I114 -> 200 | I14: =何凤!J114 -> 1380.6 | J14: =何凤!K114 -> 276120 | K14: =何凤!L114 -> 1411.722 | L14: =何凤!M114 -> 282344.4 | M14: =何凤!M123 -> 347.82 | N14: =M14+SUM(L14:L19) -> 949375.22 | O14: =N14-Q14 -> -50624.78 | P14: =O14/Q14 -> -0.05062478 | Q14: 1000000 | R14: =IFERROR(L14-J14,0) -> 6224.4 | S14: =IFERROR((R14/J14),"") -> 0.022542373
D15: =何凤!E115 -> US | E15: =何凤!F115 -> 小鹏汽车 | F15: =何凤!G115 -> XPEV | G15: =何凤!H115 -> 持有 | H15: =何凤!I115 -> 1000 | I15: =何凤!J115 -> 148.122 | J15: =何凤!K115 -> 148122 | K15: =何凤!L115 -> 154.908 | L15: =何凤!M115 -> 154908 | R15: =IFERROR(L15-J15,0) -> 6786 | S15: =IFERROR((R15/J15),"") -> 0.045813586
D16: =何凤!E116 -> CN | E16: =何凤!F116 -> 航天电机 | F16: =何凤!G116 -> 600151 | G16: =何凤!H116 -> 持有 | H16: =何凤!I116 -> 5000 | I16: =何凤!J116 -> 15.4 | J16: =何凤!K116 -> 77000 | K16: =何凤!L116 -> 18.88 | L16: =何凤!M116 -> 94400 | R16: =IFERROR(L16-J16,0) -> 17400 | S16: =IFERROR((R16/J16),"") -> 0.22597403
D17: =何凤!E117 -> CN | E17: =何凤!F117 -> 海南瑞泽 | F17: =何凤!G117 -> 002596 | G17: =何凤!H117 -> 持有 | H17: =何凤!I117 -> 40500 | I17: =何凤!J117 -> 5.35 | J17: =何凤!K117 -> 216675 | K17: =何凤!L117 -> 5.35 | L17: =何凤!M117 -> 216675 | R17: =IFERROR(L17-J17,0) -> 0 | S17: =IFERROR((R17/J17),"") -> 0
D18: =何凤!E118 -> CN | E18: =何凤!F118 -> 航天发展 | F18: =何凤!G118 -> 000547 | G18: =何凤!H118 -> 持有 | H18: =何凤!I118 -> 9000 | I18: =何凤!J118 -> 22.3 | J18: =何凤!K118 -> 200700 | K18: =何凤!L118 -> 22.3 | L18: =何凤!M118 -> 200700
R19: =IFERROR(L19-J19,0) -> 0 | S19: =IFERROR((R19/J19),"")
C20: 钟荣辉 | D20: ='荣辉 '!E171 -> US | E20: ='荣辉 '!F171 -> 脸书 | F20: ='荣辉 '!G171 -> Meta | G20: ='荣辉 '!H171 -> 持有 | H20: ='荣辉 '!I171 -> 30 | I20: ='荣辉 '!J171 -> 4942.522 | J20: ='荣辉 '!K171 -> 148275.66 | K20: ='荣辉 '!L171 -> 5138.406 | L20: ='荣辉 '!M171 -> 154152.18 | M20: ='荣辉 '!M184 -> 786832.88 | N20: =M20+SUM(L20:L28) -> 1466371.2 | O20: =N20-Q20 -> 466371.22 | P20: =O20/Q20 -> 0.46637122 | Q20: 1000000 | R20: =IFERROR(L20-J20,0) -> 5876.52 | S20: =IFERROR((R20/J20),"") -> 0.039632398
D21: ='荣辉 '!E172 -> US | E21: ='荣辉 '!F172 -> 台积电 | F21: ='荣辉 '!G172 -> TSM | G21: ='荣辉 '!H172 -> 持有 | H21: ='荣辉 '!I172 -> 30 | I21: ='荣辉 '!J172 -> 2224.352 | J21: ='荣辉 '!K172 -> 66730.56 | K21: ='荣辉 '!L172 -> 2253.81 | L21: ='荣辉 '!M172 -> 67614.3 | R21: =IFERROR(L21-J21,0) -> 883.74 | S21: =IFERROR((R21/J21),"") -> 0.013243408
D22: ='荣辉 '!E173 -> US | E22: ='荣辉 '!F173 -> 英伟达 | F22: ='荣辉 '!G173 -> NVDA | G22: ='荣辉 '!H173 -> 持有 | H22: ='荣辉 '!I173 -> 30 | I22: ='荣辉 '!J173 -> 1395.862 | J22: ='荣辉 '!K173 -> 41875.86 | K22: ='荣辉 '!L173 -> 1411.722 | L22: ='荣辉 '!M173 -> 42351.66 | R22: =IFERROR(L22-J22,0) -> 475.8 | S22: =IFERROR((R22/J22),"") -> 0.011362155
D23: ='荣辉 '!E174 -> US | E23: ='荣辉 '!F174 -> 特斯拉 | F23: ='荣辉 '!G174 -> TSLA | G23: ='荣辉 '!H174 -> 持有 | H23: ='荣辉 '!I174 -> 30 | I23: ='荣辉 '!J174 -> 3386.396 | J23: ='荣辉 '!K174 -> 101591.88 | K23: ='荣辉 '!L174 -> 3753.36 | L23: ='荣辉 '!M174 -> 112600.8 | R23: =IFERROR(L23-J23,0) -> 11008.92 | S23: =IFERROR((R23/J23),"") -> 0.10836417
D24: ='荣辉 '!E175 -> US | E24: ='荣辉 '!F175 -> 亚马逊 | F24: ='荣辉 '!G175 -> AMZN | G24: ='荣辉 '!H175 -> 持有 | H24: ='荣辉 '!I175 -> 30 | I24: ='荣辉 '!J175 -> 1771.276 | J24: ='荣辉 '!K175 -> 53138.28 | K24: ='荣辉 '!L175 -> 1773.33 | L24: ='荣辉 '!M175 -> 53199.9
D25: ='荣辉 '!E176 -> US | E25: ='荣辉 '!F176 -> 微软 | F25: ='荣辉 '!G176 -> MSFT | G25: ='荣辉 '!H176 -> 持有 | H25: ='荣辉 '!I176 -> 30 | I25: ='荣辉 '!J176 -> 3770.13 | J25: ='荣辉 '!K176 -> 113103.9 | K25: ='荣辉 '!L176 -> 3790.176 | L25: ='荣辉 '!M176 -> 113705.28
D26: ='荣辉 '!E177 -> US | E26: ='荣辉 '!F177 -> 苹果 | F26: ='荣辉 '!G177 -> AAPL | G26: ='荣辉 '!H177 -> 持有 | H26: ='荣辉 '!I177 -> 30 | I26: ='荣辉 '!J177 -> 2142.426 | J26: ='荣辉 '!K177 -> 64272.78 | K26: ='荣辉 '!L177 -> 2134.626 | L26: ='荣辉 '!M177 -> 64038.78
D27: ='荣辉 '!E178 -> US | E27: ='荣辉 '!F178 -> 谷歌 | F27: ='荣辉 '!G178 -> GOOGL | G27: ='荣辉 '!H178 -> 持有 | H27: ='荣辉 '!I178 -> 30 | I27: ='荣辉 '!J178 -> 2410.2 | J27: ='荣辉 '!K178 -> 72306 | K27: ='荣辉 '!L178 -> 2395.848 | L27: ='荣辉 '!M178 -> 71875.44
R28: =IFERROR(L28-J28,0) -> 0 | S28: =IFERROR((R28/J28),"")
C29: 宋倩 | D29: =宋倩!E84 -> 0 | E29: =宋倩!F84 -> 0 | F29: =宋倩!G84 -> 0 | G29: =宋倩!H84 -> 持有 | H29: =宋倩!I84 -> 0 | I29: =宋倩!J84 -> #DIV/0! | J29: =宋倩!K84 -> 0 | K29: =宋倩!L84 -> #N/A | L29: =宋倩!M84 -> 0 | M29: =宋倩!M92 -> 1276670.8 | N29: =M29+SUM(L29:L34) -> 1276670.8 | O29: =N29-Q29 -> 276670.75 | P29: =O29/Q29 -> 0.27667075 | Q29: 1000000 | R29: =IFERROR(L29-J29,0) -> 0 | S29: =IFERROR((R29/J29),"")
R30: =IFERROR(L30-J30,0) -> 0 | S30: =IFERROR((R30/J30),"")
R31: =IFERROR(L31-J31,0) -> 0 | S31: =IFERROR((R31/J31),"")
R32: =IFERROR(L32-J32,0) -> 0
R33: =IFERROR(L33-J33,0) -> 0
R34: =IFERROR(L34-J34,0) -> 0 | S34: =IFERROR((R34/J34),"")
C35: 张咏博 | D35: =咏博!E159 -> US | E35: =咏博!F159 -> 英伟达 | F35: =咏博!G159 -> NVDA | G35: =咏博!H159 -> 持有 | H35: =咏博!I159 -> 188 | I35: =咏博!J159 -> 833.05577 | J35: =咏博!K159 -> 156614.48 | K35: =咏博!L159 -> 1411.722 | L35: =咏博!M159 -> 265403.74 | M35: =咏博!M166 -> 872439.95 | N35: =M35+SUM(L35:L39) -> 1539929.8 | O35: =N35-Q35 -> 539929.78 | P35: =O35/Q35 -> 0.53992978 | Q35: 1000000 | R35: =IFERROR(L35-J35,0) -> 108789.25 | S35: =IFERROR((R35/J35),"") -> 0.69463085
D36: =咏博!E160 -> US | E36: =咏博!F160 -> 特斯拉 | F36: =咏博!G160 -> TSLA | G36: =咏博!H160 -> 持有 | H36: =咏博!I160 -> 68 | I36: =咏博!J160 -> 859.0335 | J36: =咏博!K160 -> 58414.278 | K36: =咏博!L160 -> 3753.36 | L36: =咏博!M160 -> 255228.48 | R36: =IFERROR(L36-J36,0) -> 196814.2 | S36: =IFERROR((R36/J36),"") -> 3.3692825
D37: =咏博!E161 -> US | E37: =咏博!F161 -> 台积电 | F37: =咏博!G161 -> TSM | G37: =咏博!H161 -> 持有 | H37: =咏博!I161 -> 50 | I37: =咏博!J161 -> 2243.514 | J37: =咏博!K161 -> 112175.7 | K37: =咏博!L161 -> 2253.81 | L37: =咏博!M161 -> 112690.5 | R37: =IFERROR(L37-J37,0) -> 514.8 | S37: =IFERROR((R37/J37),"") -> 0.0045892292
D38: =咏博!E162 -> US | E38: =咏博!F162 -> 拼多多 | F38: =咏博!G162 -> PDD | G38: =咏博!H162 -> 持有 | H38: =咏博!I162 -> 40 | I38: =咏博!J162 -> 894.86387 | J38: =咏博!K162 -> 35794.555 | K38: =咏博!L162 -> 854.178 | L38: =咏博!M162 -> 34167.12
R39: =IFERROR(L39-J39,0) -> 0 | S39: =IFERROR((R39/J39),"")
C40: 周彩银 | D40: =彩银!E15 -> CN | E40: =彩银!F15 -> 中芯国际 | F40: =彩银!G15 -> 688981 | G40: =彩银!H15 -> 持有 | H40: =彩银!I15 -> 1000 | I40: =彩银!J15 -> 122.11 | J40: =彩银!K15 -> 122110 | K40: =彩银!L15 -> 113.63 | L40: =彩银!M15 -> 113630 | M40: =彩银!M23 -> 406074.4 | N40: =M40+SUM(L40:L44) -> 1027050.4 | O40: =N40-Q40 -> 27050.4 | P40: =O40/Q40 -> 0.0270504 | Q40: 1000000 | R40: =IFERROR(L40-J40,0) -> -8480 | S40: =IFERROR((R40/J40),"") -> -0.069445582
D41: =彩银!E16 -> US | E41: =彩银!F16 -> 特斯拉 | F41: =彩银!G16 -> TSLA | G41: =彩银!H16 -> 持有 | H41: =彩银!I16 -> 100 | I41: =彩银!J16 -> 3350.256 | J41: =彩银!K16 -> 335025.6 | K41: =彩银!L16 -> 3753.36 | L41: =彩银!M16 -> 375336 | R41: =IFERROR(L41-J41,0) -> 40310.4 | S41: =IFERROR((R41/J41),"") -> 0.12032036
D42: =彩银!E17 -> CN | E42: =彩银!F17 -> 比亚迪 | F42: =彩银!G17 -> 002594 | G42: =彩银!H17 -> 持有 | H42: =彩银!I17 -> 1000 | I42: =彩银!J17 -> 98.37 | J42: =彩银!K17 -> 98370 | K42: =彩银!L17 -> 94.23 | L42: =彩银!M17 -> 94230 | R42: =IFERROR(L42-J42,0) -> -4140 | S42: =IFERROR((R42/J42),"") -> -0.042086002
D43: =彩银!E18 -> CN | E43: =彩银!F18 -> 海天味业 | F43: =彩银!G18 -> 603288 | G43: =彩银!H18 -> 持有 | H43: =彩银!I18 -> 1000 | I43: =彩银!J18 -> 38.42 | J43: =彩银!K18 -> 38420 | K43: =彩银!L18 -> 37.78 | L43: =彩银!M18 -> 37780 | R43: =IFERROR(L43-J43,0) -> -640 | S43: =IFERROR((R43/J43),"") -> -0.016657991
R44: =IFERROR(L44-J44,0) -> 0 | S44: =IFERROR((R44/J44),"")
C45: 邹俊峰 | D45: =俊峰!E82 -> CN | E45: =俊峰!F82 -> 消费50ETF | F45: =俊峰!G82 -> 515650 | G45: =俊峰!H82 -> 持有 | H45: =俊峰!I82 -> 110000 | I45: =俊峰!J82 -> 1.048 | J45: =俊峰!K82 -> 115280 | K45: =俊峰!L82 -> 1.204 | L45: =俊峰!M82 -> 132440 | M45: =俊峰!M91 -> 294498.53 | N45: =M45+SUM(L45:L48) -> 877718.53 | O45: =N45-Q45 -> -122281.47 | P45: =O45/Q45 -> -0.12228147 | Q45: 1000000 | R45: =IFERROR(L45-J45,0) -> 17160 | S45: =IFERROR((R45/J45),"") -> 0.14885496
